Workbook

Sheet MATERIAS PRIMAS
A1: CÓDIGO | B1: DESCRIPCIÓN | C1: CATIDAD | D1: % | E1: SEP - COP / Kg | F1: SEP - COP / APP | G1: AGO - COP / Kg | H1: AGO - COP / APP | I1: %
A2: MPPC077 | B2: TAROMA HAM. BOLSA X 5 KILOS | C2: 0.00091049995 | D2: =(C2*100)/#REF! -> #REF! | E2: 70021 | F2: =E2*C2 -> 63.754117 | G2: 65950 | H2: =G2*C2 -> 60.047472 | I2: =((E2/G2)*100)-100 -> 6.1728582
A3: MPCC026 | B3: TOCINO | C3: 0.032673256 | D3: 24.024453 | E3: 7029 | F3: =E3*C3 -> 229.66032 | G3: 6648 | H3: =G3*C3 -> 217.21181 | I3: =((E3/G3)*100)-100 -> 5.7310469
A4: MPPS102 | B4: REACTYNSH2 TRASGLUTAMINASA BOLSA X 1 KG | C4: 8.9915526e-05 | D4: =(C4*100)/#REF! -> #REF! | E4: 153185 | F4: =E4*C4 -> 13.77371 | G4: 145309 | H4: =G4*C4 -> 13.065535 | I4: =((E4/G4)*100)-100 -> 5.4201736
A5: MPPD172 | B5: MEZCLA DE FOSFATOS (CARFOSEL 996). SACO X 25 KILOS. | C5: 0.0011469276 | D5: =(C5*100)/#REF! -> #REF! | E5: 16795 | F5: =E5*C5 -> 19.26265 | G5: 16110 | H5: =G5*C5 -> 18.477004 | I5: =((E5/G5)*100)-100 -> 4.2520174
A6: MPPA144 | B6: ALMIDON DE PAPA SACO X 25 KILOS . | C6: 0.056625423 | D6: =(C6*100)/#REF! -> #REF! | E6: 5975 | F6: =E6*C6 -> 338.3369 | G6: 5761 | H6: =G6*C6 -> 326.21906 | I6: =((E6/G6)*100)-100 -> 3.7146329
A7: MPPD160 | B7: MEZCLA DE FOSFATOS (CARNAL 961). SACO X 25 KILOS. | C7: 0.00072081065 | D7: =(C7*100)/#REF! -> #REF! | E7: 21400 | F7: =E7*C7 -> 15.425348 | G7: 20650 | H7: 14.88474 | I7: =((E7/G7)*100)-100 -> 3.6319613
A8: MPCP037 | B8: PIEL DE POLLO NACIONAL | C8: 0.11336516 | D8: 11.336516 | E8: 3160 | F8: =E8*C8 -> 358.23389 | G8: 3067 | H8: =G8*C8 -> 347.69093 | I8: =((E8/G8)*100)-100 -> 3.0322791
A9: MPPA154 | B9: PROTEÍNA DE SOYA AL 70%. WILCON SJ. SACO X 20 KILOS | C9: 0.007863389 | D9: =(C9*100)/#REF! -> #REF! | E9: 16084 | F9: =E9*C9 -> 126.47475 | G9: 15638 | H9: 122.96768 | I9: =((E9/G9)*100)-100 -> 2.8520271
A10: MPPA168 | B10: PROTEÍNA COLAGÉNICA COLLAPRO P -950. SACO X 12,5 KILOS. | C10: 0.0003308756 | D10: =(C10*100)/#REF! -> #REF! | E10: 33158 | F10: =E10*C10 -> 10.971173 | G10: 32239 | H10: =G10*C10 -> 10.667098 | I10: =((E10/G10)*100)-100 -> 2.8505847
A11: MPPO142 | B11: COLOR NATURAL HEMOGLOBINA. I RED. BOLSA X 1 KILO. | C11: 8.9720613e-05 | D11: 0.065971039 | E11: 51477 | F11: =E11*C11 -> 4.618548 | G11: 50051 | H11: =G11*C11 -> 4.4906064 | I11: =((E11/G11)*100)-100 -> 2.8490939
A12: MPPH147 | B12: HUMO TRUSMOKE OIL EX. GARRAFA X 20 KG | C12: 0.00049154041 | D12: =(C12*100)/#REF! -> #REF! | E12: 40689 | F12: =E12*C12 -> 20.000288 | G12: 39563 | H12: =G12*C12 -> 19.446813 | I12: =((E12/G12)*100)-100 -> 2.8460936
A13: 30017 | B13: SALCHICHÓN AUTÉNTICO X 225 GRAMOS | C13: 1 | D13: =(C13*100)/#REF! -> #REF! | E13: 1385 | F13: =E13*C13 -> 1385 | G13: 1347 | H13: =G13*C13 -> 1347 | I13: =((E13/G13)*100)-100 -> 2.8210839
A14: MPPA122 | B14: PROTEÍNA DE SOYA AL 70%. ARCON T (Hojuelas). SACO X 11.34 KILOS | C14: 0.010857716 | D14: =(C14*100)/#REF! -> #REF! | E14: 16680 | F14: =E14*C14 -> 181.1067 | G14: 16262 | H14: =G14*C14 -> 176.56817 | I14: =((E14/G14)*100)-100 -> 2.5704095
A15: MIPS003 | B15: GRANULOS DE PROTEÍNA. CANASTA X 25 KILOS. | C15: 0.025856368 | D15: 4.9723784 | E15: 6260 | F15: =E15*C15 -> 161.86086 | G15: 6198 | H15: =G15*C15 -> 160.25777 | I15: =((E15/G15)*100)-100 -> 1.0003227
A16: 30018 | B16: SALCHICÓN DE POLLO X 225 GRAMOS | C16: 1 | D16: =(C16*100)/#REF! -> #REF! | E16: 1347 | F16: =E16*C16 -> 1347 | G16: 1336 | H16: =G16*C16 -> 1336 | I16: =((E16/G16)*100)-100 -> 0.82335329
A17: 10090O | B17: SALCHICHA CLASICA FAIZAN X 225 GRAMOS OFERTA | C17: 1 | D17: =(C17*100)/#REF! -> #REF! | E17: 2310 | F17: =E17*C17 -> 2310 | G17: 2293 | H17: =G17*C17 -> 2293 | I17: =((E17/G17)*100)-100 -> 0.74138683
A18: MPCP044 | B18: PASTA DE POLLO NACIONAL ALIPAQ | C18: 0.042469067 | D18: =(C18*100)/#REF! -> #REF! | E18: 5484 | F18: =E18*C18 -> 232.90036 | G18: 5453 | H18: =G18*C18 -> 231.58382 | I18: =((E18/G18)*100)-100 -> 0.56849441
A19: MPPN323 | B19: CONSERVANTE INBAC ACN/NA. CAJA X 25 KILOS. | C19: 0.0056625423 | D19: =(C19*100)/#REF! -> #REF! | E19: 59418 | F19: =E19*C19 -> 336.45694 | G19: 59227 | H19: =G19*C19 -> 335.37539 | I19: =((E19/G19)*100)-100 -> 0.32248805
A20: MPPS090 | B20: AZÚCAR REFINADA. SACO X 50 KILOS. | C20: 0.0030528513 | D20: =(C20*100)/#REF! -> #REF! | E20: 4915 | F20: =E20*C20 -> 15.004764 | G20: 4908 | H20: =G20*C20 -> 14.983394 | I20: =((E20/G20)*100)-100 -> 0.14262429
A21: MPPO135 | B21: COLOR NATURAL NARANJA LIQUIDO RA 40 - 3 9827 AF. GALÓN x 4 KILOS. | C21: 0.00017645054 | D21: 0.12974304 | E21: 53618 | F21: =E21*C21 -> 9.460925 | G21: 53617 | H21: =G21*C21 -> 9.4607485 | I21: =((E21/G21)*100)-100 -> 0.0018650801
A22: MPPC109 | B22: CONDIMENTO AJIAROMA M - C100. BOLSA X 1 KILO. | C22: 0.0057677009 | D22: 0.57677009 | E22: 62000 | F22: =E22*C22 -> 357.59745 | G22: 62000 | H22: =G22*C22 -> 357.59745 | I22: =((E22/G22)*100)-100 -> 0
A23: MPII311 | B23: AGUA POTABLE. | C23: 0.13988295 | D23: 26.900567 | E23: 7 | F23: =E23*C23 -> 0.97918065 | G23: 7 | H23: =G23*C23 -> 0.97918065 | I23: =((E23/G23)*100)-100 -> 0
A24: MPPS104 | B24: AJO MOLIDO DESHIDRATADO B. 1. CAJA X 20 KILOS. (LA CAMPANA) | C24: 0.00013572423 | D24: =(C24*100)/#REF! -> #REF! | E24: 30713 | F24: =E24*C24 -> 4.1684982 | G24: 30713 | H24: =G24*C24 -> 4.1684982 | I24: =((E24/G24)*100)-100 -> 0
B25: APANADO | C25: 0.0792 | D25: 12 | E25: 7900 | F25: 625.68 | G25: 7900 | H25: 625.68 | I25: 0
A26: MPPC120 | B26: AROMA SALCHICHON TRADICIONAL 84987B. GARRAFA X 5 KILOS | C26: 0.0038752757 | D26: =(C26*100)/#REF! -> #REF! | E26: 35100 | F26: =E26*C26 -> 136.02218 | G26: 35100 | H26: =G26*C26 -> 136.02218 | I26: =((E26/G26)*100)-100 -> 0
A27: MPPD168 | B27: CARRAGENINA CEAMGEL M 9396. SACO X 25 KILOS. | C27: 0.0015825356 | D27: =(C27*100)/#REF! -> #REF! | E27: 62980 | F27: =E27*C27 -> 99.668094 | G27: 62980 | H27: =G27*C27 -> 99.668094 | I27: =((E27/G27)*100)-100 -> 0
A28: MPPS153 | B28: CEBOLLA EN POLVO B.1. CAJA X 20 KILOS. (LA CAMPANA) | C28: 0.00051875753 | D28: =(C28*100)/#REF! -> #REF! | E28: 24619 | F28: =E28*C28 -> 12.771292 | G28: 24619 | H28: =G28*C28 -> 12.771292 | I28: =((E28/G28)*100)-100 -> 0
A29: MPLO211 | B29: COLOR CARAMELO. GARRAFA X 20 KILOS. | C29: 0.0022921844 | D29: =(C29*100)/#REF! -> #REF! | E29: 4561 | F29: =E29*C29 -> 10.454653 | G29: 4561 | H29: =G29*C29 -> 10.454653 | I29: =((E29/G29)*100)-100 -> 0
A30: MPPO134 | B30: COLOR LOY.(NARAN. LIQ. A10-1). TARRO X 1 KILO. | C30: 0.00023177825 | D30: 0.17042518 | E30: 39122 | F30: =E30*C30 -> 9.0676287 | G30: 39122 | H30: =G30*C30 -> 9.0676287 | I30: =((E30/G30)*100)-100 -> 0
A31: MPLO215 | B31: COLOR NATURAL NARANJA PR801 WD. GARRAFA X 10 KILOS. | C31: 9.0600677e-05 | D31: =(C31*100)/#REF! -> #REF! | E31: 169210 | F31: =E31*C31 -> 15.33054 | G31: 169210 | H31: =G31*C31 -> 15.33054 | I31: =((E31/G31)*100)-100 -> 0
A32: MPLO214 | B32: COLOR NATURAL ROJO AC305RWS. GARRAFA X 4 KILOS. | C32: 0.00045300338 | D32: =(C32*100)/#REF! -> #REF! | E32: 121899 | F32: =E32*C32 -> 55.220659 | G32: 121899 | H32: =G32*C32 -> 55.220659 | I32: =((E32/G32)*100)-100 -> 0
A33: MPPS157 | B33: COMINO MOLIDO B.1. BOLSA X 1 KILO. (LA CAMPANA) | C33: 0.00011389446 | D33: =(C33*100)/#REF! -> #REF! | E33: 32511 | F33: =E33*C33 -> 3.7028227 | G33: 32511 | H33: =G33*C33 -> 3.7028227 | I33: =((E33/G33)*100)-100 -> 0
A34: MPPS152 | B34: DEXTROSA. BOLSA X 1 KILO. | C34: 0.0033975254 | D34: =(C34*100)/#REF! -> #REF! | E34: 10972 | F34: =E34*C34 -> 37.277648 | G34: 10972 | H34: =G34*C34 -> 37.277648 | I34: =((E34/G34)*100)-100 -> 0
A35: MPCC012 | B35: EMULSION (Piel de Cerdo) - Tocino Partes Magras | C35: 0.0965038 | D35: =(C35*100)/#REF! -> #REF! | E35: 1500 | F35: =E35*C35 -> 144.7557 | G35: 1500 | H35: =G35*C35 -> 144.7557 | I35: =((E35/G35)*100)-100 -> 0
A36: MPCC012 | B36: EMULSIÓN ABLANDADA. Disco 6 mm | C36: 0.038784552 | D36: 7.4585677 | E36: 1500 | F36: =E36*C36 -> 58.176828 | G36: 1500 | H36: =G36*C36 -> 58.176828 | I36: =((E36/G36)*100)-100 -> 0
A37: MPPO140 | B37: ENTURBIANTE EN POLVO DPA X 1 KILO | C37: 0.003049589 | D37: 0.3049589 | E37: 50633 | F37: =E37*C37 -> 154.40984 | G37: 50633 | H37: =G37*C37 -> 154.40984 | I37: =((E37/G37)*100)-100 -> 0
A38: MPPD161 | B38: ERITORBATO DE SODIO. CAJA X 25 KILOS. | C38: 0.00056625423 | D38: =(C38*100)/#REF! -> #REF! | E38: 26800 | F38: =E38*C38 -> 15.175613 | G38: 26800 | H38: =G38*C38 -> 15.175613 | I38: =((E38/G38)*100)-100 -> 0
A39: MPPA134 | B39: EXTRACTO PROTEICO LC 300. Saco x 25 kg. | C39: 0.0090600677 | D39: =(C39*100)/#REF! -> #REF! | E39: 19616 | F39: =E39*C39 -> 177.72229 | G39: 19616 | H39: =G39*C39 -> 177.72229 | I39: =((E39/G39)*100)-100 -> 0
A40: MPCC019 | B40: GRASA EMPELLA | C40: 0.028673191 | D40: =(C40*100)/#REF! -> #REF! | E40: 4000 | F40: =E40*C40 -> 114.69276 | G40: 4000 | H40: =G40*C40 -> 114.69276 | I40: =((E40/G40)*100)-100 -> 0
A41: MPII310 | B41: HIELO EN ESCAMAS (BOLSA X 20 KILOS) | C41: 0.017749406 | D41: =(C41*100)/#REF! -> #REF! | E41: 310 | F41: =E41*C41 -> 5.5023159 | G41: 310 | H41: =G41*C41 -> 5.5023159 | I41: =((E41/G41)*100)-100 -> 0
A42: MPPH141 | B42: HUMO CHARDEX EN POLVO X 18 KG | C42: 0.00013007142 | D42: =(C42*100)/#REF! -> #REF! | E42: 65000 | F42: =E42*C42 -> 8.4546424 | G42: 65000 | H42: =G42*C42 -> 8.4546424 | I42: =((E42/G42)*100)-100 -> 0
A43: MPPH142 | B43: HUMO SMOKE OIL. GARRAFA PLÁSTICA X 12 KG. | C43: 0.00029802383 | D43: =(C43*100)/#REF! -> #REF! | E43: 41100 | F43: =E43*C43 -> 12.248779 | G43: 41100 | H43: =G43*C43 -> 12.248779 | I43: =((E43/G43)*100)-100 -> 0
A44: MPPC117 | B44: MEZCLA LIQUIDA PARA SABORIZAR SALCHICHA MANGUERA. BOLSA X 8 KILOS | C44: 0.0032769361 | D44: =(C44*100)/#REF! -> #REF! | E44: 29877 | F44: =E44*C44 -> 97.905019 | G44: 29877 | H44: =G44*C44 -> 97.905019 | I44: =((E44/G44)*100)-100 -> 0
A45: MPPC112 | B45: MEZCLA LÍQUIDA PARA SABORIZAR SALCHICHA. BOLSA X 2.7 KILOS. CAJA X 24,3 KILOS | C45: 0.0035541949 | D45: =(C45*100)/#REF! -> #REF! | E45: 27308 | F45: =E45*C45 -> 97.057954 | G45: 27308 | H45: =G45*C45 -> 97.057954 | I45: =((E45/G45)*100)-100 -> 0
A46: MPPC122 | B46: MEZCLA SABOR MORTADELA DROP TECH | C46: 0.0010080202 | D46: =(C46*100)/#REF! -> #REF! | E46: 32870 | F46: =E46*C46 -> 33.133623 | G46: 32870 | H46: =C46*G46 -> 33.133623 | I46: =((E46/G46)*100)-100 -> 0
A47: MPCC036 | B47: PAPADA DE CERDO. Disco 6mm. | C47: 0.018616585 | D47: 3.5801125 | E47: 12000 | F47: =E47*C47 -> 223.39902 | G47: 12000 | H47: =G47*C47 -> 223.39902 | I47: =((E47/G47)*100)-100 -> 0
A48: MPPS154 | B48: PIMIENTA MOLIDA BLANCA. BOLSA X 1 KILO. (TECNAS) | C48: 0.00066295412 | D48: 0.066295412 | E48: 69401 | F48: =E48*C48 -> 46.009679 | G48: 69401 | H48: =G48*C48 -> 46.009679 | I48: =((E48/G48)*100)-100 -> 0
A49: MPPS095 | B49: PIMIENTA NEGRA MOLIDA. BOLSA X 1 KILO. (TECNAS) | C49: 0.00038846494 | D49: =(C49*100)/#REF! -> #REF! | E49: 43120 | F49: =E49*C49 -> 16.750608 | G49: 43120 | H49: =G49*C49 -> 16.750608 | I49: =((E49/G49)*100)-100 -> 0
A50: MPPC075 | B50: PREPARADO SABOR CERVECERO NEO. BOLSA X 7,03 KILOS. | C50: 0.0072708106 | D50: 1.3982328 | E50: 15516 | F50: =E50*C50 -> 112.8139 | G50: 15516 | H50: =G50*C50 -> 112.8139 | I50: =((E50/G50)*100)-100 -> 0
A51: MPPC121 | B51: PREPARADO SABOR CERVECERO PREMIUM SV | C51: 0.0020955455 | D51: =(C51*100)/#REF! -> #REF! | E51: 21000 | F51: =E51*C51 -> 44.006455 | G51: 21000 | H51: =G51*C51 -> 44.006455 | I51: =((E51/G51)*100)-100 -> 0
A52: MPPC102 | B52: PREPARADO SABOR CHORIZO CERDO SEVILLA. PAQUETE X 4,8 KILOS | C52: 0.0056947229 | D52: =(C52*100)/#REF! -> #REF! | E52: 37500 | F52: =E52*C52 -> 213.55211 | G52: 37500 | H52: =G52*C52 -> 213.55211 | I52: =((E52/G52)*100)-100 -> 0
A53: MPPC097 | B53: PREPARADO SABOR CHORIZO TERNERA SEVILLA X 3,83 KG | C53: 0.0025772246 | D53: 1.8950181 | E53: 36457 | F53: =E53*C53 -> 93.957877 | G53: 36457 | H53: =G53*C53 -> 93.957877 | I53: =((E53/G53)*100)-100 -> 0
A54: MPPC076 | B54: PREPARADO SABOR JAMON CALIFORNIAX 1 KG | C54: 0.0011193788 | D54: =(C54*100)/#REF! -> #REF! | E54: 8214 | F54: =E54*C54 -> 9.1945776 | G54: 8214 | H54: =G54*C54 -> 9.1945776 | I54: =((E54/G54)*100)-100 -> 0
A55: MPLS190 | B55: PREPARADO SABOR JAMÓN T 3391 x 4 KG LÍQUIDO | C55: 0.00177285 | D55: =(C55*100)/#REF! -> #REF! | E55: 21534 | F55: =E55*C55 -> 38.176552 | G55: 21534 | H55: =G55*C55 -> 38.176552 | I55: =((E55/G55)*100)-100 -> 0
A56: MPLR191 | B56: PVH LIQUIDA - M - 1222. CANECA X 70 KILOS. | C56: 0.0031592843 | D56: =(C56*100)/#REF! -> #REF! | E56: 10412 | F56: =E56*C56 -> 32.894469 | G56: 10412 | H56: =G56*C56 -> 32.894469 | I56: =((E56/G56)*100)-100 -> 0
A57: MPPK174 | B57: SABOR CERDO COCIDO TECNAS X 1 Kg. | C57: 0.00028473614 | D57: =(C57*100)/#REF! -> #REF! | E57: 72924 | F57: =E57*C57 -> 20.764099 | G57: 72924 | H57: =G57*C57 -> 20.764099 | I57: =((E57/G57)*100)-100 -> 0
A58: MPPC110 | B58: SABOR ITALIAN MORTADELA FLAVOUR SACO X 15 KILOS | C58: 0.00140112 | D58: =(C58*100)/#REF! -> #REF! | E58: 64256 | F58: =E58*C58 -> 90.030367 | G58: 64256 | H58: =C58*G58 -> 90.030367 | I58: =((E58/G58)*100)-100 -> 0
A59: MPPC119 | B59: SABORIZANTE A POLLO SV. BOLSA X 1 KILO | C59: 0.0033147706 | D59: 0.33147706 | E59: 46385 | F59: =E59*C59 -> 153.75564 | G59: 46385 | H59: =G59*C59 -> 153.75564 | I59: =((E59/G59)*100)-100 -> 0
A60: MPPS150 | B60: SAL YODADA REFISAL. SACO X 25 KILOS. | C60: 0.006464092 | D60: 1.2430946 | E60: 878 | F60: =E60*C60 -> 5.6754727 | G60: 878 | H60: =G60*C60 -> 5.6754727 | I60: =((E60/G60)*100)-100 -> 0
A61: MPPC094 | B61: ADITIVO BURGER MEAT 80-B NATUR. BOLSA X 5 KILOS. | C61: 0.014476954 | D61: =(C61*100)/#REF! -> #REF! | E61: 11052 | F61: =E61*C61 -> 159.9993 | G61: 11052 | H61: =G61*C61 -> 159.9993 | I61: =((E61/G61)*100)-100 -> 0
A62: MPPV192 | B62: BATIDO COMPLETO #1 JOLI. SACO X 25 KILOS. | C62: 0.33333333 | D62: 33.333333 | E62: 5320 | F62: 1773.3333 | G62: 5320 | H62: =G62*C62 -> 1773.3333 | I62: =((E62/G62)*100)-100 -> 0
A63: MPPC115 | B63: CONDIMENTO AJIAROMA M - M100. BOLSA X 1 KILO | C63: 0.00056364282 | D63: =(C63*100)/#REF! -> #REF! | E63: 65850 | F63: =E63*C63 -> 37.11588 | G63: 65857 | H63: =G63*C63 -> 37.119825 | I63: =((E63/G63)*100)-100 -> -0.01062909
A64: 20018O | B64: MORTADELA SELECCIONADA X 225 GRAMOS OFERTA | C64: 1 | D64: =(C64*100)/#REF! -> #REF! | E64: 2094 | F64: =E64*C64 -> 2094 | G64: 2095 | H64: =G64*C64 -> 2095 | I64: =((E64/G64)*100)-100 -> -0.047732697
A65: MPPA151 | B65: PLASMA APROPORK. SACO X 20 KILOS. | C65: 0.0062287965 | D65: =(C65*100)/#REF! -> #REF! | E65: 28967 | F65: =E65*C65 -> 180.42955 | G65: 29262 | H65: =G65*C65 -> 182.26704 | I65: =((E65/G65)*100)-100 -> -1.0081334
A66: MPPS151 | B66: SAL CURANTE AL 12 %. SACO X 25 KILOS. | C66: 0.00086618832 | D66: 0.16657468 | E66: 2500 | F66: =E66*C66 -> 2.1654708 | G66: 2554 | H66: =G66*C66 -> 2.212245 | I66: =((E66/G66)*100)-100 -> -2.1143305
A67: MPCP031 | B67: PASTA DE POLLO IMPORTADA TYSON USA | C67: 0.10068113 | D67: =(C67*100)/#REF! -> #REF! | E67: 6993 | F67: =E67*C67 -> 704.06312 | G67: 7255 | H67: =G67*C67 -> 730.44157 | I67: =((E67/G67)*100)-100 -> -3.6113025
A68: MPCC020 | B68: PIERNA DE CERDO | C68: 0.054116945 | D68: 5.4116945 | E68: 17600 | F68: =E68*C68 -> 952.45823 | G68: 19147.5 | H68: =G68*C68 -> 1036.2042 | I68: =((E68/G68)*100)-100 -> -8.081995
A69: MPCC010 | B69: BRAZUELO DE CERDO. | C69: 0.056374452 | D69: 41.451803 | E69: 16500 | F69: =E69*C69 -> 930.17845 | G69: 18045 | H69: =G69*C69 -> 1017.277 | I69: =((E69/G69)*100)-100 -> -8.5619285
B70: PP BATIDO PREPARADO | C70: 0.0924 | D70: 14 | E70: 1778 | F70: 164.2872 | G70: 2240 | H70: 206.976 | I70: -20.625
A71: MPCP058 | B71: CARNE OSCURA | C71: 0.054116945 | D71: 5.4116945 | E71: 6800 | F71: =E71*C71 -> 367.99523 | G71: 15000 | H71: =G71*C71 -> 811.75418 | I71: =((E71/G71)*100)-100 -> -54.666667
A72: - | B72: REPELE (CHARQUEADO) | C72: 0.096513028 | D72: =(C72*100)/#REF! -> #REF! | E72: 1600 | F72: =E72*C72 -> 154.42085 | G72: 3719.25 | H72: =G72*C72 -> 358.95608 | I72: =((E72/G72)*100)-100 -> -56.980574

Sheet MATERIAL DE EMPAQUE
A1: CÓDIGO | B1: DESCRIPCIÓN | C1: CATIDAD | D1: SEP - COP / Kg | E1: SEP - COP / APP | F1: AGO - COP / Kg | G1: AGO - COP / APP | H1: %
A2: MPEP405 | B2: Grapas Poly-Clip GMBH 15-08 5 x 1,5 Carrete x 5,500 unidades | C2: 2 | D2: 27 | E2: =D2*C2 -> 54 | F2: 22 | G2: 44 | H2: =((D2/F2)*100)-100 -> 22.727273
A3: MPEP434 | B3: Grapas Poly-Clip GMBH R-ID M 07-150 Carrete x 6,800 unidades | C3: 2 | D3: 27 | E3: =D3*C3 -> 54 | F3: 22 | G3: =F3*C3 -> 44 | H3: =((D3/F3)*100)-100 -> 22.727273
A4: MPES972 | B4: Caja Koba Salchichón Tradicional Viandé x 500 gramos (15 unidades) | C4: 0.046 | D4: 1624 | E4: =D4*C4 -> 74.704 | F4: 1353 | G4: =F4*C4 -> 62.238 | H4: =((D4/F4)*100)-100 -> 20.029564
A5: MPES974 | B5: Caja Koba Salchicha Tradicional Viandé x 450 gramos. (22 unidades) | C5: 0.045 | D5: 1816 | E5: =D5*C5 -> 81.72 | F5: 1513 | G5: =F5*C5 -> 68.085 | H5: =((D5/F5)*100)-100 -> 20.026438
A6: MPES202 | B6: Lámina Inferior Sudpack GVP 130-323 mm (5.0 mils). 1 Rollo x 350 metros | C6: 0.04 | D6: 1350 | E6: =D6*C6 -> 54 | F6: 1125 | G6: =F6*C6 -> 45 | H6: =((D6/F6)*100)-100 -> 20
A7: MPES186 | B7: Lámina Inferior Sudpack GVP 130-423 mm (5.0 mils). 1 Rollo x 350 metros | C7: 0.14 | D7: 1464 | E7: =D7*C7 -> 204.96 | F7: 1323 | G7: =F7*C7 -> 185.22 | H7: =((D7/F7)*100)-100 -> 10.657596
A8: MPES251 | B8: Lámina Superior Impresa Mega Combo Faizán x 900 gramos | C8: 0.0109 | D8: 26300 | E8: =D8*C8 -> 286.67 | F8: 23900 | G8: =F8*C8 -> 260.51 | H8: =((D8/F8)*100)-100 -> 10.041841
A9: MPEP969 | B9: Clips HC25-3218T. Carrete x 2,400 unidades. | C9: 0.091 | D9: 57 | E9: =D9*C9 -> 5.187 | F9: 52 | G9: =F9*C9 -> 4.732 | H9: =((D9/F9)*100)-100 -> 9.6153846
A10: MPEP424 | B10: Fibrosa FVP CLS 140 B5 4 H5 Natural Corrugado. (Viandé) | C10: 0.0575 | D10: 4053 | E10: =D10*C10 -> 233.0475 | F10: 3712 | G10: =F10*C10 -> 213.44 | H10: =((D10/F10)*100)-100 -> 9.1864224
A11: MPES994 | B11: Tubular Salchichón Tradicional x 750 Gramos Cal 44 | C11: 0.5 | D11: 606 | E11: =D11*C11 -> 303 | F11: 565 | G11: =F11*C11 -> 282.5 | H11: =((D11/F11)*100)-100 -> 7.2566372
A12: MPEP380 | B12: Funda Celulosa Nojax 20 x 100 Tubo x 30,48 metros. Caja x 200 tubos x 6,096 metros | C12: 9 | D12: 204 | E12: =D12*C12 -> 1836 | F12: 192 | G12: =F12*C12 -> 1728 | H12: =((D12/F12)*100)-100 -> 6.25
A13: MPES207 | B13: Tubular Salchichón Pollo Bakel x 225 Gramos. Cal 40 | C13: 0.22 | D13: 512 | E13: =D13*C13 -> 112.64 | F13: 491 | G13: =F13*C13 -> 108.02 | H13: =((D13/F13)*100)-100 -> 4.2769857
A14: MPES208 | B14: Tubular Salchichón Tradicional Viande x 500 Gramos. Cal 44 | C14: 0.4 | D14: 522 | E14: =D14*C14 -> 208.8 | F14: 504 | G14: =F14*C14 -> 201.6 | H14: =((D14/F14)*100)-100 -> 3.5714286
A15: MPES133 | B15: Tubular Salchichón Cervecero 1.500 gramos | C15: 0.7 | D15: 589 | E15: =D15*C15 -> 412.3 | F15: 569 | G15: =C15*F15 -> 398.3 | H15: =((D15/F15)*100)-100 -> 3.5149385
A16: MPES182 | B16: Lámina Superior Mortadela Seleccionada Viandé x 225 gramos x 17 unidades. Ancho = 415 mm. (Pet / coextrusión HBA 70 micras). | C16: 0.073 | D16: 908 | E16: =D16*C16 -> 66.284 | F16: 878 | G16: 64.094 | H16: =((D16/F16)*100)-100 -> 3.4168565
A17: MPES183 | B17: Lámina Superior Impresa Salchicha Viandé x 225 gramos x 8 unidades. Ancho = 415 mm. (Pet / coextrusión HBA 70 micras). | C17: 0.073 | D17: 908 | E17: =D17*C17 -> 66.284 | F17: 880 | G17: =F17*C17 -> 64.24 | H17: =((D17/F17)*100)-100 -> 3.1818182
A18: MPEP410 | B18: Funda Celulosa 23 USA x 4 CE S (Cartón x 7.680 metros x 300 tubos,C/tubo x 25.6 metros. 6 caddy x 50 tubos) | C18: 1.76 | D18: 243 | E18: =D18*C18 -> 427.68 | F18: 236 | G18: =F18*C18 -> 415.36 | H18: =((D18/F18)*100)-100 -> 2.9661017
A19: MPES100 | B19: Tubular Salchichón Cervecero x 750 gramos | C19: 0.35 | D19: 606 | E19: =D19*C19 -> 212.1 | F19: 589 | G19: =F19*C19 -> 206.15 | H19: =((D19/F19)*100)-100 -> 2.8862479
A20: MPES106 | B20: Tubular Salchichón Cervecero x 500 gramos | C20: 0.3 | D20: 686 | E20: =D20*C20 -> 205.8 | F20: 667 | G20: 192.9 | H20: =((D20/F20)*100)-100 -> 2.8485757
A21: MPES462 | B21: Lámina Inferior Modflex 180 micras (280m/rollo). 7 mils - 423 mm | C21: 0.14 | D21: 2388 | E21: =D21*C21 -> 334.32 | F21: 2322 | G21: =F21*C21 -> 325.08 | H21: =((D21/F21)*100)-100 -> 2.8423773
A22: MPES161 | B22: Tubular Salchichón Pollo X 225 gramos Cal 40 | C22: 0.22 | D22: 581 | E22: =D22*C22 -> 127.82 | F22: 565 | G22: =F22*C22 -> 124.3 | H22: =((D22/F22)*100)-100 -> 2.8318584
A23: MPES162 | B23: Tubular Salchichón Auténtico x 225 gramos. Cal 40 | C23: 0.22 | D23: 581 | E23: =D23*C23 -> 127.82 | F23: 565 | G23: =F23*C23 -> 124.3 | H23: =((D23/F23)*100)-100 -> 2.8318584
A24: MPEP355 | B24: Funda Celulosa 18 x 100 (Cartón x 9.144 metros x 300 tubos,C/tubo x 30.48 metros. 6 caddy x 50 tubos) | C24: 4.4 | D24: 222 | E24: =D24*C24 -> 976.8 | F24: 216 | G24: =F24*C24 -> 950.4 | H24: =((D24/F24)*100)-100 -> 2.7777778
A25: MPES155 | B25: Etiqueta Megasalchicha x 560 gramos x 6 unidades | C25: 1 | D25: 115 | E25: =D25*C25 -> 115 | F25: 112 | G25: =F25*C25 -> 112 | H25: =((D25/F25)*100)-100 -> 2.6785714
A26: MPES206 | B26: Tubular Salchichón Pollo Bakel x 500 Gramos. Cal 44 | C26: 0.4 | D26: 535 | E26: =D26*C26 -> 214 | F26: 522 | G26: 208.8 | H26: =((D26/F26)*100)-100 -> 2.4904215
A27: MPEP955 | B27: Polijax 20 X 110 Impresa. Tubo x 33.53 metros. Caja x 300 tubos x 10.058 metros | C27: 1.68 | D27: 255 | E27: =D27*C27 -> 428.4 | F27: 249 | G27: =F27*C27 -> 418.32 | H27: =((D27/F27)*100)-100 -> 2.4096386
A28: MPEP973 | B28: Funda Celulosa 20 x 100 CE FP CLR | C28: 0.88 | D28: 225 | E28: =D28*C28 -> 198 | F28: 220 | G28: =F28*C28 -> 193.6 | H28: =((D28/F28)*100)-100 -> 2.2727273
A29: MPEP431 | B29: Fibrosa FVP CLS 95 B3 4 H3 Natural Corrugado. (Mortadela) | C29: 0.036 | D29: 3800 | E29: =D29*C29 -> 136.8 | F29: 3716 | G29: =F29*C29 -> 133.776 | H29: =((D29/F29)*100)-100 -> 2.2604952
A30: MPEP354 | B30: Funda Colageno NDX 26/60 (cartón x 4,718 metros x 258 tubos, C/tubo x 18.29 metros. 6 Caddy x 43 tubos C/U) | C30: 0.1818 | D30: 598 | E30: =D30*C30 -> 108.7164 | F30: 585 | G30: =F30*C30 -> 106.353 | H30: =((D30/F30)*100)-100 -> 2.2222222
A31: MPES964 | B31: Lámina Inferior Sudpack GVA 200 BT 323 MM (8.MILS) 1 Rollo x 300 metros | C31: 0.146 | D31: 2219 | E31: =D31*C31 -> 323.974 | F31: 2173 | G31: =F31*C31 -> 317.258 | H31: =((D31/F31)*100)-100 -> 2.1168891
A32: MPEP968 | B32: Fibrosa FVP CLS 95 B3 4 H3 Natural Corrugada x 25 metros. | C32: 0.036 | D32: 3800 | E32: =D32*C32 -> 136.8 | F32: 3742 | G32: =F32*C32 -> 134.712 | H32: =((D32/F32)*100)-100 -> 1.5499733
A33: MPES209 | B33: Tubular Salchichón Cervecero Viande x 225 Gramos. Cal 40 | C33: 0.22 | D33: 474 | E33: =D33*C33 -> 104.28 | F33: 470 | G33: =F33*C33 -> 103.4 | H33: =((D33/F33)*100)-100 -> 0.85106383
A34: MPES190 | B34: Lámina Superior Impresa Salchicha x 225 gramos x 9 unidades. Sin Código. Ancho = 415 mm. (Pet / coextrusión HBA 70 micras). | C34: 0.073 | D34: 1519 | E34: =D34*C34 -> 110.887 | F34: 1510 | G34: =F34*C34 -> 110.23 | H34: =((D34/F34)*100)-100 -> 0.59602649
A35: MPEP352 | B35: Multiflex 180 mm. Transparente sin impresión. Para Milanesa. | C35: 0.15 | D35: 795 | E35: =D35*C35 -> 119.25 | F35: 795 | G35: =F35*C35 -> 119.25 | H35: =((D35/F35)*100)-100 -> 0
A36: MPEP418 | B36: Funda Colágeno NDX F 25/50 Cierre de Bola x 258 Tubos | C36: 0.4545 | D36: 574 | E36: =D36*C36 -> 260.883 | F36: 574 | G36: =F36*C36 -> 260.883 | H36: =((D36/F36)*100)-100 -> 0
A37: MPEP956 | B37: Lazos Poly-Clip LTDA GSA22 Rollo x 3.500 unidades de Lazadas | C37: 1 | D37: 46 | E37: =D37*C37 -> 46 | F37: 46 | G37: =F37*C37 -> 46 | H37: =((D37/F37)*100)-100 -> 0
A38: MPEP963 | B38: FIBROSA T-SHIRR BTC CLR REG 1 1/2 x 150 35ST Smoke-E3 | C38: 0.03 | D38: 2510 | E38: =D38*C38 -> 75.3 | F38: 2510 | G38: =F38*C38 -> 75.3 | H38: =((D38/F38)*100)-100 -> 0
... A67: MPES959 | B67: Caja Hamburguesa x 2.700 gramos | C67: 1 | D67: 1022 | E67: =D67*C67 -> 1022 | F67: 1022 | G67: =F67*C67 -> 1022 | H67: =((D67/F67)*100)-100 -> 0
A68: MPES968 | B68: Caja Koba Salchichón de Pollo Brakel x 500 gramos (15 unidades) | C68: 0.046 | D68: 1624 | E68: =D68*C68 -> 74.704 | F68: 1624 | G68: 74.704 | H68: =((D68/F68)*100)-100 -> 0
A69: MPES969 | B69: Caja Koba Jamón de Cerdo Viandé x 300 gramos (32 unidades) | C69: 0.03125 | D69: 1624 | E69: =D69*C69 -> 50.75 | F69: 1624 | G69: =F69*C69 -> 50.75 | H69: =((D69/F69)*100)-100 -> 0
A70: MPES973 | B70: Caja Koba Super Combo Tradicional Viandé (9 unidades) | C70: 0.11 | D70: 1727 | E70: =D70*C70 -> 189.97 | F70: 1727 | G70: =F70*C70 -> 189.97 | H70: =((D70/F70)*100)-100 -> 0
A71: MPES985 | B71: Etiqueta Salchicha Perro Caliente x 480 gramos x 12 unidades | C71: 1 | D71: 114 | E71: =D71*C71 -> 114 | F71: 114 | G71: =F71*C71 -> 114 | H71: =((D71/F71)*100)-100 -> 0

Sheet MP OCT
B2: PRECIO MATERIAS PRIMAS - OCT 22
B4: GRUPO | C4: CÓDIGO | D4: DESCRIPCIÓN | E4: OCT - COP / UMB | F4: SEP - COP / UMB | G4: %
B5: AGUA POTABLE | C5: MPII311 | D5: AGUA POTABLE. | E5: 7 | F5: 7 | G5: =((E5/F5)*100)-100 -> 0
B6: AGUA POTABLE | C6: MPII310 | D6: HIELO EN ESCAMAS (BOLSA X 20 KILOS) | E6: 310 | F6: 310 | G6: =((E6/F6)*100)-100 -> 0
B7: ALMIDONES | C7: MPPA144 | D7: ALMIDON DE PAPA SACO X 25 KILOS . | E7: 6316.85 | F7: 5975 | G7: =((F7/E7)*100)-100 -> -5.4117163
B8: ANTIOXIDANTE | C8: MPPD161 | D8: ERITORBATO DE SODIO. CAJA X 25 KILOS. | E8: 26800 | F8: 26800 | G8: =((E8/F8)*100)-100 -> 0
B9: AROMAS Y SABORES | C9: MPPC077 | D9: TAROMA HAM. BOLSA X 5 KILOS | E9: 75475.71 | F9: 70021 | G9: =((F9/E9)*100)-100 -> -7.2271066
B10: AROMAS Y SABORES | C10: MPPC102 | D10: PREPARADO SABOR CHORIZO CERDO SEVILLA. PAQUETE X 4,8 KILOS | E10: 40125 | F10: 37500 | G10: =((F10/E10)*100)-100 -> -6.5420561
B11: AROMAS Y SABORES | C11: MPPC115 | D11: CONDIMENTO AJIAROMA M - M100. BOLSA X 1 KILO | E11: 65857 | F11: 65850 | G11: =((F11/E11)*100)-100 -> -0.01062909
B12: AROMAS Y SABORES | C12: MPPC094 | D12: ADITIVO BURGER MEAT 80-B NATUR. BOLSA X 5 KILOS. | E12: 11052 | F12: 11052 | G12: =((E12/F12)*100)-100 -> 0
B13: AROMAS Y SABORES | C13: MPPC120 | D13: AROMA SALCHICHON TRADICIONAL 84987B. GARRAFA X 5 KILOS | E13: 35100 | F13: 35100 | G13: =((E13/F13)*100)-100 -> 0
B14: AROMAS Y SABORES | C14: MPPC117 | D14: MEZCLA LIQUIDA PARA SABORIZAR SALCHICHA MANGUERA. BOLSA X 8 KILOS | E14: 29877 | F14: 29877 | G14: =((E14/F14)*100)-100 -> 0
B15: AROMAS Y SABORES | C15: MPPC112 | D15: MEZCLA LÍQUIDA PARA SABORIZAR SALCHICHA. BOLSA X 2.7 KILOS. CAJA X 24,3 KILOS | E15: 27308 | F15: 27308 | G15: =((E15/F15)*100)-100 -> 0
B16: AROMAS Y SABORES | C16: MPPC122 | D16: MEZCLA SABOR MORTADELA DROP TECH | E16: 32870 | F16: 32870 | G16: =((E16/F16)*100)-100 -> 0
B17: AROMAS Y SABORES | C17: MPPC075 | D17: PREPARADO SABOR CERVECERO NEO. BOLSA X 7,03 KILOS. | E17: 15516 | F17: 15516 | G17: =((E17/F17)*100)-100 -> 0
B18: AROMAS Y SABORES | C18: MPPC116 | D18: PREPARADO SABOR CERVECERO SV - GF. BOLSA X 6,55 KILOS | E18: 16071 | F18: 16071 | G18: =((E18/F18)*100)-100 -> 0
B19: AROMAS Y SABORES | C19: MPPC097 | D19: PREPARADO SABOR CHORIZO TERNERA SEVILLA X 3,83 KG | E19: 36457 | F19: 36457 | G19: =((E19/F19)*100)-100 -> 0
B20: AROMAS Y SABORES | C20: MPPC076 | D20: PREPARADO SABOR JAMON CALIFORNIAX 1 KG | E20: 8214 | F20: 8214 | G20: =((E20/F20)*100)-100 -> 0
B21: AROMAS Y SABORES | C21: MPLS190 | D21: PREPARADO SABOR JAMÓN T 3391 x 4 KG LÍQUIDO | E21: 21534 | F21: 21534 | G21: =((E21/F21)*100)-100 -> 0
B22: AROMAS Y SABORES | C22: MPPK174 | D22: SABOR CERDO COCIDO TECNAS X 1 Kg. | E22: 72924 | F22: 72924 | G22: =((E22/F22)*100)-100 -> 0
B23: AROMAS Y SABORES | C23: MPPC110 | D23: SABOR ITALIAN MORTADELA FLAVOUR SACO X 15 KILOS | E23: 64256 | F23: 64256 | G23: =((E23/F23)*100)-100 -> 0
B24: AROMAS Y SABORES | C24: MPPC119 | D24: SABORIZANTE A POLLO SV. BOLSA X 1 KILO | E24: 46385 | F24: 46385 | G24: =((E24/F24)*100)-100 -> 0
B25: AROMAS Y SABORES | C25: MPPC109 | D25: CONDIMENTO AJIAROMA M - C100. BOLSA X 1 KILO. | E25: 62000 | F25: 65857 | G25: =((F25/E25)*100)-100 -> 6.2209677
B26: AROMAS Y SABORES | C26: MPPC121 | D26: PREPARADO SABOR CERVECERO PREMIUM SV | E26: 16071 | F26: 21000 | G26: =((F26/E26)*100)-100 -> 30.670151
B27: BREADER | D27: APANADO | E27: 7900 | F27: 7900 | G27: =((E27/F27)*100)-100 -> 0
B28: CARNE DE CERDO | C28: MPCC034 | D28: PIERNA DE CERDO. Molienda x Disco Riñon | E28: 17600 | F28: 17440 | G28: =((F28/E28)*100)-100 -> -0.90909091
B29: CARNE DE CERDO | C29: MPCC010 | D29: BRAZUELO DE CERDO. | E29: 15045 | F29: 16500 | G29: =((F29/E29)*100)-100 -> 9.670987
B30: CARNE DE POLLO | C30: MPCP031 | D30: PASTA DE POLLO IMPORTADA | E30: 7012.5 | F30: 6993 | G30: =((F30/E30)*100)-100 -> -0.27807487
B31: CARNE DE POLLO | C31: MPCP058 | D31: CARNE OSCURA DE POLLO | E31: 6800 | F31: 6800 | G31: =((E31/F31)*100)-100 -> 0
B32: CARNE DE POLLO | C32: MPCP044 | D32: PASTA DE POLLO NACIONAL | E32: 5420 | F32: 5484 | G32: =((F32/E32)*100)-100 -> 1.1808118
B33: COLORANTES | C33: MPPO142 | D33: COLOR NATURAL HEMOGLOBINA. I RED. BOLSA X 1 KILO. | E33: 53429.29 | F33: 51477 | G33: =((F33/E33)*100)-100 -> -3.6539696
B34: COLORANTES | C34: MPLO211 | D34: COLOR CARAMELO. GARRAFA X 20 KILOS. | E34: 4561 | F34: 4561 | G34: =((E34/F34)*100)-100 -> 0
B35: COLORANTES | C35: MPPO134 | D35: COLOR LOY.(NARAN. LIQ. A10-1). TARRO X 1 KILO. | E35: 39122 | F35: 39122 | G35: =((E35/F35)*100)-100 -> 0
B36: COLORANTES | C36: MPLO215 | D36: COLOR NATURAL NARANJA PR801 WD. GARRAFA X 10 KILOS. | E36: 169210 | F36: 169210 | G36: =((E36/F36)*100)-100 -> 0
B37: COLORANTES | C37: MPPO135 | D37: COLOR NATURAL NARANJA LIQUIDO RA 40 - 3 9827 AF. GALÓN x 4 KILOS. | E37: 53618 | F37: 53618 | G37: =((E37/F37)*100)-100 -> 0
B38: COLORANTES | C38: MPLO214 | D38: COLOR NATURAL ROJO AC305RWS. GARRAFA X 4 KILOS. | E38: 121899 | F38: 121899 | G38: =((E38/F38)*100)-100 -> 0
B39: CONDIMENTOS Y ESPECIAS | C39: MPPS104 | D39: AJO MOLIDO DESHIDRATADO B. 1. CAJA X 20 KILOS. (LA CAMPANA) | E39: 30713 | F39: 30713 | G39: =((E39/F39)*100)-100 -> 0
B40: CONDIMENTOS Y ESPECIAS | C40: MPPS153 | D40: CEBOLLA EN POLVO B.1. CAJA X 20 KILOS. (LA CAMPANA). | E40: 24619 | F40: 24619 | G40: =((E40/F40)*100)-100 -> 0
B41: CONDIMENTOS Y ESPECIAS | C41: MPPS154 | D41: PIMIENTA MOLIDA BLANCA. BOLSA X 1 KILO. (TECNAS) | E41: 69401 | F41: 69401 | G41: =((E41/F41)*100)-100 -> 0
B42: CONDIMENTOS Y ESPECIAS | C42: MPPS095 | D42: PIMIENTA NEGRA MOLIDA. BOLSA X 1 KILO. (TECNAS) | E42: 43120 | F42: 43120 | G42: =((E42/F42)*100)-100 -> 0
B43: CONDIMENTOS Y ESPECIAS | C43: MPPS157 | D43: COMINO MOLIDO B.1. BOLSA X 1 KILO. (LA CAMPANA) | E43: 28330 | F43: 32511 | G43: =((F43/E43)*100)-100 -> 14.758207
B44: CONSERVANTES | C44: MPPN323 | D44: CONSERVANTE INBAC ACN/NA. CAJA X 25 KILOS. | E44: 61143.15 | F44: 59418 | G44: =((F44/E44)*100)-100 -> -2.8214935
B45: EDULCORANTES | C45: MPPS090 | D45: AZÚCAR REFINADA. SACO X 50 KILOS. | E45: 4915.32 | F45: 4915 | G45: =((F45/E45)*100)-100 -> -0.0065102577
B46: EDULCORANTES | C46: MPPS152 | D46: DEXTROSA. BOLSA X 1 KILO. | E46: 10972 | F46: 10972 | G46: =((E46/F46)*100)-100 -> 0
B47: ENTURBIANTE | C47: MPPO140 | D47: ENTURBIANTE EN POLVO DPA X 1 KILO | E47: 50633 | F47: 50633 | G47: =((E47/F47)*100)-100 -> 0
B48: ENZYMAS | C48: MPPS102 | D48: REACTYNSH2 TRASGLUTAMINASA BOLSA X 1 KG | E48: 153185 | F48: 153185 | G48: =((E48/F48)*100)-100 -> 0
B49: EXTENSORES | C49: MPPA158 | D49: SOLU-TEX GRASAS NEUTRO. SACO X 15 KILOS | E49: 34163 | F49: 34163 | G49: =((E49/F49)*100)-100 -> 0
B50: FIJADORES DE COLOR | C50: MPPS151 | D50: SAL CURANTE AL 12 %. SACO X 25 KILOS. | E50: 2500 | F50: 2500 | G50: =((E50/F50)*100)-100 -> 0
B51: GELIFICANTES | C51: MPPD168 | D51: CARRAGENINA CEAMGEL M 9396. SACO X 25 KILOS. | E51: 62980 | F51: 62980 | G51: =((E51/F51)*100)-100 -> 0
B52: GRASA DE CERDO | C52: MPCC019 | D52: GRASA EMPELLA | E52: 4000 | F52: 4000 | G52: =((E52/F52)*100)-100 -> 0
B53: GRASA DE CERDO | C53: MPCC036 | D53: PAPADA DE CERDO. Disco 6mm. | E53: 12000 | F53: 12000 | G53: =((E53/F53)*100)-100 -> 0
B54: GRASA DE CERDO | C54: MPCC026 | D54: TOCINO DE CERDO | E54: 7022.73 | F54: 7029 | G54: =((F54/E54)*100)-100 -> 0.089281519
B55: GRASA DE POLLO | C55: MPCP037 | D55: PIEL DE POLLO NACIONAL | E55: 3160 | F55: 3160 | G55: =((E55/F55)*100)-100 -> 0
B56: HUMOS | C56: MPPH147 | D56: HUMO TRUSMOKE OIL EX. GARRAFA X 20 KG | E56: 42232.96 | F56: 40689 | G56: =((F56/E56)*100)-100 -> -3.6558176
B57: HUMOS | C57: MPPH141 | D57: HUMO CHARDEX EN POLVO X 18 KG | E57: 65000 | F57: 65000 | G57: =((E57/F57)*100)-100 -> 0
B58: HUMOS | C58: MPPH142 | D58: HUMO SMOKE OIL. GARRAFA PLÁSTICA X 12 KG. | E58: 41100 | F58: 41100 | G58: =((E58/F58)*100)-100 -> 0
B59: MODIFICADORES DE PH | C59: MPPD172 | D59: MEZCLA DE FOSFATOS (CARFOSEL 996). SACO X 25 KILOS. | E59: 17733 | F59: 16795 | G59: =((F59/E59)*100)-100 -> -5.2895731
B60: MODIFICADORES DE PH | C60: MPPD160 | D60: MEZCLA DE FOSFATOS (CARNAL 961). SACO X 25 KILOS. | E60: 21400 | F60: 21400 | G60: =((E60/F60)*100)-100 -> 0
B61: PRODUCTOS EN PROCESO | C61: MIPS003 | D61: GRANULOS DE PROTEÍNA. CANASTA X 25 KILOS. | E61: 6345 | F61: 6260 | G61: =((F61/E61)*100)-100 -> -1.3396375
B62: PRODUCTOS EN PROCESO | C62: MPCC012 | D62: EMULSION (PIEL DE CERDO) - TOCINO PARTES MAGRAS | E62: 1500 | F62: 1500 | G62: =((E62/F62)*100)-100 -> 0
B63: PRODUCTOS EN PROCESO | D63: PP BATIDO PREPARADO | E63: 1778 | F63: 1778 | G63: =((E63/F63)*100)-100 -> 0
B64: PRODUCTOS EN PROCESO | C64: - | D64: REPELE (CHARQUEADO) | E64: 1600 | F64: 1600 | G64: =((E64/F64)*100)-100 -> 0
B65: PROTEÍNA ANIMAL | C65: MPPA134 | D65: EXTRACTO PROTEICO LC 300. Saco x 25 kg. | E65: 22615.13 | F65: 19616 | G65: =((F65/E65)*100)-100 -> -13.261608
B66: PROTEÍNA ANIMAL | C66: MPPA168 | D66: PROTEÍNA COLAGÉNICA COLLAPRO P -950. SACO X 12,5 KILOS. | E66: 34415.23 | F66: 33158 | G66: =((F66/E66)*100)-100 -> -3.653121
B67: PROTEÍNA ANIMAL | C67: MPPA151 | D67: PLASMA APROPORK. SACO X 20 KILOS. | E67: 29262 | F67: 28967 | G67: =((F67/E67)*100)-100 -> -1.0081334
B68: PROTEÍNA VEGETAL | C68: MPPA164 | D68: PROTEÍNA DE SOYA AL 69%. ARCON MM. SACO X 20 KILOS | E68: 16779.61 | F68: 15214 | G68: =((F68/E68)*100)-100 -> -9.3304314
B69: PROTEÍNA VEGETAL | C69: MPPA122 | D69: PROTEÍNA DE SOYA AL 70%. ARCON T (Hojuelas). SACO X 11.34 KILOS | E69: 16768.69 | F69: 16680 | G69: =((F69/E69)*100)-100 -> -0.52890238
B70: PROTEÍNA VEGETAL | C70: MPPA132 | D70: PROTEÍNA DE SOYA AL 65%. SACO X 20 KILOS | E70: 14450 | F70: 14450 | G70: =((E70/F70)*100)-100 -> 0
B71: RESALTADORES DE SABOR | C71: MPLR191 | D71: PVH LIQUIDA - M - 1222. CANECA X 70 KILOS. | E71: 10412 | F71: 10412 | G71: =((E71/F71)*100)-100 -> 0
B72: RESALTADORES DE SABOR | C72: MPPS165 | D72: SAL REDUCIDA EN SODIO | E72: 5990 | F72: 5990 | G72: =((E72/F72)*100)-100 -> 0
B73: RESALTADORES DE SABOR | C73: MPPS150 | D73: SAL YODADA REFISAL. SACO X 25 KILOS. | E73: 878 | F73: 878 | G73: =((E73/F73)*100)-100 -> 0

Sheet ME OCT
B2: PRECIO MATERIAL DE EMPAQUE Y EMBUTIDO - OCT 22
B4: GRUPO | C4: CÓDIGO | D4: DESCRIPCIÓN | E4: OCT - COP / UMB | F4: SEP - COP / UMB | G4: %
B5: BOLSAS LAMINADAS | C5: MPES138 | D5: Bolsa Amarilla Impresa Milanesa x 1.800 gramos x 15 Unidades. Canal Intitucional. Bolsa Plana Pet//PEDB 70 micras | E5: 577 | F5: 577 | G5: =((F5/E5)*100)-100 -> 0
B6: BOLSAS LAMINADAS | C6: MPES143 | D6: Bolsa Impresa Roja Hamburguesa x 450 gramos x 5 unidades. Canal Moderno. Bolsa Flex Up Pet//PEBD 80 micras | E6: 437 | F6: 437 | G6: =((F6/E6)*100)-100 -> 0
B7: BOLSAS REGULARES | C7: MPES513 | D7: Bolsa AD BCO Impresa FAIZAN 23x25 + 4 cm en 1.0 ML | E7: 58 | F7: 58 | G7: =((F7/E7)*100)-100 -> 0
B8: CLIPS | C8: MPEP405 | D8: Grapas Poly-Clip GMBH 15-08 5 x 1,5 Carrete x 5,500 unidades | E8: 28 | F8: 27 | G8: =((F8/E8)*100)-100 -> -3.5714286
B9: CLIPS | C9: MPEP969 | D9: Clips HC25-3218T. Carrete x 2,400 unidades. | E9: 28 | F9: 52 | G9: =((F9/E9)*100)-100 -> 85.714286
B10: COLLARINES | C10: MPES155 | D10: Etiqueta Megasalchicha x 560 gramos x 6 unidades | E10: 115 | F10: 115 | G10: =((F10/E10)*100)-100 -> 0
B11: CORRUGADOS | C11: MPES959 | D11: Caja Hamburguesa x 2.700 gramos | E11: 1022 | F11: 1022 | G11: =((F11/E11)*100)-100 -> 0
B12: CORRUGADOS | C12: MPES968 | D12: Caja Koba Salchichón de Pollo Brakel x 500 gramos (15 unidades) | E12: 1624 | F12: 1624 | G12: =((F12/E12)*100)-100 -> 0
B13: CORRUGADOS | C13: MPES969 | D13: Caja Koba Jamón de Cerdo Viandé x 300 gramos (32 unidades) | E13: 1624 | F13: 1624 | G13: =((F13/E13)*100)-100 -> 0
B14: CORRUGADOS | C14: MPES972 | D14: Caja Koba Salchichón Tradicional Viandé x 500 gramos (15 unidades) | E14: 1624 | F14: 1624 | G14: =((F14/E14)*100)-100 -> 0
B15: CORRUGADOS | C15: MPES973 | D15: Caja Koba Super Combo Tradicional Viandé (9 unidades) | E15: 1727 | F15: 1727 | G15: =((F15/E15)*100)-100 -> 0
B16: CORRUGADOS | C16: MPES974 | D16: Caja Koba Salchicha Tradicional Viandé x 450 gramos. (22 unidades) | E16: 1816 | F16: 1816 | G16: =((F16/E16)*100)-100 -> 0
... B71: PELÍCULA SUPERIOR | C71: MPES461 | D71: Lámina Impresa Salchichón Cervecero Tajado x 50 gramos x 1,000 metros x 302 mm . | E71: 954 | F71: 954 | G71: =((F71/E71)*100)-100 -> 0

Sheet EXPLOSION ME DIC 2022
A1: Etiquetas de fila | B1: NECESIDAD DIC /2022 | C1: OCT - COP / UMB | D1: INVERSIÓN ME | E1: INVENTARIO NOV 30
A2: Lámina Inferior Sudpack GVP 130-423 mm (5.0 mils). 1 Rollo x 350 metros | B2: 59942.199 | C2: 9901.35 | D2: =C2*B2 -> 5.9350869e+08
A3: Grapas Poly-Clip GMBH R-ID M 07-150 Carrete x 6,800 unidades | B3: 2326841.8 | C3: 224 | D3: =C3*B3 -> 5.2121256e+08
A4: Lámina Inferior Sudpack GVA 200 BT 323 MM (8.MILS) 1 Rollo x 300 metros | B4: 9692.648 | C4: 20291 | D4: =C4*B4 -> 1.9667352e+08
A5: Fibrosa FVP CLS 140 B5 4 H5 Natural Corrugado. (Viandé) | B5: 6582.51 | C5: 24870.52 | D5: =C5*B5 -> 1.6371045e+08
A6: Separador 15 cm x 15 cm Impreso Highpack | B6: 1084064.2 | C6: 114 | D6: =C6*B6 -> 1.2358332e+08
A7: Fibrosa FVP CLS 95 B3 4 H3 Natural Corrugada x 25 metros. | B7: 13268.7 | C7: 8542.28 | D7: =C7*B7 -> 1.1334495e+08
A8: Lámina Superior Impresa Super Combo Tradicional Viandé x 900 gramos x 9 unidades. Ancho = 45 cms. (Pet / coextrusión HBA 73 micras). | B8: 3815 | C8: 26300 | D8: =C8*B8 -> 100334500
A9: Tubular Salchichón Cervecero Viande x 225 Gramos. Cal 40 | B9: 154000 | C9: 491.73 | D9: =C9*B9 -> 75726420
A10: Funda Celulosa 18 x 100 (Cartón x 9.144 metros x 300 tubos,C/tubo x 30.48 metros. 6 caddy x 50 tubos) | B10: 110144.6 | C10: 624.51 | D10: =C10*B10 -> 68786403
A11: Funda Celulosa 20 x 100 CE FP CLR | B11: 308000 | C11: 216.66 | D11: =C11*B11 -> 66731280
A12: Caja Koba Super Combo Tradicional Viandé (9 unidades) | B12: 38500 | C12: 1727 | D12: =C12*B12 -> 66489500
A13: Funda Colageno NDX 26/60 (cartón x 4,718 metros x 258 tubos, C/tubo x 18.29 metros. 6 Caddy x 43 tubos C/U) | B13: 25153.653 | C13: 1873.83 | D13: =C13*B13 -> 47133670
... A68: Etiqueta Salchicha Desayuno Premium x 125 Gramos x 5 Unidades | B68: 888.32 | C68: 65 | D68: =C68*B68 -> 57740.8
A70: Total general | B70: 5062049.9 | C70: 184708.59 | D70: =SUM(D2:D68) -> 2.6806775e+09

Sheet D1
A1: TABLA DE REFERENCIAS
A2: Marca | B2: Línea de PICADOS SALCHICHAS | C2: ='CIF Y PV'!F6 -> MB-JUN
A3: D1 | B3: SALCHICHA PERRO CALIENTE VIANDE X 240 G X 6 UND | C3: =VLOOKUP(B3,'MB FEB'!B3:D86,3,FALSE) -> 0.38889371
A4: D1 | B4: SALCHICHA SUPER PERRO VIANDE X 400 G X 5 UND | C4: =VLOOKUP(B4,'MB FEB'!B4:D87,3,FALSE) -> 0.39099101
B5: LINEA SALCHICHAS | C5: =AVERAGE(C3:C4) -> 0.38994236
A6: Marca | B6: Línea de PICADOS CHORIZOS | C6: ='CIF Y PV'!F6 -> MB-JUN
A7: D1 | B7: CHORIZO ANTIOQUEÑO X 225 VIANDE | C7: =VLOOKUP(B7,'MB FEB'!B7:D90,3,FALSE) -> 0.35182806
A8: D1 | B8: CHORIZO CON TERNERA VIANDE X 225 GRS 5 UND | C8: =VLOOKUP(B8,'MB FEB'!B8:D91,3,FALSE) -> 0.32120562
A9: D1 | B9: CHORIZO SANTARROSANO VIANDE X 225 GRS 5 UNDS | C9: ='MB FEB'!D41 -> 0.31001682
B10: LINEA CHORIZOS | C10: =AVERAGE(C7:C8) -> 0.33651684
A11: Marca | B11: Línea de SALCHICHONES | C11: ='CIF Y PV'!F6 -> MB-JUN
A12: D1 | B12: SCHON. TRADICIONAL VIANDE X 500 G | C12: =VLOOKUP(B12,'MB FEB'!B11:D94,3,FALSE) -> 0.39602175
A13: D1 | B13: SCHON. POLLO BRAKEL X 500 G | C13: =VLOOKUP(B13,'MB FEB'!B12:D95,3,FALSE) -> 0.39872019
A14: D1 | B14: SNACK CERVECERITO X150 GRS | C14: ='MB FEB'!D51 -> 0.29202328
B15: LINEA SALCHICHICHONES | C15: =AVERAGE(C12:C13) -> 0.39737097
A16: Marca | B16: Línea de BARRAS | C16: ='CIF Y PV'!F6 -> MB-JUN
A17: D1 | B17: JAMON PREMIUM VIANDE X 300 G X 15 UND | C17: =VLOOKUP(B17,'MB FEB'!B14:D98,3,FALSE) -> 0.36652172
A18: D1 | B18: MORTADELA JAMONADA VIANDE X 400 GRS | C18: ='MB FEB'!D55 -> 0.29387153
B19: LINEA JAMONES | C19: =AVERAGE(C17) -> 0.36652172
A20: Marca | B20: Línea OFERTAS | C20: ='CIF Y PV'!F6 -> MB-JUN
A21: D1 | B21: SUPER COMBO VIANDE * 900 | C21: =VLOOKUP(B21,'MB FEB'!B16:D101,3,FALSE) -> 0.33424604
B22: LINEA OFERTAS | C22: =AVERAGE(C21) -> 0.33424604
A23: Marca | B23: Línea TOCINOS | C23: ='CIF Y PV'!F6 -> MB-JUN
B26: LINEA | C26: ='CIF Y PV'!F6 -> MB-JUN | D26: META
B27: LINEA SALCHICHAS | C27: =VLOOKUP(B27,B3:C22,2,FALSE) -> 0.38994236 | D27: 0.25
B28: LINEA CHORIZOS | C28: =VLOOKUP(B28,B4:C23,2,FALSE) -> 0.33651684 | D28: 0.25
B29: LINEA SALCHICHICHONES | C29: =VLOOKUP(B29,B5:C24,2,FALSE) -> 0.39737097 | D29: 0.25
B30: LINEA JAMONES | C30: =VLOOKUP(B30,B6:C25,2,FALSE) -> 0.36652172 | D30: 0.25
B31: LINEA OFERTAS | C31: =VLOOKUP(B31,B7:C26,2,FALSE) -> 0.33424604 | D31: 0.25

Sheet FAZAN
A1: TABLA DE REFERENCIAS
A2: Marca | B2: Línea de PICADOS SALCHICHAS | C2: ='CIF Y PV'!F6 -> MB-JUN
A3: Fazàn | B3: SCHA. CLASICA X 225 G X 9 UND | C3: =VLOOKUP(B3,'MB FEB'!B3:D85,3,FALSE) -> 0.60707026
A4: Fazàn | B4: SALCHICHA CLASICA X 450 G - 18 UND | C4: =VLOOKUP(B4,'MB FEB'!B4:D86,3,FALSE) -> 0.55693962
A5: Fazàn | B5: SALCHICHA PERRO CALIENTE X 480 G - 12 UND | C5: =VLOOKUP(B5,'MB FEB'!B5:D87,3,FALSE) -> 0.62997797
A6: Fazàn | B6: SALCHICHA SUPER PERRO X 500 G | C6: =VLOOKUP(B6,'MB FEB'!B6:D88,3,FALSE) -> 0.52052742
A7: Fazàn | B7: SALCHICHA MINIPERRO X 1.000 G - 40 UND | C7: =VLOOKUP(B7,'MB FEB'!B7:D89,3,FALSE) -> 0.50082322
A8: Fazàn | B8: SALCHICHA SUPER PERRO X 2.500 G - 50 UND | C8: =VLOOKUP(B8,'MB FEB'!B8:D90,3,FALSE) -> 0.46486749
A9: Fazàn | B9: SCHA. DESAYUNO PREMIUM X 115 G X 5 UND | C9: =VLOOKUP(B9,'MB FEB'!B9:D91,3,FALSE) -> 0.53683079
A10: Fazàn | B10: SALCHICHA DESAYUNO PREMIUM X 480 G - 14 UND | C10: =VLOOKUP(B10,'MB FEB'!B10:D92,3,FALSE) -> 0.50502403
A11: Fazàn | B11: SALCHICHA DESAYUNO PREMIUM FZAN X 240 X 7UND | C11: =VLOOKUP(B11,'MB FEB'!B11:D93,3,FALSE) -> 0.53664543
A12: Fazàn | B12: SALCHICHA DESAYUNO PREMIUM X 960 | C12: =VLOOKUP(B12,'MB FEB'!B13:D95,3,FALSE) -> 0.50195425
A13: Fazàn | B13: SCHA JUMBO X 1200 G | C13: =VLOOKUP(B13,'MB FEB'!B14:D96,3,FALSE) -> 0.44979161
A14: Fazàn | B14: SCHA JUMBO X 450 G FAZÁN | C14: =VLOOKUP(B14,'MB FEB'!B15:D98,3,FALSE) -> 0.52236802
A15: Fazàn | B15: SALCHICHA MANGUERA X 560 G - 6 UND | C15: =VLOOKUP(B15,'MB FEB'!B16:D99,3,FALSE) -> 0.49362857
A16: Fazàn | B16: MEGA SALCHICHA TIPO MANGUERA 1120 G 12 UND | C16: =VLOOKUP(B16,'MB FEB'!B16:D100,3,FALSE) -> 0.45830782
A17: Fazàn | B17: SALCHICHA LONG X 1100 GRS X 20 UNDS | C17: =VLOOKUP(B17,'MB FEB'!B17:D101,3,FALSE) -> 0.38767084
A18: Fazàn | B18: SALCHICHA UNINORTE X 1280 GRS X 16 UNDS | C18: =VLOOKUP(B18,'MB FEB'!B18:D102,3,FALSE) -> 0.49236164
A19: Fazàn | B19: ='MB FEB'!B23 -> SALCHICHA SUIZA X 990 GRS 9 UNDS | C19: ='MB FEB'!D23 -> 0.41897254
B20: LINEA SALCHICHAS | C20: =AVERAGE(C3:C18) -> 0.51029931
A21: Marca | B21: Línea de PICADOS CHORIZOS | C21: ='CIF Y PV'!F6 -> MB-JUN
A22: Fazàn | B22: CHORIZO DE CERDO X 250 G - 5 UND - Fazán | C22: =VLOOKUP(B22,'MB FEB'!B24:D107,3,FALSE) -> 0.5046436
A23: Fazàn | B23: CHORIZO DE CERDO X 400 G - 8 UND | C23: =VLOOKUP(B23,'MB FEB'!B25:D108,3,FALSE) -> 0.47834783
A24: Fazàn | B24: CHORIZO DE CERDO X 1000 G - 20 UND | C24: =VLOOKUP(B24,'MB FEB'!B25:D109,3,FALSE) -> 0.44865358
A25: Fazàn | B25: CHORIZO CON TERNERA X 110 G - 2 UND | C25: =VLOOKUP(B25,'MB FEB'!B25:D110,3,FALSE) -> 0.41924188
A26: Fazàn | B26: CHORIZO CON TERNERA X 220 G - 4 UND | C26: =VLOOKUP(B26,'MB FEB'!B26:D111,3,FALSE) -> 0.41018414
A27: Fazàn | B27: CHORIZO CON TERNERA X 440 G - 8 UND FZAN | C27: =VLOOKUP(B27,'MB FEB'!B27:D112,3,FALSE) -> 0.44823859
A28: Fazàn | B28: CHORIZO CON TERNERA X 1100 G - | C28: =VLOOKUP(B28,'MB FEB'!B29:D114,3,FALSE) -> 0.4410006
A29: Fazàn | B29: CHORIZO SANTARROSANO x 300 | C29: =VLOOKUP(B29,'MB FEB'!B30:D115,3,FALSE) -> 0.55181118
A30: Fazàn | B30: CHORIZO SANTARROSANO x 480 | C30: =VLOOKUP(B30,'MB FEB'!B31:D116,3,FALSE) -> 0.55072142
A31: Fazàn | B31: CHORIZO SANTARROSANO x 1200 | C31: =VLOOKUP(B31,'MB FEB'!B31:D117,3,FALSE) -> 0.50712913
A32: Fazàn | B32: CHORIZO COCTEL SANTARROSANO X 300 xx UND | C32: =VLOOKUP(B32,'MB FEB'!B32:D118,3,FALSE) -> 0.47635479
A33: Fazàn | B33: CHORIZO COCTEL SANTARROSANO X 1000 74 UND | C33: =VLOOKUP(B33,'MB FEB'!B33:D119,3,FALSE) -> 0.44850789
A34: Fazàn | B34: CHORIZO SANTARROSANO LARGO PERRITOS 1.2 G 15 UND | C34: =VLOOKUP(B34,'MB FEB'!B34:D120,3,FALSE) -> 0.44358077
B35: LINEA CHORIZOS | C35: =AVERAGE(C22:C34) -> 0.47141657
A36: Marca | B36: Línea de SALCHICHONES | C36: ='CIF Y PV'!F6 -> MB-JUN
A37: Fazàn | B37: SALCHICHON AUTENTICO X 750 G | C37: =VLOOKUP(B37,'MB FEB'!B37:D123,3,FALSE) -> 0.56055922
A38: Fazàn | B38: SALCHICHON CERVECERO X 500 G | C38: =VLOOKUP(B38,'MB FEB'!B39:D124,3,FALSE) -> 0.62036304
A39: Fazàn | B39: SALCHICHON CERVECERO X 750 G | C39: =VLOOKUP(B39,'MB FEB'!B39:D125,3,FALSE) -> 0.58120586
A40: Fazàn | B40: SALCHICHON CERVECERO X 1.300 G | C40: =VLOOKUP(B40,'MB FEB'!B40:D126,3,FALSE) -> 0.54643466
A41: Fazàn | B41: SALCHICHON CERVECERO X 1.500 G | C41: =VLOOKUP(B41,'MB FEB'!B42:D127,3,FALSE) -> 0.55995331
A42: Fazàn | B42: OFTA CERV PREM X 6 UND | C42: =VLOOKUP(B42,'MB FEB'!B43:D128,3,FALSE) -> 0.48948186
B43: LINEA SALCHICHONES | C43: =AVERAGE(C37:C42) -> 0.55966632
A44: Marca | B44: Línea de BARRAS | C44: ='CIF Y PV'!F6 -> MB-JUN
A45: Fazàn | B45: MORTADELA SELECCIONADA X 225 G - 14 UND | C45: =VLOOKUP(B45,'MB FEB'!B46:D131,3,FALSE) -> 0.5411638
A46: Fazàn | B46: MORATDELA JAMONADA X 225 GRS | C46: =VLOOKUP(B46,'MB FEB'!B47:D132,3,FALSE) -> 0.58076996
A47: Fazàn | B47: JAMÓN SANDUCHE X 500 G X 28 UND (I) | C47: =VLOOKUP(B47,'MB FEB'!B48:D133,3,FALSE) -> 0.44923704
A48: Fazàn | B48: JAMON SANDUCHE FZAN X 225 | C48: =VLOOKUP(B48,'MB FEB'!B49:D134,3,FALSE) -> 0.5483305
A49: Fazàn | B49: JAMÓN SANDUCHE X 450 G X 24 UND FZAN | C49: =VLOOKUP(B49,'MB FEB'!B53:D137,3,FALSE) -> 0.54987211
A50: Fazàn | B50: JAMON DE CERDO PREMIUM X 120 G - 6 UND FZA | C50: =VLOOKUP(B50,'MB FEB'!B54:D138,3,FALSE) -> 0.54790739
A51: Fazàn | B51: JAMON DE CERDO PREMIUM X 200 G - 10 UND FZAN | C51: =VLOOKUP(B51,'MB FEB'!B57:D140,3,FALSE) -> 0.62751501
A52: Fazàn | B52: JAMON DE CERDO PREMIUM X 220 G - 11 UND | C52: =VLOOKUP(B52,'MB FEB'!B58:D141,3,FALSE) -> 0.62751501
A53: Fazàn | B53: JAMON DE CERDO PREMIUM X 400 G -20 UND | C53: =VLOOKUP(B53,'MB FEB'!B58:D142,3,FALSE) -> 0.61276241
A54: Fazàn | B54: MILANESA DE POLLO APANADA X 240 G - 2 UND | C54: =VLOOKUP(B54,'MB FEB'!B58:D143,3,FALSE) -> 0.53818582
A55: Fazàn | B55: MILANESA DE POLLO APANADA X 600 G - 5 UND | C55: =VLOOKUP(B55,'MB FEB'!B59:D144,3,FALSE) -> 0.72094191
A56: Fazàn | B56: MILANESA DE POLLO APANADA X 1.800 G - 15 UND | C56: =VLOOKUP(B56,'MB FEB'!B60:D145,3,FALSE) -> 0.4146307
B57: LINEA TAJADOS | C57: =AVERAGE(C45:C56) -> 0.56323597
A58: Marca | B58: Línea PRERFORMADOS | C58: ='CIF Y PV'!F6 -> MB-JUN
A59: Fazàn | B59: HAMBURGUESAS (BOLSA ROJA) X 900 G - 10 UND | C59: =VLOOKUP(B59,'MB FEB'!B62:D148,3,FALSE) -> 0.21058802
A60: Fazàn | B60: HAMBURGUESAS (CAJA) X 2700 G - 30 UND | C60: =VLOOKUP(B60,'MB FEB'!B63:D149,3,FALSE) -> 0.51039764
A61: Fazàn | B61: HAMBURGUESA X 450 G - 5 UND | C61: =VLOOKUP(B61,'MB FEB'!B64:D150,3,FALSE) -> 0.54109051
A62: Fazàn | B62: HAMBURGUESA DE POLLO X 1425 X 15 UND | C62: =VLOOKUP(B62,'MB FEB'!B65:D151,3,FALSE) -> 0.48256038
A63: Fazàn | B63: HAMBURGUESA DE POLLO X 1500 X 10 UND | C63: =VLOOKUP(B63,'MB FEB'!B66:D152,3,FALSE) -> 0.45994617
A64: Fazàn | B64: ='MB FEB'!B72 -> HAMBURGUESA DE POLLO X 750 5 UND | C64: ='MB FEB'!D72 -> 0.42336231
B65: LINEA HAMBURGUESAS | C65: =AVERAGE(C59:C63) -> 0.44091654
A66: Marca | B66: Línea OFERTAS | C66: ='CIF Y PV'!F6 -> MB-JUN
A67: Fazàn | B67: MEGA COMBO FAIZAN * 900 NUEVO CON JAMON 225 | C67: =VLOOKUP(B67,'MB FEB'!B69:D155,3,FALSE) -> 0.97784914
B69: LINEA OFERTAS | C69: =AVERAGE(C67:C68) -> 0.97784914
A70: Marca | B70: Línea TOCINOS | C70: ='CIF Y PV'!F6 -> MB-JUN
A71: Fazàn | B71: TOCINO BARRIGUERO X 1 KG | C71: =VLOOKUP(B71,'MB FEB'!B74:D159,3,FALSE) -> 0.53795251
A72: Fazàn | B72: TOCINO PAPADA X 1 KG | C72: =VLOOKUP(B72,'MB FEB'!B75:D160,3,FALSE) -> 0.48791509
A73: Fazàn | B73: TOCINETA REESTRUCTURADA X 150 GRS | C73: =VLOOKUP(B73,'MB FEB'!B76:D161,3,FALSE) -> 0.52149942
B74: LINEA TOCINOS | C74: =AVERAGE(C71:C73) -> 0.51578901
B77: LINEA | C77: ='CIF Y PV'!F6 -> MB-JUN | D77: META
B78: LINEA SALCHICHAS | C78: =VLOOKUP(B78,B3:C74,2,FALSE) -> 0.51029931 | D78: 0.35
B79: LINEA CHORIZOS | C79: =VLOOKUP(B79,B4:C75,2,FALSE) -> 0.47141657 | D79: 0.35
B80: LINEA SALCHICHONES | C80: =VLOOKUP(B80,B5:C76,2,FALSE) -> 0.55966632 | D80: 0.35
B81: LINEA TAJADOS | C81: =VLOOKUP(B81,B6:C77,2,FALSE) -> 0.56323597 | D81: 0.35
B82: LINEA HAMBURGUESAS | C82: =VLOOKUP(B82,B7:C78,2,FALSE) -> 0.44091654 | D82: 0.35
B83: LINEA OFERTAS | C83: =VLOOKUP(B83,B8:C79,2,FALSE) -> 0.97784914 | D83: 0.35
B84: LINEA TOCINOS | C84: =VLOOKUP(B84,B9:C80,2,FALSE) -> 0.51578901 | D84: 0.35

Sheet MB FEB
A1: TABLA DE REFERENCIAS
A2: Marca | B2: Línea de PICADOS SALCHICHAS | C2: MB - JUNIO COSTOS | D2: MB - JUNIO | E2: MB - MAY | F2: %
A3: Fazàn | B3: SCHA. CLASICA X 225 G X 9 UND | D3: ='SCHA CLÁSICA 225 G 9 UND'!H49 -> 0.60707026 | E3: 0.59656243 | F3: =((E3/D3)*100-100) -> -1.7309087
A4: Fazàn | F4: =((E4/D4)*100-100) -> #DIV/0!
A5: Fazàn | B5: SALCHICHA CLASICA X 450 G - 18 UND | D5: ='SCHA CLÁSICA 450 G 18 UND'!H49 -> 0.55693962 | E5: 0.54567661 | F5: =((E5/D5)*100-100) -> -2.0223043
A6: Fazàn | B6: SCHA. SELECCIONADA VIANDE X 450 G X 16 UND | F6: =((E6/D6)*100-100) -> #DIV/0!
A7: Fazàn | B7: SALCHICHA PERRO CALIENTE X 480 G - 12 UND | D7: ='SCHA PERRO X 480 G - 12 UNDS'!H50 -> 0.62997797 | E7: 0.61103573 | F7: =((E7/D7)*100-100) -> -3.0068112
A8: Fazàn | B8: SALCHICHA SUPER PERRO X 500 G | D8: ='SCHA S. PERRO X 500 '!H49 -> 0.52052742 | E8: 0.51160819 | F8: =((E8/D8)*100-100) -> -1.7134986
A9: Fazàn | B9: SALCHICHA MINIPERRO X 1.000 G - 40 UND | D9: ='MINI PERRO X 1.0'!H49 -> 0.50082322 | E9: 0.48386113 | F9: =((E9/D9)*100-100) -> -3.3868408
A10: Fazàn | B10: SALCHICHA SUPER PERRO X 2.500 G - 50 UND | D10: ='SUPER PERRO X 2500 RX'!H49 -> 0.46486749 | E10: 0.44837769 | F10: =((E10/D10)*100-100) -> -3.5472037
A11: Fazàn | B11: SCHA. DESAYUNO PREMIUM X 115 G X 5 UND | D11: ='SCHA DESAYUNO 115 G - 5 UNDS'!H50 -> 0.53683079 | E11: 0.54670193 | F11: =((E11/D11)*100-100) -> 1.8387813
A12: Fazàn | B12: SALCHICHA DESAYUNO PREMIUM X 480 G - 14 UND | D12: ='SCHA DESAYUNO 480 G -14 UND'!H50 -> 0.50502403 | E12: 0.47995401 | F12: =((E12/D12)*100-100) -> -4.9641233
A13: Fazàn | B13: SALCHICHA DESAYUNO PREMIUM FZAN X 240 X 7UND | D13: ='SCHA DESAYUNO FZA x 240 x 7 UND'!H50 -> 0.53664543 | E13: 0.5139396 | F13: =((E13/D13)*100-100) -> -4.2310675
A14: Fazàn | B14: SALCHICHA DESAYUNO PREMIUM X 960 | D14: ='SCHA DESAYUNO 960 G'!H49 -> 0.50195425 | E14: 0.47529336 | F14: =((E14/D14)*100-100) -> -5.3114189
A15: Fazàn | B15: SCHA JUMBO X 1200 G | D15: ='SCHA JUMBO X 1200 G'!G50 -> 0.44979161 | E15: 0.43315422 | F15: =((E15/D15)*100-100) -> -3.6989108
A16: Fazàn | B16: SCHA JUMBO X 450 G FAZÁN | D16: ='SCHA JUMBO X 450G fazán'!G51 -> 0.52236802 | E16: 0.50862991 | F16: =((E16/D16)*100-100) -> -2.6299662
A17: Fazàn | B17: SALCHICHA MANGUERA X 560 G - 6 UND | D17: ='SCHA MANGUERA 560 G - 6 UND'!H46 -> 0.49362857 | E17: 0.48863147 | F17: =((E17/D17)*100-100) -> -1.0123198
A18: Viande | B18: MEGA SALCHICHA TIPO MANGUERA 1120 G 12 UND | D18: ='SCHA MANGUERA 1120G - 12UND'!H47 -> 0.45830782 | E18: 0.4507582 | F18: =((E18/D18)*100-100) -> -1.64728
A19: Viande | B19: SALCHICHA PERRO CALIENTE VIANDE X 240 G X 6 UND | D19: ='PERRO CALIENTE VIANDE x 240G'!H55 -> 0.38889371 | E19: 0.36799175 | F19: =((E19/D19)*100-100) -> -5.3747206
A20: Viande | B20: SALCHICHA SUPER PERRO VIANDE X 400 G X 5 UND | D20: ='SUPER PERRO VIANDE X 400G RX'!H54 -> 0.39099101 | E20: 0.39302729 | F20: =((E20/D20)*100-100) -> 0.52080125
A21: Fazàn | B21: SALCHICHA LONG X 1100 GRS X 20 UNDS | D21: ='SALCHICHA LONG'!H54 -> 0.38767084 | E21: 0.36394502 | F21: =((E21/D21)*100-100) -> -6.1200941
A22: Fazàn | B22: SALCHICHA UNINORTE X 1280 GRS X 16 UNDS | D22: ='SALCHICHA UNINORTE'!H54 -> 0.49236164 | E22: 0.47146796 | F22: =((E22/D22)*100-100) -> -4.2435642
A23: Fazàn | B23: SALCHICHA SUIZA X 990 GRS 9 UNDS | D23: {='SCHA SUIZA X 9'!D50:F50} -> 0.41897254 | E23: 0 | F23: 0
A24: Marca | B24: Línea de PICADOS CHORIZOS | C24: MB - JUNIO COSTOS | D24: MB - JUNIO | E24: MB - MAY | F24: %
A25: Faizán | B25: CHORIZO DE CERDO X 250 G - 5 UND - Fazán | D25: ='CHORIZO DE CERDO 250 FAZÁN'!H46 -> 0.5046436 | E25: 0.48774426 | F25: =((E25/D25)*100)-100 -> -3.3487677
A26: Faizán | B26: CHORIZO DE CERDO X 400 G - 8 UND | D26: ='CHORIZO DE CERDO 400 g'!H46 -> 0.47834783 | E26: 0.45729626 | F26: =((E26/D26)*100)-100 -> -4.4008926
A27: Faizán | B27: CHORIZO DE CERDO X 1000 G - 20 UND | D27: ='CHORIZO DE CERDO 1000'!H44 -> 0.44865358 | E27: 0.42854515 | F27: =((E27/D27)*100)-100 -> -4.4819496
A28: Faizán | B28: CHORIZO CON TERNERA X 110 G - 2 UND | D28: ='CHRZ CON TERNERA 110 G 2 UND'!H44 -> 0.41924188 | E28: 0.41005234 | F28: =((E28/D28)*100)-100 -> -2.1919419
A29: Faizán | B29: CHORIZO CON TERNERA X 220 G - 4 UND | D29: ='CHORIZO CON TERNERA 220'!H44 -> 0.41018414 | E29: 0.39403717 | F29: =((E29/D29)*100)-100 -> -3.9365176
A30: Faizán | B30: CHORIZO CON TERNERA X 440 G - 8 UND FZAN | D30: ='CHORIZO CON TERNERA 440 G FZAN'!H45 -> 0.44823859 | E30: 0.4462477 | F30: =((E30/D30)*100)-100 -> -0.44415966
A31: Faizán | B31: CHORIZO CON TERNERA X 1100 G - | D31: ='CHORIZO CON TERNERA 1100'!H43 -> 0.4410006 | E31: 0.42971815 | F31: =((E31/D31)*100)-100 -> -2.5583746
A32: Faizán | B32: CHORIZO SANTARROSANO x 300 | D32: ='CHORIZO SANTARROSANO x 300'!I46 -> 0.55181118 | E32: 0.55049237 | F32: =((E32/D32)*100)-100 -> -0.23899596
A33: Faizán | B33: CHORIZO SANTARROSANO x 480 | D33: ='CHORIZO SANTARROSANO x 480 '!I46 -> 0.55072142 | E33: 0.54971082 | F33: =((E33/D33)*100)-100 -> -0.18350325
A34: Faizán | B34: CHORIZO SANTARROSANO x 1200 | D34: ='CHORIZO SANTARROSANO x 1200'!I46 -> 0.50712913 | E34: 0.5052663 | F34: =((E34/D34)*100)-100 -> -0.36732838
A35: Faizán | B35: CHORIZO COCTEL SANTARROSANO X 300 xx UND | D35: ='CHORIZO SANTA COCTEL x 300'!I47 -> 0.47635479 | E35: 0.47019606 | F35: =((E35/D35)*100)-100 -> -1.2928865
A36: Faizán | B36: CHORIZO COCTEL SANTARROSANO X 1000 74 UND | D36: ='CHORIZO SANTA COCTEL x 1000'!I46 -> 0.44850789 | E36: 0.44317735 | F36: =((E36/D36)*100)-100 -> -1.1885037
A37: Faizán | B37: CHORIZO SANTARROSANO LARGO PERRITOS 1.2 G 15 UND | D37: ='CHORIZO SANTA LARGO x 1200 '!I46 -> 0.44358077 | E37: 0.44346944 | F37: =((E37/D37)*100)-100 -> -0.025097701
A38: FAZÀN | B38: CHORIZO RED DE ALIMENTOS
A39: Viande | B39: CHORIZO ANTIOQUEÑO X 225 VIANDE | D39: ='CHORIZO ANTIOQUEÑO VIANDE'!H52 -> 0.35182806 | E39: 0.3092663 | F39: =((E39/D39)*100)-100 -> -12.097319
A40: Viande | B40: CHORIZO CON TERNERA VIANDE X 225 GRS 5 UND | D40: ='CHORIZO TERNERA VIANDE'!H54 -> 0.32120562 | E40: 0.27949049 | F40: =((E40/D40)*100)-100 -> -12.987047
A41: Viande | B41: CHORIZO SANTARROSANO VIANDE X 225 GRS 5 UNDS | D41: ='CHORIZO SANTARRO VIANDE'!H47 -> 0.31001682 | E41: 0.2679226 | F41: =((E41/D41)*100)-100 -> -13.578043
A42: Marca | B42: Línea de SALCHICHONES | C42: MB - JUNIO COSTOS | D42: MB - JUNIO | E42: MB - MAY | F42: %
A43: Viande | B43: SCHON. TRADICIONAL VIANDE X 500 G | D43: ='SCHON TRAD VIANDÉ X 500 '!H50 -> 0.39602175 | E43: 0.39563299 | F43: =((E43/D43)*100)-100 -> -0.098165387
A44: Faizán | B44: SALCHICHON AUTENTICO X 750 G | D44: ='SCHON AUTENTICO X 750 G'!H49 -> 0.56055922 | E44: 0.55705796 | F44: =((E44/D44)*100)-100 -> -0.62460161
A45: Viande | B45: SCHON. POLLO BRAKEL X 500 G | D45: ='SCHON POLLO BRAKEL X 500'!H48 -> 0.39872019 | E45: 0.39327734 | F45: =((E45/D45)*100)-100 -> -1.3650801
A46: Faizán | B46: SALCHICHON CERVECERO X 500 G | D46: ='CERVECERO 500'!F43 -> 0.62036304 | E46: 0.60471003 | F46: =((E46/D46)*100)-100 -> -2.5232013
A47: Faizán | B47: SALCHICHON CERVECERO X 750 G | D47: ='CERVECERO 750'!H44 -> 0.58120586 | E47: 0.56417907 | F47: =((E47/D47)*100)-100 -> -2.9295631
A48: Faizán | B48: SALCHICHON CERVECERO X 1.300 G | D48: ='CERVECERO 1300'!H44 -> 0.54643466 | E48: 0.52828122 | F48: =((E48/D48)*100)-100 -> -3.3221605
A49: Faizán | B49: SALCHICHON CERVECERO X 1.500 G | D49: ='CERVECERO 1500'!H44 -> 0.55995331 | E49: 0.54232629 | F49: =((E49/D49)*100)-100 -> -3.1479439
A50: Faizán | B50: OFTA CERV PREM X 6 UND | D50: ='OFTA CERV PREM X 6 UND'!H30 -> 0.48948186 | E50: 0.47349059 | F50: =((E50/D50)*100)-100 -> -3.266979
A51: Viande | B51: SNACK CERVECERITO X150 GRS | D51: ='OFTA SNACK PREM X 3 UND'!H31 -> 0.29202328 | E51: 0.31475472 | F51: =((E51/D51)*100)-100 -> 7.7841181
A52: Marca | B52: Línea de BARRAS | C52: MB - JUNIO COSTOS | D52: MB - JUNIO | E52: MB - MAY | F52: %
A53: Faizán | B53: MORTADELA SELECCIONADA X 225 G - 14 UND | D53: ='MDELA FAIZAN 225 G 14 U SC'!H59 -> 0.5411638 | E53: 0.53323823 | F53: =((E53/D53)*100)-100 -> -1.4645417
A54: Faizán | B54: MORATDELA JAMONADA X 225 GRS | D54: ='MORTADELA JAMON X 225 '!H57 -> 0.58076996 | E54: 0.56517638 | F54: =((E54/D54)*100)-100 -> -2.6849845
A55: VIANDE | B55: MORTADELA JAMONADA VIANDE X 400 GRS | D55: ='MORTA JAMONADA 400'!H54 -> 0.29387153 | E55: 0.30768655
A56: Faizán | B56: JAMÓN SANDUCHE X 500 G X 28 UND (I) | D56: ='JMN SDW INST 500 G 28 U '!H58 -> 0.44923704 | E56: 0.43273133 | F56: =((E56/D56)*100)-100 -> -3.6741659
A57: Faizán | B57: JAMON SANDUCHE FZAN X 225 | D57: ='JMN SDW FZAN X 225 '!H58 -> 0.5483305 | E57: 0.53846206 | F57: =((E57/D57)*100)-100 -> -1.7997249
A58: Faizán | B58: JAMÓN SANDUCHE X 450 G X 24 UND FZAN | D58: ='JMN SDW 450 G 28 U '!H58 -> 0.54987211 | E58: 0.53891025 | F58: =((E58/D58)*100)-100 -> -1.9935305
A59: Faizán | B59: JAMON DE CERDO PREMIUM X 120 G - 6 UND FZA | D59: ='JMN PREMIUM FZAN 120 G '!H51 -> 0.54790739 | E59: 0.52634293 | F59: =((E59/D59)*100)-100 -> -3.9357865
A60: Faizán | B60: JAMON DE CERDO PREMIUM X 200 G - 10 UND FZAN | D60: ='JMN PREMIUM FZAN 200 G'!H52 -> 0.62751501 | E60: 0.60762373 | F60: =((E60/D60)*100)-100 -> -3.169848
A61: Faizán | B61: JAMON DE CERDO PREMIUM X 220 G - 11 UND | D61: ='JMN PREMIUM FZAN 200 G'!H52 -> 0.62751501 | E61: 0.60762373 | F61: =((E61/D61)*100)-100 -> -3.169848
A62: Faizán | B62: JAMON DE CERDO PREMIUM X 400 G -20 UND | D62: ='JMN PREMIUM 400 G'!H52 -> 0.61276241 | E62: 0.59078641 | F62: =((E62/D62)*100)-100 -> -3.5863815
A63: Viande | B63: JAMON PREMIUM VIANDE X 300 G X 15 UND | D63: ='JMN PREM VIANDÉ 300 G - 15 V2.'!I104 -> 0.36652172 | E63: 0.32965572 | F63: =((E63/D63)*100)-100 -> -10.05834
A64: Faizán | B64: MILANESA DE POLLO APANADA X 240 G - 2 UND | D64: ='MNESA APANADA 240 G 2 UNDS'!H61 -> 0.53818582 | E64: 0.53431082 | F64: =((E64/D64)*100)-100 -> -0.72001148
A65: Faizán | B65: MILANESA DE POLLO APANADA X 600 G - 5 UND | D65: ='MNESA APANADA 600 G 5 UNDS'!H61 -> 0.72094191 | E65: 0.71697673 | F65: =((E65/D65)*100)-100 -> -0.55000035
A66: Faizán | B66: MILANESA DE POLLO APANADA X 1.800 G - 15 UND | D66: ='MNESA APANADA 1800 G 15 UND'!H61 -> 0.4146307 | E66: 0.40061934 | F66: =((E66/D66)*100)-100 -> -3.3792393
A67: Marca | B67: Línea PRERFORMADOS | C67: MB - JUNIO COSTOS | D67: MB - JUNIO | E67: MB - MAY | F67: %
A68: Faizán | B68: HAMBURGUESAS (BOLSA ROJA) X 900 G - 10 UND | D68: ='HSA 900 G - 10 UNDS'!I43 -> 0.21058802 | E68: 0.17134734 | F68: =((E68/D68)*100)-100 -> -18.633858
A69: Faizán | B69: HAMBURGUESAS (CAJA) X 2700 G - 30 UND | D69: ='HSA cja 2700 G - 30 UNDS'!H48 -> 0.51039764 | E69: 0.51544719 | F69: =((E69/D69)*100)-100 -> 0.98933762
A70: Faizán | B70: HAMBURGUESA X 450 G - 5 UND | D70: ='HSA 450 G - 5 UNDS'!H43 -> 0.54109051 | E70: 0.53917225 | F70: =((E70/D70)*100)-100 -> -0.3545169
A71: Faizán | B71: HAMBURGUESA DE POLLO X 1425 X 15 UND | D71: ='HSA POLLO 1425 X 15 '!H37 -> 0.48256038 | E71: 0.46642613 | F71: =((E71/D71)*100)-100 -> -3.3434677
A72: Faizán | B72: HAMBURGUESA DE POLLO X 750 5 UND | D72: ='HSA POLLO 750 X5'!H38 -> 0.42336231 | E72: 0.40684806
A73: Faizán | B73: HAMBURGUESA DE POLLO X 1500 X 10 UND | D73: ='HSA POLLO 1500 X10'!H39 -> 0.45994617 | E73: 0.44399385 | F73: =((E73/D73)*100)-100 -> -3.4683015
A74: Marca | B74: Línea OFERTAS | C74: MB - JUNIO COSTOS | D74: MB - JUNIO | E74: MB - MAY | F74: %
A75: Viande | B75: SUPER COMBO VIANDE * 900 | D75: ='SÚPER COMBO VIANDÉ 900 G'!H34 -> 0.33424604 | E75: 0.29368743 | F75: =((E75/D75)*100)-100 -> -12.134358
A76: Faizán | B76: MEGA COMBO FAIZAN * 900 NUEVO CON JAMON 225 | D76: ='MEGA COMBO FAIZAN 900 G NUEVO'!H33 -> 0.97784914 | E76: 0.4188608 | F76: =((E76/D76)*100)-100 -> -57.16509
A77: Faizán | B77: MEGA COMBO FAIZAN * 900 | D77: 41.31 | E77: 0.52917718 | F77: =((E77/D77)*100)-100 -> -98.719009
A78: Marca | B78: Línea TOCINOS | C78: MB - JUNIO COSTOS | D78: MB - JUNIO | E78: MB - MAY | F78: %
A79: Faizán | B79: TOCINO BARRIGUERO X 1 KG | D79: ='TOCINO BARRIGUERO 1KG'!F76 -> 0.53795251 | E79: 0.4884537 | F79: =((E79/D79)*100)-100 -> -9.2013334
A80: Faizán | B80: TOCINO PAPADA X 1 KG | C80: 49.28 | D80: ='TOCINO PAPADA 1KG'!F76 -> 0.48791509 | E80: 0.41959614 | F80: =((E80/D80)*100)-100 -> -14.002222
A81: Faizán | B81: TOCINETA REESTRUCTURADA X 150 GRS | D81: ='TOCINETA X 150 RX'!G51 -> 0.52149942 | E81: 0.52511027 | F81: =((E81/D81)*100)-100 -> 0.6923962
B82: TOCINETA REESTRUCTURADA X 400 GRS | D82: ='TOCINETAx 400 rx'!G51 -> 0.52301673 | E82: 0.52467204
A83: Faizán | B83: TOCINETA REESTRUCTURADA X 1000 KG | D83: ='TOCINETA X 1000 GRS RX'!G51 -> 0.48105306 | E83: 0.48229059 | F83: =((E83/D83)*100)-100 -> 0.25725396
A84: Marca | B84: Línea Especiales | C84: MB - JUNIO COSTOS | D84: MB - JUNIO | E84: MB - MAY | F84: %
A85: Faizán | B85: PERNIL NAVIDEÑO

Sheet CERVECERO 500
B2: CERVECERO FAIZAN X 500 G
K3: 1 Und | L3: Q Batch
B4: CÓDIGO | C4: DESCRIPCIÓN | D4: CATIDAD | E4: % | F4: =+'CIF Y PV'!$F$2 -> JUN-COP/Kg | G4: =+'CIF Y PV'!$G$2 -> JUN-COP/APP | H4: =+'CIF Y PV'!$H$2 -> MAY-COP/Kg | I4: =+'CIF Y PV'!$I$2 -> MAY-COP/APP | J4: % | K4: =+D22/1000 -> 0.5145 | L4: 2011.05
B5: =VLOOKUP(C5,[1]Hoja1!$B$2:$C$260,2,FALSE) -> 1112001 | C5: PASTA DE POLLO IMPORTADA PREMIUM | D5: 0.18012645 | E5: 35.01 | F5: =VLOOKUP(B5,[2]Hoja1!$C$2:$E$279,3,FALSE) -> 3663.96 | G5: =D5*F5 -> 659.97611 | H5: 4222.72 | I5: =H5*D5 -> 760.62356 | J5: =((F5/H5)*100)-100 -> -13.232229 | K5: =$K$4*E5% -> 0.18012645 | L5: =$L$4*E5 -> 70406.86 | M5: =L5*F5 -> 2.5796792e+08
B6: =VLOOKUP(C6,[1]Hoja1!$B$2:$C$260,2,FALSE) -> 1121009 | C6: TOCINO NACIONAL | D6: 0.0225351 | E6: 4.38 | F6: =VLOOKUP(B6,[2]Hoja1!$C$2:$E$279,3,FALSE) -> 8741.62 | G6: =D6*F6 -> 196.99328 | I6: =H6*D6 -> 0 | K6: =$K$4*E6% -> 0.0225351 | L6: =$L$4*E6 -> 8808.399 | M6: =L6*F6 -> 76999677
B7: =VLOOKUP(C7,[1]Hoja1!$B$2:$C$260,2,FALSE) -> 1122007 | C7: RECORTE DE CERDO 80/20 IMPORTADO | D7: 0.04121145 | E7: 8.01 | F7: =VLOOKUP(B7,[2]Hoja1!$C$2:$E$279,3,FALSE) -> 11229.33 | G7: =D7*F7 -> 462.77697 | I7: =H7*D7 -> 0 | K7: =$K$4*E7% -> 0.04121145 | L7: =$L$4*E7 -> 16108.51 | M7: =L7*F7 -> 1.8088778e+08
B8: =VLOOKUP(C8,[1]Hoja1!$B$2:$C$260,2,FALSE) -> 2906001 | C8: EMULSION DE PIEL DE CERDO | D8: 0.0488775 | E8: 9.5 | F8: =VLOOKUP(B8,[2]Hoja1!$C$2:$E$279,3,FALSE) -> 1956.71 | G8: =D8*F8 -> 95.639093 | H8: 2033.73 | I8: =H8*D8 -> 99.403638 | J8: =((F8/H8)*100)-100 -> -3.7871301 | K8: =$K$4*E8% -> 0.0488775 | L8: =$L$4*E8 -> 19104.975 | M8: =L8*F8 -> 37382896
B9: =VLOOKUP(C9,[1]Hoja1!$B$2:$C$260,2,FALSE) -> 1131002 | C9: AGUA POTABLE | D9: 0.1402527 | E9: 27.26 | F9: =VLOOKUP(B9,[2]Hoja1!$C$2:$E$279,3,FALSE) -> 0 | G9: =D9*F9 -> 0 | H9: 0 | I9: =H9*D9 -> 0 | K9: =$K$4*E9% -> 0.1402527 | L9: =$L$4*E9 -> 54821.223 | M9: =L9*F9 -> 0
B10: 1210005 | C10: SAL YODADA REFISAL | D10: 0.004116 | E10: 0.8 | F10: =VLOOKUP(B10,[2]Hoja1!$C$2:$E$279,3,FALSE) -> 1356 | G10: =D10*F10 -> 5.581296 | K10: =$K$4*E10% -> 0.004116 | L10: =$L$4*E10 -> 1608.84
B11: 1210010 | C11: CLORURO DE POTASIO - KCL | D11: 0.00272685 | E11: 0.53 | F11: =VLOOKUP(B11,[2]Hoja1!$C$2:$E$279,3,FALSE) -> 11600 | G11: =D11*F11 -> 31.63146 | H11: 8910.1 | I11: =H11*D11 -> 24.296506 | J11: =((F11/H11)*100)-100 -> 30.189336 | K11: =$K$4*E11% -> 0.00272685 | L11: =$L$4*E11 -> 1065.8565 | M11: =L11*F11 -> 12363935
B12: =VLOOKUP(C12,[1]Hoja1!$B$2:$C$260,2,FALSE) -> 1210004 | C12: SAL CURANTE AL 12 % | D12: 0.0008232 | E12: 0.16 | F12: =VLOOKUP(B12,[2]Hoja1!$C$2:$E$279,3,FALSE) -> 3841 | G12: =D12*F12 -> 3.1619112 | H12: 3508.01 | I12: =H12*D12 -> 2.8877938 | J12: =((F12/H12)*100)-100 -> 9.4922762 | K12: =$K$4*E12% -> 0.0008232 | L12: =$L$4*E12 -> 321.768 | M12: =L12*F12 -> 1235910.9
B13: =VLOOKUP(C13,[1]Hoja1!$B$2:$C$260,2,FALSE) -> 121007 | C13: SUPRA MEAT F451 | D13: 0.0002558365 | E13: 12 | F13: =VLOOKUP(B13,[2]Hoja1!$C$2:$E$279,3,FALSE) -> 16905 | G13: =D13*F13 -> 4.3249161 | H13: 16100 | I13: =H13*D13 -> 4.1189677 | J13: =((F13/H13)*100)-100 -> 5 | K13: =$K$4*E13% -> 0.06174 | L13: =$L$4*E13 -> 24132.6 | M13: =L13*F13 -> 407961603
B14: =VLOOKUP(C14,[1]Hoja1!$B$2:$C$260,2,FALSE) -> 1230003 | C14: PREPARADO SABOR CERVECERO NEO | D14: 0.0071941225 | E14: 1.3982745 | F14: =VLOOKUP(B14,[2]Hoja1!$C$2:$E$279,3,FALSE) -> 20099.99 | G14: =D14*F14 -> 144.60179 | H14: 19145.99 | I14: =H14*D14 -> 137.7386 | J14: =((F14/H14)*100)-100 -> 4.9827666 | K14: =$K$4*E14% -> 0.0071941225 | L14: =$L$4*E14 -> 2812 | M14: =L14*F14 -> 56521172
B15: =VLOOKUP(C15,[1]Hoja1!$B$2:$C$260,2,FALSE) -> 1220009 | C15: CEBOLLA EN POLVO | D15: 0.0002558365 | E15: 0.049725268 | F15: =VLOOKUP(B15,[2]Hoja1!$C$2:$E$279,3,FALSE) -> 21312.16 | G15: =D15*F15 -> 5.4524285 | H15: 20299 | I15: =H15*D15 -> 5.1932252 | J15: =((F15/H15)*100)-100 -> 4.9911818 | K15: =$K$4*E15% -> 0.0002558365 | L15: =$L$4*E15 -> 100 | M15: =L15*F15 -> 2131216
B16: =VLOOKUP(C16,[1]Hoja1!$B$2:$C$260,2,FALSE) -> 1220005 | C16: AJO MOLIDO DESHIDRATADO B.1 | D16: 0.0002558365 | E16: 0.049725268 | F16: =VLOOKUP(B16,[2]Hoja1!$C$2:$E$279,3,FALSE) -> 17429.99 | G16: =D16*F16 -> 4.4592277 | H16: 17430 | I16: =H16*D16 -> 4.4592303 | J16: =((F16/H16)*100)-100 -> -5.7372347e-05 | K16: =$K$4*E16% -> 0.0002558365 | L16: =$L$4*E16 -> 100 | M16: =L16*F16 -> 1742999
B17: =VLOOKUP(C17,[1]Hoja1!$B$2:$C$260,2,FALSE) -> 1260009 | C17: PROTEINA CONCENTRADA DE SOYA 70% | D17: 0.02046692 | E17: 3.9780214 | F17: =VLOOKUP(B17,[2]Hoja1!$C$2:$E$279,3,FALSE) -> 7033.69 | G17: =D17*F17 -> 143.95797 | H17: 9565.21 | I17: =H17*D17 -> 195.77039 | J17: =((F17/H17)*100)-100 -> -26.465911 | K17: =$K$4*E17% -> 0.02046692 | L17: =$L$4*E17 -> 8000 | M17: =L17*F17 -> 56269520
B18: =VLOOKUP(C18,[1]Hoja1!$B$2:$C$260,2,FALSE) -> 1260011 | C18: ALMIDON DE PAPA | D18: 0.04501875 | E18: 8.75 | F18: =VLOOKUP(B18,[2]Hoja1!$C$2:$E$279,3,FALSE) -> 4450.01 | G18: =D18*F18 -> 200.33389 | H18: 4500 | I18: =H18*D18 -> 202.58437 | J18: =((F18/H18)*100)-100 -> -1.1108889 | K18: =$K$4*E18% -> 0.04501875 | L18: =$L$4*E18 -> 17596.688 | M18: =L18*F18 -> 78305435
B19: =VLOOKUP(C19,[1]Hoja1!$B$2:$C$260,2,FALSE) -> 1270009 | C19: HUMO TRUSMOKE DRY x 20 KG | D19: 0.00048608936 | E19: 0.094478009 | F19: =VLOOKUP(B19,[2]Hoja1!$C$2:$E$279,3,FALSE) -> 57046.53 | G19: =D19*F19 -> 27.729711 | H19: 53849.37 | I19: =H19*D19 -> 26.175606 | J19: =((F19/H19)*100)-100 -> 5.9372282 | K19: =$K$4*E19% -> 0.00048608936 | L19: =$L$4*E19 -> 190 | M19: =L19*F19 -> 10838841
B20: TOTAL | D20: =SUM(D5:D19) -> 0.51460264 | E20: =SUM(E5:E19) -> 111.97022 | G20: =SUM(G5:G19) -> 1986.6201 | I20: =SUM(I5:I19) -> 1463.2519 | J20: =((G20/I20)*100)-100 -> 35.767469 | K20: =SUM(K5:K19) -> 0.57608681 | M20: =SUM(M5:M19) -> 1.1806089e+09
B22: MERMAS | D22: =+C25+(C25*C31%) -> 514.5
B23: Linea | C23: Salchichones
B24: Referencia | C24: Salchichón Cervecero Faizán
B25: Presentación en Gramos | C25: 500
B26: Máquina | C26: 0
B27: Cocción | C27: 0.2
B28: Frío | C28: 0.2
B29: Recorte | C29: 0.5
B30: Sobrepeso | C30: 2
B31: Merma Total | C31: =C30+C29+C28+C27 -> 2.9
B33: MATERIAL DE EMPAQUE
B34: CÓDIGO | C34: DESCRIPCIÓN | D34: CATIDAD | E34: =+'CIF Y PV'!$F$4 -> JUN-COP/UMB | F34: =+'CIF Y PV'!$G$4 -> JUN-COP/APP | G34: =+'CIF Y PV'!$H$4 -> MAY-COP/UMB | H34: =+'CIF Y PV'!$I$4 -> MAY-COP/APP | I34: % | J34: 30270
B35: 1380005 | C35: GRAPAS POLY- R-ID M 07-150 | D35: 2 | E35: =VLOOKUP(B35,[2]Hoja1!$C$2:$E$279,3,FALSE) -> 29.02 | F35: =E35*D35 -> 58.04 | G35: 31.68 | H35: =G35*D35 -> 63.36 | I35: =((E35/G35)*100)-100 -> -8.3964646 | J35: =J34*D35 -> 60540
B36: 1370016 | C36: TUBU SALCHICHON CERVECERO FAIZAN X 500G | D36: 0.28 | E36: =VLOOKUP(B36,[2]Hoja1!$C$2:$E$279,3,FALSE) -> 627.22 | F36: =E36*D36 -> 175.6216 | G36: 668.96 | H36: =G36*D36 -> 187.3088 | I36: =((E36/G36)*100)-100 -> -6.239536 | J36: =J34*D36 -> 8475.6
C37: TOTAL | F37: =SUM(F35:F36) -> 233.6616 | H37: =SUM(H35:H36) -> 250.6688 | I37: =((F37/H37)*100)-100 -> -6.7847295
F38: =+'CIF Y PV'!$G$1 -> MAYO
B39: TOTAL INSUMOS (UND 500 G) | D39: =+F37+G20 -> 2220.2817
B40: ASIGNACIÓN MOD/CIF | D40: =+('CIF Y PV'!C3/1000)*500 -> 945
B41: TOTAL COSTO POR UND (500) | D41: =+D39+D40 -> 3165.2817
B42: PRECIO DE VENTA | D42: ='CIF Y PV'!C57 -> 8337.654
B43: MB | F43: =+(D42-D41)/D42 -> 0.62036304
F45: 0.5643

Sheet CERVECERO 750
B2: CERVECERO FAIZAN X 750 G
K3: 1 UND | L3: 1 bacth
B4: CÓDIGO | C4: DESCRIPCIÓN | D4: CATIDAD | E4: % | F4: =+'CIF Y PV'!$F$2 -> JUN-COP/Kg | G4: =+'CIF Y PV'!$G$2 -> JUN-COP/APP | H4: =+'CIF Y PV'!$H$2 -> MAY-COP/Kg | I4: =+'CIF Y PV'!$I$2 -> MAY-COP/APP | J4: % | K4: =+D22/1000 -> 0.77175 | L4: 2011.05
B5: =VLOOKUP(C5,[1]Hoja1!$B$2:$C$260,2,FALSE) -> 1112001 | C5: PASTA DE POLLO IMPORTADA PREMIUM | D5: 0.27018968 | E5: 35.01 | F5: =VLOOKUP(B5,[2]Hoja1!$C$2:$E$279,3,FALSE) -> 3663.96 | G5: =D5*F5 -> 989.96416 | H5: 4222.72 | I5: =H5*D5 -> 1140.9353 | J5: =((F5/H5)*100)-100 -> -13.232229 | K5: =$K$4*E5% -> 0.27018968 | L5: =$L$4*E5 -> 70406.86
B6: =VLOOKUP(C6,[1]Hoja1!$B$2:$C$260,2,FALSE) -> 1121009 | C6: TOCINO NACIONAL | D6: 0.03380265 | E6: 4.38 | F6: =VLOOKUP(B6,[2]Hoja1!$C$2:$E$279,3,FALSE) -> 8741.62 | G6: =D6*F6 -> 295.48992 | H6: 2033.73 | I6: =H6*D6 -> 68.745463 | J6: =((F6/H6)*100)-100 -> 329.83189 | K6: =$K$4*E6% -> 0.03380265 | L6: =$L$4*E6 -> 8808.399
B7: =VLOOKUP(C7,[1]Hoja1!$B$2:$C$260,2,FALSE) -> 1122007 | C7: RECORTE DE CERDO 80/20 IMPORTADO | D7: 0.061817175 | E7: 8.01 | F7: =VLOOKUP(B7,[2]Hoja1!$C$2:$E$279,3,FALSE) -> 11229.33 | G7: =D7*F7 -> 694.16546 | H7: 0 | I7: =H7*D7 -> 0 | J7: =((F7/H7)*100)-100 -> #DIV/0! | K7: =$K$4*E7% -> 0.061817175 | L7: =$L$4*E7 -> 16108.51
B8: =VLOOKUP(C8,[1]Hoja1!$B$2:$C$260,2,FALSE) -> 2906001 | C8: EMULSION DE PIEL DE CERDO | D8: 0.07331625 | E8: 9.5 | F8: =VLOOKUP(B8,[2]Hoja1!$C$2:$E$279,3,FALSE) -> 1956.71 | G8: =D8*F8 -> 143.45864 | H8: 8910.1 | I8: =H8*D8 -> 653.25512 | J8: =((F8/H8)*100)-100 -> -78.039416 | K8: =$K$4*E8% -> 0.07331625 | L8: =$L$4*E8 -> 19104.975
B9: =VLOOKUP(C9,[1]Hoja1!$B$2:$C$260,2,FALSE) -> 1131002 | C9: AGUA POTABLE | D9: 0.21037905 | E9: 27.26 | F9: =VLOOKUP(B9,[2]Hoja1!$C$2:$E$279,3,FALSE) -> 0 | G9: =D9*F9 -> 0 | H9: 3508.01 | I9: =H9*D9 -> 738.01181 | J9: =((F9/H9)*100)-100 -> -100 | K9: =$K$4*E9% -> 0.21037905 | L9: =$L$4*E9 -> 54821.223
B10: 1210005 | C10: SAL YODADA REFISAL | D10: 0.006174 | E10: 0.8 | F10: =VLOOKUP(B10,[2]Hoja1!$C$2:$E$279,3,FALSE) -> 1356 | G10: =D10*F10 -> 8.371944 | K10: =$K$4*E10% -> 0.006174
B11: 1210010 | C11: CLORURO DE POTASIO - KCL | D11: 0.004090275 | E11: 0.53 | F11: =VLOOKUP(B11,[2]Hoja1!$C$2:$E$279,3,FALSE) -> 11600 | G11: =D11*F11 -> 47.44719 | H11: 16100 | I11: =H11*D11 -> 65.853427 | J11: =((F11/H11)*100)-100 -> -27.950311 | K11: =$K$4*E11% -> 0.004090275 | L11: =$L$4*E11 -> 1065.8565
B12: =VLOOKUP(C12,[1]Hoja1!$B$2:$C$260,2,FALSE) -> 1210004 | C12: SAL CURANTE AL 12 % | D12: 0.0012348 | E12: 0.16 | F12: =VLOOKUP(B12,[2]Hoja1!$C$2:$E$279,3,FALSE) -> 3841 | G12: =D12*F12 -> 4.7428668 | H12: 19145.99 | I12: =H12*D12 -> 23.641468 | J12: =((F12/H12)*100)-100 -> -79.938358 | K12: =$K$4*E12% -> 0.0012348 | L12: =$L$4*E12 -> 321.768
B13: =VLOOKUP(C13,[1]Hoja1!$B$2:$C$260,2,FALSE) -> 121007 | C13: SUPRA MEAT F451 | D13: 0.00038375475 | E13: 0.049725268 | F13: =VLOOKUP(B13,[2]Hoja1!$C$2:$E$279,3,FALSE) -> 16905 | G13: =D13*F13 -> 6.4873741 | H13: 20299 | I13: =H13*D13 -> 7.7898378 | J13: =((F13/H13)*100)-100 -> -16.720035 | K13: =$K$4*E13% -> 0.00038375475 | L13: =$L$4*E13 -> 100
B14: =VLOOKUP(C14,[1]Hoja1!$B$2:$C$260,2,FALSE) -> 1230003 | C14: PREPARADO SABOR CERVECERO NEO | D14: 0.010791184 | E14: 1.3982745 | F14: =VLOOKUP(B14,[2]Hoja1!$C$2:$E$279,3,FALSE) -> 20099.99 | G14: =D14*F14 -> 216.90268 | H14: 17430 | I14: =H14*D14 -> 188.09033 | J14: =((F14/H14)*100)-100 -> 15.318359 | K14: =$K$4*E14% -> 0.010791184 | L14: =$L$4*E14 -> 2812
B15: =VLOOKUP(C15,[1]Hoja1!$B$2:$C$260,2,FALSE) -> 1220009 | C15: CEBOLLA EN POLVO | D15: 0.00038375475 | E15: 0.049725268 | F15: =VLOOKUP(B15,[2]Hoja1!$C$2:$E$279,3,FALSE) -> 21312.16 | G15: =D15*F15 -> 8.1786427 | H15: 9565.21 | I15: =H15*D15 -> 3.6706948 | J15: =((F15/H15)*100)-100 -> 122.80912 | K15: =$K$4*E15% -> 0.00038375475 | L15: =$L$4*E15 -> 100
B16: =VLOOKUP(C16,[1]Hoja1!$B$2:$C$260,2,FALSE) -> 1220005 | C16: AJO MOLIDO DESHIDRATADO B.1 | D16: 0.00038375475 | E16: 0.049725268 | F16: =VLOOKUP(B16,[2]Hoja1!$C$2:$E$279,3,FALSE) -> 17429.99 | G16: =D16*F16 -> 6.6888415 | H16: 4500 | I16: =H16*D16 -> 1.7268964 | J16: =((F16/H16)*100)-100 -> 287.33311 | K16: =$K$4*E16% -> 0.00038375475 | L16: =$L$4*E16 -> 100
B17: =VLOOKUP(C17,[1]Hoja1!$B$2:$C$260,2,FALSE) -> 1260009 | C17: PROTEINA CONCENTRADA DE SOYA 70% | D17: 0.03070038 | E17: 3.9780214 | F17: =VLOOKUP(B17,[2]Hoja1!$C$2:$E$279,3,FALSE) -> 7033.69 | G17: =D17*F17 -> 215.93696 | H17: 12278.37 | I17: =H17*D17 -> 376.95063 | J17: =((F17/H17)*100)-100 -> -42.71479 | K17: =$K$4*E17% -> 0.03070038 | L17: =$L$4*E17 -> 8000
B18: =VLOOKUP(C18,[1]Hoja1!$B$2:$C$260,2,FALSE) -> 1260011 | C18: ALMIDON DE PAPA | D18: 0.067528125 | E18: 8.75 | F18: =VLOOKUP(B18,[2]Hoja1!$C$2:$E$279,3,FALSE) -> 4450.01 | G18: =D18*F18 -> 300.50083 | H18: 53849.37 | I18: =H18*D18 -> 3636.347 | J18: =((F18/H18)*100)-100 -> -91.736189 | K18: =$K$4*E18% -> 0.067528125 | L18: =$L$4*E18 -> 17596.688
B19: =VLOOKUP(C19,[1]Hoja1!$B$2:$C$260,2,FALSE) -> 1270009 | C19: HUMO TRUSMOKE DRY x 20 KG | D19: 0.00072913403 | E19: 0.094478009 | F19: =VLOOKUP(B19,[2]Hoja1!$C$2:$E$279,3,FALSE) -> 57046.53 | G19: =D19*F19 -> 41.594567 | I19: =#REF!*D19 -> #REF! | J19: =((F19/#REF!)*100)-100 -> #REF! | K19: =$K$4*E19% -> 0.00072913403 | L19: =$L$4*E19 -> 190
B20: TOTAL | D20: =SUM(D5:D19) -> 0.77190396 | E20: =SUM(E5:E19) -> 100.01995 | G20: =SUM(G5:G19) -> 2979.9301 | I20: =SUM(I5:I19) -> #REF! | J20: =((G20/I20)*100)-100 -> #REF! | L20: =SUM(L5:L19) -> 199536.28
B22: MERMAS | D22: =+C25+(C25*C31%) -> 771.75
B23: Linea | C23: Salchichones
B24: Referencia | C24: Salchichón Cervecero Faizán
B25: Presentación en Gramos | C25: 750
B26: Máquina | C26: 0
B27: Cocción | C27: 0.3
B28: Frío | C28: 0.3
B29: Recorte | C29: 0.3
B30: Sobrepeso | C30: 2
B31: Merma Total | C31: =C30+C29+C28+C27 -> 2.9
B33: MATERIAL DE EMPAQUE
B34: CÓDIGO | C34: DESCRIPCIÓN | D34: CATIDAD | E34: =+'CIF Y PV'!$F$4 -> JUN-COP/UMB | F34: =+'CIF Y PV'!$G$4 -> JUN-COP/APP | G34: =+'CIF Y PV'!$H$4 -> MAY-COP/UMB | H34: =+'CIF Y PV'!$I$4 -> MAY-COP/APP | I34: % | J34: 14931
B35: 1380005 | C35: GRAPAS POLY- R-ID M 07-150 | D35: 2 | E35: =VLOOKUP(B35,[2]Hoja1!$C$2:$E$279,3,FALSE) -> 29.02 | F35: =D35*E35 -> 58.04 | G35: 31.68 | H35: =G35*D35 -> 63.36 | I35: =((E35/G35)*100)-100 -> -8.3964646 | J35: =J34*D35 -> 29862
B36: 1380003 | C36: LAZOS POLY-CLIP GSA20 | D36: 1 | E36: =VLOOKUP(B36,[2]Hoja1!$C$2:$E$279,3,FALSE) -> 56.19 | F36: =D36*E36 -> 56.19 | G36: 57.87 | H36: =G36*D36 -> 57.87 | I36: =((E36/G36)*100)-100 -> -2.9030586 | J36: =J34*D36 -> 14931
B37: 1370015 | C37: TUBU SALCHICHON CERVECERO FAIZAN 750G | D37: 0.39 | E37: =VLOOKUP(B37,[2]Hoja1!$C$2:$E$279,3,FALSE) -> 552.94 | F37: =D37*E37 -> 215.6466 | G37: 555.72 | H37: =G37*D37 -> 216.7308 | I37: =((E37/G37)*100)-100 -> -0.50025193 | J37: =J34*D37 -> 5823.09
C38: TOTAL | F38: =SUM(F35:F37) -> 329.8766 | H38: =SUM(H35:H37) -> 337.9608 | I38: =((F38/H38)*100)-100 -> -2.3920526
H39: =+'CIF Y PV'!$G$1 -> MAYO
B40: TOTAL INSUMOS (UND 750 G) | H40: =+F38+G20 -> 3309.8067
B41: ASIGNACIÓN MOD/CIF | H41: =+('CIF Y PV'!C3/1000)*750 -> 1417.5
B42: TOTAL COSTO POR UND (750) | H42: =+H41+H40 -> 4727.3067
B43: PRECIO DE VENTA | H43: ='CIF Y PV'!C58 -> 11287.901
B44: MB | H44: =+(H43-H42)/H43 -> 0.58120586

Sheet CERVECERO 1300
B2: CERVECERO FAIZAN X 1300 G
B4: CÓDIGO | C4: DESCRIPCIÓN | D4: CATIDAD | E4: % | F4: =+'CIF Y PV'!$F$2 -> JUN-COP/Kg | G4: =+'CIF Y PV'!$G$2 -> JUN-COP/APP | H4: =+'CIF Y PV'!$H$2 -> MAY-COP/Kg | I4: =+'CIF Y PV'!$I$2 -> MAY-COP/APP | J4: % | K4: =+D22/1000 -> 1.3286
B5: =VLOOKUP(C5,[1]Hoja1!$B$2:$C$260,2,FALSE) -> 1112001 | C5: PASTA DE POLLO IMPORTADA PREMIUM | D5: 0.46514286 | E5: 35.01 | F5: =VLOOKUP(B5,[2]Hoja1!$C$2:$E$279,3,FALSE) -> 3663.96 | G5: =D5*F5 -> 1704.2648 | H5: 4222.72 | I5: =H5*D5 -> 1964.1681 | J5: =((F5/H5)*100)-100 -> -13.232229 | K5: =$K$4*E5% -> 0.46514286
B6: =VLOOKUP(C6,[1]Hoja1!$B$2:$C$260,2,FALSE) -> 1121009 | C6: TOCINO NACIONAL | D6: 0.05819268 | E6: 4.38 | F6: =VLOOKUP(B6,[2]Hoja1!$C$2:$E$279,3,FALSE) -> 8741.62 | G6: =D6*F6 -> 508.6983 | H6: 2033.73 | I6: =H6*D6 -> 118.3482 | J6: =((F6/H6)*100)-100 -> 329.83189 | K6: =$K$4*E6% -> 0.05819268
B7: =VLOOKUP(C7,[1]Hoja1!$B$2:$C$260,2,FALSE) -> 1122007 | C7: RECORTE DE CERDO 80/20 IMPORTADO | D7: 0.10642086 | E7: 8.01 | F7: =VLOOKUP(B7,[2]Hoja1!$C$2:$E$279,3,FALSE) -> 11229.33 | G7: =D7*F7 -> 1195.035 | H7: 0 | I7: =H7*D7 -> 0 | J7: =((F7/H7)*100)-100 -> #DIV/0! | K7: =$K$4*E7% -> 0.10642086
B8: =VLOOKUP(C8,[1]Hoja1!$B$2:$C$260,2,FALSE) -> 2906001 | C8: EMULSION DE PIEL DE CERDO | D8: 0.126217 | E8: 9.5 | F8: =VLOOKUP(B8,[2]Hoja1!$C$2:$E$279,3,FALSE) -> 1956.71 | G8: =D8*F8 -> 246.97007 | H8: 8910.1 | I8: =H8*D8 -> 1124.6061 | J8: =((F8/H8)*100)-100 -> -78.039416 | K8: =$K$4*E8% -> 0.126217
B9: =VLOOKUP(C9,[1]Hoja1!$B$2:$C$260,2,FALSE) -> 1131002 | C9: AGUA POTABLE | D9: 0.36217636 | E9: 27.26 | F9: =VLOOKUP(B9,[2]Hoja1!$C$2:$E$279,3,FALSE) -> 0 | G9: =D9*F9 -> 0 | H9: 3508.01 | I9: =H9*D9 -> 1270.5183 | J9: =((F9/H9)*100)-100 -> -100 | K9: =$K$4*E9% -> 0.36217636
B10: 1210005 | C10: SAL YODADA REFISAL | D10: 0.0106288 | E10: 0.8 | F10: =VLOOKUP(B10,[2]Hoja1!$C$2:$E$279,3,FALSE) -> 1356 | G10: =D10*F10 -> 14.412653 | H10: 3508.01 | K10: =$K$4*E10% -> 0.0106288
B11: 1210010 | C11: CLORURO DE POTASIO - KCL | D11: 0.00704158 | E11: 0.53 | F11: =VLOOKUP(B11,[2]Hoja1!$C$2:$E$279,3,FALSE) -> 11600 | G11: =D11*F11 -> 81.682328 | H11: 16100 | I11: =H11*D11 -> 113.36944 | J11: =((F11/H11)*100)-100 -> -27.950311 | K11: =$K$4*E11% -> 0.00704158
B12: =VLOOKUP(C12,[1]Hoja1!$B$2:$C$260,2,FALSE) -> 1210004 | C12: SAL CURANTE AL 12 % | D12: 0.00212576 | E12: 0.16 | F12: =VLOOKUP(B12,[2]Hoja1!$C$2:$E$279,3,FALSE) -> 3841 | G12: =D12*F12 -> 8.1650442 | H12: 19145.99 | I12: =H12*D12 -> 40.69978 | J12: =((F12/H12)*100)-100 -> -79.938358 | K12: =$K$4*E12% -> 0.00212576
B13: =VLOOKUP(C13,[1]Hoja1!$B$2:$C$260,2,FALSE) -> 121007 | C13: SUPRA MEAT F451 | D13: 0.00066064991 | E13: 0.049725268 | F13: =VLOOKUP(B13,[2]Hoja1!$C$2:$E$279,3,FALSE) -> 16905 | G13: =D13*F13 -> 11.168287 | H13: 20299 | I13: =H13*D13 -> 13.410533 | J13: =((F13/H13)*100)-100 -> -16.720035 | K13: =$K$4*E13% -> 0.00066064991
B14: =VLOOKUP(C14,[1]Hoja1!$B$2:$C$260,2,FALSE) -> 1230003 | C14: PREPARADO SABOR CERVECERO NEO | D14: 0.018577475 | E14: 1.3982745 | F14: =VLOOKUP(B14,[2]Hoja1!$C$2:$E$279,3,FALSE) -> 20099.99 | G14: =D14*F14 -> 373.40707 | H14: 17430 | I14: =H14*D14 -> 323.8054 | J14: =((F14/H14)*100)-100 -> 15.318359 | K14: =$K$4*E14% -> 0.018577475
B15: =VLOOKUP(C15,[1]Hoja1!$B$2:$C$260,2,FALSE) -> 1220009 | C15: CEBOLLA EN POLVO | D15: 0.00066064991 | E15: 0.049725268 | F15: =VLOOKUP(B15,[2]Hoja1!$C$2:$E$279,3,FALSE) -> 21312.16 | G15: =D15*F15 -> 14.079877 | H15: 9565.21 | I15: =H15*D15 -> 6.3192551 | J15: =((F15/H15)*100)-100 -> 122.80912 | K15: =$K$4*E15% -> 0.00066064991
B16: =VLOOKUP(C16,[1]Hoja1!$B$2:$C$260,2,FALSE) -> 1220005 | C16: AJO MOLIDO DESHIDRATADO B.1 | D16: 0.00066064991 | E16: 0.049725268 | F16: =VLOOKUP(B16,[2]Hoja1!$C$2:$E$279,3,FALSE) -> 17429.99 | G16: =D16*F16 -> 11.515121 | H16: 4500 | I16: =H16*D16 -> 2.9729246 | J16: =((F16/H16)*100)-100 -> 287.33311 | K16: =$K$4*E16% -> 0.00066064991
B17: =VLOOKUP(C17,[1]Hoja1!$B$2:$C$260,2,FALSE) -> 1260009 | C17: PROTEINA CONCENTRADA DE SOYA 70% | D17: 0.052851993 | E17: 3.9780214 | F17: =VLOOKUP(B17,[2]Hoja1!$C$2:$E$279,3,FALSE) -> 7033.69 | G17: =D17*F17 -> 371.74453 | H17: 12278.37 | I17: =H17*D17 -> 648.93632 | J17: =((F17/H17)*100)-100 -> -42.71479 | K17: =$K$4*E17% -> 0.052851993
B18: =VLOOKUP(C18,[1]Hoja1!$B$2:$C$260,2,FALSE) -> 1260011 | C18: ALMIDON DE PAPA | D18: 0.1162525 | E18: 8.75 | F18: =VLOOKUP(B18,[2]Hoja1!$C$2:$E$279,3,FALSE) -> 4450.01 | G18: =D18*F18 -> 517.32479 | H18: 53849.37 | I18: =H18*D18 -> 6260.1239 | J18: =((F18/H18)*100)-100 -> -91.736189 | K18: =$K$4*E18% -> 0.1162525
B19: =VLOOKUP(C19,[1]Hoja1!$B$2:$C$260,2,FALSE) -> 1270009 | C19: HUMO TRUSMOKE DRY x 20 KG | D19: 0.0012552348 | E19: 0.094478009 | F19: =VLOOKUP(B19,[2]Hoja1!$C$2:$E$279,3,FALSE) -> 57046.53 | G19: =D19*F19 -> 71.606791 | H19: 8850.84 | I19: =H19*D19 -> 11.109883 | J19: =((F19/H19)*100)-100 -> 544.53238 | K19: =$K$4*E19% -> 0.0012552348
B20: TOTAL | D20: =SUM(D5:D19) -> 1.3288651 | E20: =SUM(E5:E19) -> 100.01995 | G20: =SUM(G5:G19) -> 5130.0746 | I20: =SUM(I5:I19) -> 11898.388 | J20: =((G20/I20)*100)-100 -> -56.884289
B22: MERMAS | D22: =+C25+(C25*C31%) -> 1328.6
B23: Linea | C23: Salchichones
B24: Referencia | C24: Salchichón Cervecero Faizán
B25: Presentación en Gramos | C25: 1300
B26: Máquina | C26: 0
B27: Cocción | C27: 0.5
B28: Frío | C28: 0.5
B29: Recorte | C29: 0.5
B30: Sobrepeso | C30: 0.7
B31: Merma Total | C31: =C30+C29+C28+C27 -> 2.2
B33: MATERIAL DE EMPAQUE
B34: CÓDIGO | C34: DESCRIPCIÓN | D34: CATIDAD | E34: =+'CIF Y PV'!$F$4 -> JUN-COP/UMB | F34: =+'CIF Y PV'!$G$4 -> JUN-COP/APP | G34: =+'CIF Y PV'!$H$4 -> MAY-COP/UMB | H34: =+'CIF Y PV'!$I$4 -> MAY-COP/APP | I34: % | J34: 4119
B35: 1380005 | C35: GRAPAS POLY- R-ID M 07-150 | D35: 2 | E35: =VLOOKUP(B35,[2]Hoja1!$C$2:$E$279,3,FALSE) -> 29.02 | F35: =D35*E35 -> 58.04 | G35: 31.68 | H35: =G35*D35 -> 63.36 | I35: =((E35/G35)*100)-100 -> -8.3964646 | J35: =J34*D35 -> 8238
B36: 1380003 | C36: LAZOS POLY-CLIP GSA20 | D36: 1 | E36: =VLOOKUP(B36,[2]Hoja1!$C$2:$E$279,3,FALSE) -> 56.19 | F36: =D36*E36 -> 56.19 | G36: 57.87 | H36: =G36*D36 -> 57.87 | I36: =((E36/G36)*100)-100 -> -2.9030586 | J36: =J34*D36 -> 4119
B37: 1370025 | C37: TUBU SALCHICHON CERVECERO FAIZAN X 1300G | D37: 0.59 | E37: =VLOOKUP(B37,[2]Hoja1!$C$2:$E$279,3,FALSE) -> 555.04 | F37: =D37*E37 -> 327.4736 | G37: 600.8 | H37: =G37*D37 -> 354.472 | I37: =((E37/G37)*100)-100 -> -7.6165113 | J37: =J34*D37 -> 2430.21
C38: TOTAL | F38: =SUM(F35:F37) -> 441.7036 | H38: =SUM(H35:H37) -> 475.702 | I38: =((F38/H38)*100)-100 -> -7.1469954
H39: =+'CIF Y PV'!$G$1 -> MAYO
B40: TOTAL INSUMOS (UND 1300 G) | H40: =F38+G20 -> 5571.7782
B41: ASIGNACIÓN MOD/CIF | H41: =+('CIF Y PV'!C3/1000)*1300 -> 2457
B42: TOTAL COSTO POR UND (1300) | H42: =+H40+H41 -> 8028.7782
B43: PRECIO DE VENTA | H43: ='CIF Y PV'!C56 -> 17701.481
B44: MB | H44: =+(H43-H42)/H43 -> 0.54643466 | K44: =1-K43 -> 1

Sheet CERVECERO 1500
B2: CERVECERO FAIZAN X 1500 G
B4: CÓDIGO | C4: DESCRIPCIÓN | D4: CATIDAD | E4: % | F4: =+'CIF Y PV'!$F$2 -> JUN-COP/Kg | G4: =+'CIF Y PV'!$G$2 -> JUN-COP/APP | H4: =+'CIF Y PV'!$H$2 -> MAY-COP/Kg | I4: =+'CIF Y PV'!$I$2 -> MAY-COP/APP | J4: % | K4: =+D22/1000 -> 1.533
B5: =VLOOKUP(C5,[1]Hoja1!$B$2:$C$260,2,FALSE) -> 1112001 | C5: PASTA DE POLLO IMPORTADA PREMIUM | D5: 0.5367033 | E5: 35.01 | F5: =VLOOKUP(B5,[2]Hoja1!$C$2:$E$279,3,FALSE) -> 3663.96 | G5: =D5*F5 -> 1966.4594 | H5: 4222.72 | I5: =H5*D5 -> 2266.3478 | J5: =((F5/H5)*100)-100 -> -13.232229 | K5: =$K$4*E5% -> 0.5367033
B6: =VLOOKUP(C6,[1]Hoja1!$B$2:$C$260,2,FALSE) -> 1121009 | C6: TOCINO NACIONAL | D6: 0.0671454 | E6: 4.38 | F6: =VLOOKUP(B6,[2]Hoja1!$C$2:$E$279,3,FALSE) -> 8741.62 | G6: =D6*F6 -> 586.95957 | H6: 2033.73 | I6: =H6*D6 -> 136.55561 | J6: =((F6/H6)*100)-100 -> 329.83189 | K6: =$K$4*E6% -> 0.0671454
B7: =VLOOKUP(C7,[1]Hoja1!$B$2:$C$260,2,FALSE) -> 1122007 | C7: RECORTE DE CERDO 80/20 IMPORTADO | D7: 0.1227933 | E7: 8.01 | F7: =VLOOKUP(B7,[2]Hoja1!$C$2:$E$279,3,FALSE) -> 11229.33 | G7: =D7*F7 -> 1378.8865 | H7: 0 | I7: =H7*D7 -> 0 | J7: =((F7/H7)*100)-100 -> #DIV/0! | K7: =$K$4*E7% -> 0.1227933
B8: =VLOOKUP(C8,[1]Hoja1!$B$2:$C$260,2,FALSE) -> 2906001 | C8: EMULSION DE PIEL DE CERDO | D8: 0.145635 | E8: 9.5 | F8: =VLOOKUP(B8,[2]Hoja1!$C$2:$E$279,3,FALSE) -> 1956.71 | G8: =D8*F8 -> 284.96546 | H8: 8910.1 | I8: =H8*D8 -> 1297.6224 | J8: =((F8/H8)*100)-100 -> -78.039416 | K8: =$K$4*E8% -> 0.145635
B9: =VLOOKUP(C9,[1]Hoja1!$B$2:$C$260,2,FALSE) -> 1131002 | C9: AGUA POTABLE | D9: 0.4178958 | E9: 27.26 | F9: =VLOOKUP(B9,[2]Hoja1!$C$2:$E$279,3,FALSE) -> 0 | G9: =D9*F9 -> 0 | H9: 3508.01 | I9: =H9*D9 -> 1465.9826 | J9: =((F9/H9)*100)-100 -> -100 | K9: =$K$4*E9% -> 0.4178958
B10: 1210005 | C10: SAL YODADA REFISAL | D10: 0.012264 | E10: 0.8 | F10: =VLOOKUP(B10,[2]Hoja1!$C$2:$E$279,3,FALSE) -> 1356 | G10: =D10*F10 -> 16.629984 | K10: =$K$4*E10% -> 0.012264
B11: 1210010 | C11: CLORURO DE POTASIO - KCL | D11: 0.0081249 | E11: 0.53 | F11: =VLOOKUP(B11,[2]Hoja1!$C$2:$E$279,3,FALSE) -> 11600 | G11: =D11*F11 -> 94.24884 | H11: 16100 | I11: =H11*D11 -> 130.81089 | J11: =((F11/H11)*100)-100 -> -27.950311 | K11: =$K$4*E11% -> 0.0081249
B12: =VLOOKUP(C12,[1]Hoja1!$B$2:$C$260,2,FALSE) -> 1210004 | C12: SAL CURANTE AL 12 % | D12: 0.0024528 | E12: 0.16 | F12: =VLOOKUP(B12,[2]Hoja1!$C$2:$E$279,3,FALSE) -> 3841 | G12: =D12*F12 -> 9.4212048 | H12: 19145.99 | I12: =H12*D12 -> 46.961284 | J12: =((F12/H12)*100)-100 -> -79.938358 | K12: =$K$4*E12% -> 0.0024528
B13: =VLOOKUP(C13,[1]Hoja1!$B$2:$C$260,2,FALSE) -> 121007 | C13: SUPRA MEAT F451 | D13: 0.00076228836 | E13: 0.049725268 | F13: =VLOOKUP(B13,[2]Hoja1!$C$2:$E$279,3,FALSE) -> 16905 | G13: =D13*F13 -> 12.886485 | H13: 20299 | I13: =H13*D13 -> 15.473691 | J13: =((F13/H13)*100)-100 -> -16.720035 | K13: =$K$4*E13% -> 0.00076228836
B14: =VLOOKUP(C14,[1]Hoja1!$B$2:$C$260,2,FALSE) -> 1230003 | C14: PREPARADO SABOR CERVECERO NEO | D14: 0.021435549 | E14: 1.3982745 | F14: =VLOOKUP(B14,[2]Hoja1!$C$2:$E$279,3,FALSE) -> 20099.99 | G14: =D14*F14 -> 430.85431 | H14: 17430 | I14: =H14*D14 -> 373.62161 | J14: =((F14/H14)*100)-100 -> 15.318359 | K14: =$K$4*E14% -> 0.021435549
B15: =VLOOKUP(C15,[1]Hoja1!$B$2:$C$260,2,FALSE) -> 1220009 | C15: CEBOLLA EN POLVO | D15: 0.00076228836 | E15: 0.049725268 | F15: =VLOOKUP(B15,[2]Hoja1!$C$2:$E$279,3,FALSE) -> 21312.16 | G15: =D15*F15 -> 16.246011 | H15: 9565.21 | I15: =H15*D15 -> 7.2914482 | J15: =((F15/H15)*100)-100 -> 122.80912 | K15: =$K$4*E15% -> 0.00076228836
B16: =VLOOKUP(C16,[1]Hoja1!$B$2:$C$260,2,FALSE) -> 1220005 | C16: AJO MOLIDO DESHIDRATADO B.1 | D16: 0.00076228836 | E16: 0.049725268 | F16: =VLOOKUP(B16,[2]Hoja1!$C$2:$E$279,3,FALSE) -> 17429.99 | G16: =D16*F16 -> 13.286678 | H16: 4500 | I16: =H16*D16 -> 3.4302976 | J16: =((F16/H16)*100)-100 -> 287.33311 | K16: =$K$4*E16% -> 0.00076228836
B17: =VLOOKUP(C17,[1]Hoja1!$B$2:$C$260,2,FALSE) -> 1260009 | C17: PROTEINA CONCENTRADA DE SOYA 70% | D17: 0.060983069 | E17: 3.9780214 | F17: =VLOOKUP(B17,[2]Hoja1!$C$2:$E$279,3,FALSE) -> 7033.69 | G17: =D17*F17 -> 428.936 | H17: 12278.37 | I17: =H17*D17 -> 748.77268 | J17: =((F17/H17)*100)-100 -> -42.71479 | K17: =$K$4*E17% -> 0.060983069
B18: =VLOOKUP(C18,[1]Hoja1!$B$2:$C$260,2,FALSE) -> 1260011 | C18: ALMIDON DE PAPA | D18: 0.1341375 | E18: 8.75 | F18: =VLOOKUP(B18,[2]Hoja1!$C$2:$E$279,3,FALSE) -> 4450.01 | G18: =D18*F18 -> 596.91322 | H18: 53849.37 | I18: =H18*D18 -> 7223.2199 | J18: =((F18/H18)*100)-100 -> -91.736189 | K18: =$K$4*E18% -> 0.1341375
B19: =VLOOKUP(C19,[1]Hoja1!$B$2:$C$260,2,FALSE) -> 1270009 | C19: HUMO TRUSMOKE DRY x 20 KG | D19: 0.0014483479 | E19: 0.094478009 | F19: =VLOOKUP(B19,[2]Hoja1!$C$2:$E$279,3,FALSE) -> 57046.53 | G19: =D19*F19 -> 82.623221 | H19: 8850.84 | I19: =H19*D19 -> 12.819095 | J19: =((F19/H19)*100)-100 -> 544.53238 | K19: =$K$4*E19% -> 0.0014483479
B20: TOTAL | D20: =SUM(D5:D19) -> 1.5333058 | E20: =SUM(E5:E19) -> 100.01995 | G20: =SUM(G5:G19) -> 5919.3169 | I20: =SUM(I5:I19) -> 13728.909 | J20: =((G20/I20)*100)-100 -> -56.884289
B22: MERMAS | D22: =+C25+(C25*C31%) -> 1533 | E22: ,.
B23: Linea | C23: Salchichones
B24: Referencia | C24: Salchichón Cervecero Faizán
B25: Presentación en Gramos | C25: 1500
B26: Máquina | C26: 0
B27: Cocción | C27: 0.5
B28: Frío | C28: 0.5
B29: Recorte | C29: 0.5
B30: Sobrepeso | C30: 0.7
B31: Merma Total | C31: =C30+C29+C28+C27 -> 2.2
B33: MATERIAL DE EMPAQUE
B34: CÓDIGO | C34: DESCRIPCIÓN | D34: CATIDAD | E34: =+'CIF Y PV'!$F$4 -> JUN-COP/UMB | F34: =+'CIF Y PV'!$G$4 -> JUN-COP/APP | G34: =+'CIF Y PV'!$H$4 -> MAY-COP/UMB | H34: =+'CIF Y PV'!$I$4 -> MAY-COP/APP | I34: % | J34: 34604
B35: 1380005 | C35: GRAPAS POLY- R-ID M 07-150 | D35: 2 | E35: =VLOOKUP(B35,[2]Hoja1!$C$2:$E$279,3,FALSE) -> 29.02 | F35: =D35*E35 -> 58.04 | G35: 31.68 | H35: =G35*D35 -> 63.36 | I35: =((E35/G35)*100)-100 -> -8.3964646 | J35: =J34*D35 -> 69208
B36: 1380003 | C36: LAZOS POLY-CLIP GSA20 | D36: 1 | E36: =VLOOKUP(B36,[2]Hoja1!$C$2:$E$279,3,FALSE) -> 56.19 | F36: =D36*E36 -> 56.19 | G36: 57.87 | H36: =G36*D36 -> 57.87 | I36: =((E36/G36)*100)-100 -> -2.9030586 | J36: =J34*D36 -> 34604
B37: 1370014 | C37: TUBU SALCHICHON CERVECERO FAIZAN 1500G | D37: 0.7 | E37: =VLOOKUP(B37,[2]Hoja1!$C$2:$E$279,3,FALSE) -> 555.02 | F37: =D37*E37 -> 388.514 | G37: 587.08 | H37: =G37*D37 -> 410.956 | I37: =((E37/G37)*100)-100 -> -5.4609253 | J37: =J34*D37 -> 24222.8
C38: TOTAL | F38: =SUM(F35:F37) -> 502.744 | H38: =SUM(H35:H37) -> 532.186 | I38: =((F38/H38)*100)-100 -> -5.5322763
H39: =+'CIF Y PV'!$G$1 -> MAYO
B40: TOTAL INSUMOS (UND 1500 G) | E40: 46.28 | H40: =F38+G20 -> 6422.0609
B41: ASIGNACIÓN MOD/CIF | H41: =+('CIF Y PV'!C3/1000)*1500 -> 2835
B42: TOTAL COSTO POR UND (1500) | H42: =+H40+H41 -> 9257.0609
B43: PRECIO DE VENTA | H43: ='CIF Y PV'!C55 -> 21036.542
B44: MB | H44: =+(H43-H42)/H43 -> 0.55995331 | K44: =1-K43 -> 1
E52: ='CERVECERO 1500'!H44 -> 0.55995331 | F52: 0.4981

Sheet SCHON CERV PREM X 50 G
B2: SCHON CERV PREM X 50 G
B4: CÓDIGO | C4: DESCRIPCIÓN | D4: CATIDAD | E4: % | F4: =+'CIF Y PV'!$F$2 -> JUN-COP/Kg | G4: =+'CIF Y PV'!$G$2 -> JUN-COP/APP | H4: =+'CIF Y PV'!$H$2 -> MAY-COP/Kg | I4: =+'CIF Y PV'!$I$2 -> MAY-COP/APP | J4: % | K4: =+D22/1000 -> 0.0705 | L4: 250
B5: =VLOOKUP(C5,[1]Hoja1!$B$2:$C$260,2,FALSE) -> 2903003 | C5: BRAZUELO CHARQUEADO | D5: 0.0388737 | E5: 55.14 | F5: =VLOOKUP(B5,[2]Hoja1!$C$2:$E$279,3,FALSE) -> 11506.13 | G5: =D5*F5 -> 447.28585 | H5: 14000 | I5: =H5*D5 -> 544.2318 | J5: =((F5/H5)*100)-100 -> -17.813357 | K5: =$K$4*E5% -> 0.0388737 | L5: =$L$4*E5% -> 137.85 | M5: =L5*F5 -> 1586120
B6: =VLOOKUP(C6,[1]Hoja1!$B$2:$C$260,2,FALSE) -> 1121009 | C6: TOCINO NACIONAL | D6: 0.01014495 | E6: 14.39 | F6: =VLOOKUP(B6,[2]Hoja1!$C$2:$E$279,3,FALSE) -> 8741.62 | G6: =D6*F6 -> 88.683298 | H6: 8754.28 | I6: =H6*D6 -> 88.811733 | J6: =((F6/H6)*100)-100 -> -0.14461498 | K6: =$K$4*E6% -> 0.01014495 | L6: =$L$4*E6% -> 35.975 | M6: =L6*F6 -> 314479.78
B7: =VLOOKUP(C7,[1]Hoja1!$B$2:$C$260,2,FALSE) -> 1131002 | C7: AGUA POTABLE | D7: 0.01746285 | E7: 24.77 | F7: =VLOOKUP(B7,[2]Hoja1!$C$2:$E$279,3,FALSE) -> 0 | G7: =D7*F7 -> 0 | H7: 0 | I7: =H7*D7 -> 0 | J7: =((F7/H7)*100)-100 -> #DIV/0! | K7: =$K$4*E7% -> 0.01746285 | L7: =$L$4*E7% -> 61.925 | M7: =L7*F7 -> 0
B8: =VLOOKUP(C8,[1]Hoja1!$B$2:$C$260,2,FALSE) -> 1250009 | C8: COLOR NATURAL ROJO AC150 | D8: 2.7072e-05 | E8: 0.0384 | F8: =VLOOKUP(B8,[2]Hoja1!$C$2:$E$279,3,FALSE) -> 83551.55 | G8: =D8*F8 -> 2.2619076 | H8: 71910.02 | I8: =H8*D8 -> 1.9467481 | J8: =((F8/H8)*100)-100 -> 16.189023 | K8: =$K$4*E8% -> 2.7072e-05 | L8: =$L$4*E8% -> 0.096 | M8: =L8*F8 -> 8020.9488
B9: =VLOOKUP(C9,[1]Hoja1!$B$2:$C$260,2,FALSE) -> 1250003 | C9: COLOR NATURAL HEMOGLOBINA I RED | D9: 4.23e-05 | E9: 0.06 | F9: =VLOOKUP(B9,[2]Hoja1!$C$2:$E$279,3,FALSE) -> 50952.79 | G9: =D9*F9 -> 2.155303 | H9: 47385.41 | I9: =H9*D9 -> 2.0044028 | J9: =((F9/H9)*100)-100 -> 7.5284354 | K9: =$K$4*E9% -> 4.23e-05 | L9: =$L$4*E9% -> 0.15 | M9: =L9*F9 -> 7642.9185
B10: =VLOOKUP(C10,[1]Hoja1!$B$2:$C$260,2,FALSE) -> 1210005 | C10: SAL YODADA REFISAL | D10: 0.0005076 | E10: 0.72 | F10: =VLOOKUP(B10,[2]Hoja1!$C$2:$E$279,3,FALSE) -> 1356 | G10: =D10*F10 -> 0.6883056 | H10: 8910.1 | I10: =H10*D10 -> 4.5227668 | J10: =((F10/H10)*100)-100 -> -84.781316 | K10: =$K$4*E10% -> 0.0005076 | L10: =$L$4*E10% -> 1.8 | M10: =L10*F10 -> 2440.8
B11: 1210010 | C11: CLORURO DE POTASIO - KCL | D11: 0.0003384 | E11: 0.48 | F11: =VLOOKUP(B11,[2]Hoja1!$C$2:$E$279,3,FALSE) -> 11600 | G11: =D11*F11 -> 3.92544 | K11: =$K$4*E11% -> 0.0003384 | L11: =$L$4*E11% -> 1.2 | M11: =L11*F11 -> 13920
B12: =VLOOKUP(C12,[1]Hoja1!$B$2:$C$260,2,FALSE) -> 1210004 | C12: SAL CURANTE AL 12 % | D12: 5.64e-05 | E12: 0.16 | F12: =VLOOKUP(B12,[2]Hoja1!$C$2:$E$279,3,FALSE) -> 3841 | G12: =D12*F12 -> 0.2166324 | H12: 3508.01 | I12: =H12*D12 -> 0.19785176 | J12: =((F12/H12)*100)-100 -> 9.4922762 | K12: =$K$4*E12% -> 0.0001128 | L12: =$L$4*E12% -> 0.4 | M12: =L12*F12 -> 1536.4
B13: 1240007 | C13: CONSERVANTE PROVIAN K | D13: 0.00020868 | E13: 0.296 | F13: =VLOOKUP(B13,[2]Hoja1!$C$2:$E$279,3,FALSE) -> 25921.42 | G13: =D13*F13 -> 5.4092819 | H13: 47900 | I13: =H13*D13 -> 9.995772 | J13: =((F13/H13)*100)-100 -> -45.884301 | K13: =$K$4*E13% -> 0.00020868 | L13: =$L$4*E13% -> 0.74 | M13: =L13*F13 -> 19181.851
B14: =VLOOKUP(C14,[1]Hoja1!$B$2:$C$260,2,FALSE) -> 1230009 | C14: PREPARADO SABOR CERVECERO PREMIUM SV LS | D14: 0.0014382 | E14: 2.04 | F14: =VLOOKUP(B14,[2]Hoja1!$C$2:$E$279,3,FALSE) -> 36960 | G14: =D14*F14 -> 53.155872 | H14: 47900 | I14: =H14*D14 -> 68.88978 | J14: =((F14/H14)*100)-100 -> -22.839248 | K14: =$K$4*E14% -> 0.0014382 | L14: =$L$4*E14% -> 5.1 | M14: =L14*F14 -> 188496
B15: =VLOOKUP(C15,[1]Hoja1!$B$2:$C$260,2,FALSE) -> 1210003 | C15: ERITORBATO DE SODIO | D15: 3.525e-05 | E15: 0.05 | F15: =VLOOKUP(B15,[2]Hoja1!$C$2:$E$279,3,FALSE) -> 16235.45 | G15: =D15*F15 -> 0.57229961 | H15: 12852.58 | K15: =$K$4*E15% -> 3.525e-05 | L15: =$L$4*E15% -> 0.125 | M15: =L15*F15 -> 2029.4313
B16: =VLOOKUP(C16,[1]Hoja1!$B$2:$C$260,2,FALSE) -> 1270004 | C16: HUMO TRUSMOKE OIL EX | D16: 1.692e-05 | E16: 0.024 | F16: =VLOOKUP(B16,[2]Hoja1!$C$2:$E$279,3,FALSE) -> 50662 | G16: =D16*F16 -> 0.85720104 | H16: 53849.37 | I16: =H16*D16 -> 0.91113134 | J16: =((F16/H16)*100)-100 -> -5.9190479 | K16: =$K$4*E16% -> 1.692e-05 | L16: =$L$4*E16% -> 0.06 | M16: =L16*F16 -> 3039.72
B17: =VLOOKUP(C17,[1]Hoja1!$B$2:$C$260,2,FALSE) -> 1260022 | C17: PROTEINA COLAGENICA ALTA FUNCIONALIDAD | D17: 0.0003384 | E17: 0.48 | F17: =VLOOKUP(B17,[2]Hoja1!$C$2:$E$279,3,FALSE) -> 22988.01 | G17: =D17*F17 -> 7.7791426 | H17: 27066.49 | I17: =H17*D17 -> 9.1593002 | J17: =((F17/H17)*100)-100 -> -15.068374 | K17: =$K$4*E17% -> 0.0003384 | L17: =$L$4*E17% -> 1.2 | M17: =L17*F17 -> 27585.612
B18: =VLOOKUP(C18,[1]Hoja1!$B$2:$C$260,2,FALSE) -> 1260009 | C18: PROTEINA CONCENTRADA DE SOYA 70% | D18: 0.000987 | E18: 1.4 | F18: =VLOOKUP(B18,[2]Hoja1!$C$2:$E$279,3,FALSE) -> 7033.69 | G18: =D18*F18 -> 6.942252 | H18: 9565.21 | I18: =H18*D18 -> 9.4408623 | J18: =((F18/H18)*100)-100 -> -26.465911 | K18: =$K$4*E18% -> 0.000987 | L18: =$L$4*E18% -> 3.5 | M18: =L18*F18 -> 24617.915
F19: =VLOOKUP(B19,[2]Hoja1!$C$2:$E$279,3,FALSE) -> #N/A | I19: =H19*D19 -> 0 | M19: =L19*F19 -> #N/A
B20: TOTAL | D20: =SUM(D5:D18) -> 0.070477722 | E20: =SUM(E5:E18) -> 100.0484 | G20: =SUM(G5:G18) -> 619.93278 | I20: =SUM(I5:I18) -> 740.11215 | J20: =((G20/I20)*100)-100 -> -16.237994 | M20: =SUM(M5:M18) -> 2199111.4
B22: MERMAS | D22: =+C25+(C25*C31%) -> 70.5
B23: Linea | C23: Salchichon
B24: Referencia | C24: Cervecerito
B25: Presentación en Gramos | C25: 50
B26: Máquina | C26: 0
B27: Cocción | C27: 9
B28: Frío | C28: 2
B29: Recorte | C29: 10
B30: Sobrepeso | C30: 20
B31: Merma Total | C31: =C30+C29+C28+C27 -> 41
B33: MATERIAL DE EMPAQUE
B34: CÓDIGO | C34: DESCRIPCIÓN | D34: CATIDAD | E34: =+'CIF Y PV'!$F$4 -> JUN-COP/UMB | F34: =+'CIF Y PV'!$G$4 -> JUN-COP/APP | G34: =+'CIF Y PV'!$H$4 -> MAY-COP/UMB | H34: =+'CIF Y PV'!$I$4 -> MAY-COP/APP | I34: % | J34: 4194
B35: 1370048 | C35: FIBROSA NALO P CLEAR 53 MM | D35: 0.035 | E35: =VLOOKUP(B35,[2]Hoja1!$C$2:$E$279,3,FALSE) -> 1806.94 | F35: =D35*E35 -> 63.2429 | G35: 1573.56 | H35: =G35*D35 -> 55.0746 | I35: =((E35/G35)*100)-100 -> 14.831338 | J35: =J34*D35 -> 146.79
B36: 1380003 | C36: LAZOS POLY-CLIP GSA20 | D36: 1 | E36: =VLOOKUP(B36,[2]Hoja1!$C$2:$E$279,3,FALSE) -> 56.19 | F36: =D36*E36 -> 56.19 | G36: 57.87 | H36: =G36*D36 -> 57.87 | I36: =((E36/G36)*100)-100 -> -2.9030586 | J36: =J35*D36 -> 146.79
B37: 1310018 | C37: LAM SUP TRANS ECOWEB M/PAUV 42U 301MM | D37: 0.0187 | E37: =VLOOKUP(B37,[2]Hoja1!$C$2:$E$279,3,FALSE) -> 478.26 | F37: =D37*E37 -> 8.943462 | G37: 503.51 | H37: =G37*D37 -> 9.415637 | I37: =((E37/G37)*100)-100 -> -5.0147961
B38: 1320004 | C38: LAM INFE SUDPACK GVA200 BT323 MM 8MM | D38: 0.0187 | E38: =VLOOKUP(B38,[2]Hoja1!$C$2:$E$279,3,FALSE) -> 1481.51 | F38: =D38*E38 -> 27.704237 | G38: 1575.9 | H38: =G38*D38 -> 29.46933 | I38: =((E38/G38)*100)-100 -> -5.9895932
B39: 1330043 | C39: ETI CERVECERITO 50 GR X 5 TAJ | D39: 1 | E39: =VLOOKUP(B39,[2]Hoja1!$C$2:$E$279,3,FALSE) -> 85.1 | F39: =E39*D39 -> 85.1 | G39: 85.28 | H39: =G39*D39 -> 85.28
B40: 1380005 | C40: GRAPAS POLY- R-ID M 07-150 | D40: 0.13 | E40: =VLOOKUP(B40,[2]Hoja1!$C$2:$E$279,3,FALSE) -> 29.02 | F40: =D40*E40 -> 3.7726 | G40: 31.68 | H40: =G40*D40 -> 4.1184 | I40: =((E40/G40)*100)-100 -> -8.3964646 | J40: =J36*D40 -> 19.0827
C41: TOTAL | F41: =SUM(F35:F40) -> 244.9532 | H41: =SUM(H35:H40) -> 241.22797 | I41: =((F41/H41)*100)-100 -> 1.5442787
H42: =+'CIF Y PV'!$G$1 -> MAYO
B43: TOTAL INSUMOS (UND 50 G) | H43: =+F41+G20 -> 864.88598
B44: ASIGNACIÓN MOD/CIF | H44: =+('CIF Y PV'!C3/1000)*50 -> 94.5
B45: TOTAL COSTO POR UND (50) | D45: 48.53 | H45: =+H43+H44 -> 959.38598
D46: 47.41 | I46: =1-#REF! -> #REF! | K46: =1-#REF! -> #REF!
D47: 32.65

Sheet OFTA CERV PREM X 6 UND
B2: OFTA CERV PREM X 6 UND X 300 G
B4: CÓDIGO | C4: DESCRIPCIÓN | D4: CATIDAD | E4: % | F4: =+'CIF Y PV'!$F$2 -> JUN-COP/Kg | G4: =+'CIF Y PV'!$G$2 -> JUN-COP/APP | H4: =+'CIF Y PV'!$H$2 -> MAY-COP/Kg | I4: =+'CIF Y PV'!$I$2 -> MAY-COP/APP | J4: %
B5: 30046 | C5: SALCHICHON CERVECERO PREMIUM X 50 G - 5 UND | D5: 6 | E5: =(D5*100)/$D$7 -> 100 | F5: ='SCHON CERV PREM X 50 G'!H45 -> 959.38598 | G5: =F5*D5 -> 5756.3159 | H5: 1150.4461 | I5: 6222 | J5: =((F5/H5)*100)-100 -> -16.60748
J6: =((F6/H6)*100)-100 -> #DIV/0!
B7: TOTAL | D7: =SUM(D5:D5) -> 6 | E7: =SUM(E5:E5) -> 100 | G7: =SUM(G5:G6) -> 5756.3159 | I7: =SUM(I5:I6) -> 6222 | J7: =((G7/I7)*100)-100 -> -7.4844763
B9: MERMAS
B10: Linea | C10: Ofertas
B11: Referencia | C11: Cervecero Premium
B12: Presentación en Gramos | C12: 300
B13: Máquina | C13: 0
B14: Cocción | C14: 0
B15: Frío | C15: 0
B16: Recorte | C16: 0
B17: Sobrepeso | C17: 0
B18: Merma Total | C18: =C17+C16+C15+C14 -> 0
B20: MATERIAL DE EMPAQUE
B21: CÓDIGO | C21: DESCRIPCIÓN | D21: CATIDAD | E21: =+'CIF Y PV'!$F$4 -> JUN-COP/UMB | F21: =+'CIF Y PV'!$G$4 -> JUN-COP/APP | G21: =+'CIF Y PV'!$H$4 -> MAY-COP/UMB | H21: =+'CIF Y PV'!$I$4 -> MAY-COP/APP
B22: 1340009 | C22: BOLSA CERVECERITO PREMIUM X 6U 16CMX22CM | D22: 1 | E22: =VLOOKUP(B22,[2]Hoja1!$C$2:$E$279,3,FALSE) -> 373.7 | F22: =D22*E22 -> 373.7 | G22: 372.57 | H22: =G22*D22 -> 372.57
C23: TOTAL | F23: =F22 -> 373.7 | H23: =SUM(H22) -> 372.57
H25: =+'CIF Y PV'!$G$1 -> MAYO
B26: TOTAL INSUMOS (UND 300G) | H26: =F23+G7 -> 6130.0159
B27: ASIGNACIÓN MOD/CIF | H27: 0
B28: TOTAL COSTO POR UND (300 G) | H28: =H27+H26 -> 6130.0159
B29: PRECIO DE VENTA | H29: ='CIF Y PV'!C6 -> 12007.44
B30: MB | H30: =+(H29-H28)/H29 -> 0.48948186

Sheet SCHA JUMBO X 1200 G
B2: SCHA JUMBO X 1200 G
M3: Batch
B4: CÓDIGO | C4: DESCRIPCIÓN | D4: CATIDAD | E4: % | F4: =+'CIF Y PV'!$F$2 -> JUN-COP/Kg | G4: =+'CIF Y PV'!$G$2 -> JUN-COP/APP | H4: =+'CIF Y PV'!$H$2 -> MAY-COP/Kg | I4: =+'CIF Y PV'!$I$2 -> MAY-COP/APP | J4: % | K4: =+D26/1000 -> 1.368 | L4: 250
B5: =VLOOKUP(C5,[1]Hoja1!$B$2:$C$260,2,FALSE) -> 1112001 | C5: PASTA DE POLLO IMPORTADA PREMIUM | D5: 0.342 | E5: 25 | F5: =VLOOKUP(B5,[2]Hoja1!$C$2:$E$279,3,FALSE) -> 3663.96 | G5: =F5*D5 -> 1253.0743 | H5: 4222.72 | I5: =H5*D5 -> 1444.1702 | J5: =((F5/H5)*100)-100 -> -13.232229 | K5: =$K$4*E5% -> 0.342 | L5: =$L$4*E5% -> 62.5 | M5: =L5*F5 -> 228997.5
B6: =VLOOKUP(C6,[1]Hoja1!$B$2:$C$260,2,FALSE) -> 1122001 | C6: BRAZUELO DE CERDO NACIONAL | D6: 0.30096 | E6: 22 | F6: =VLOOKUP(B6,[2]Hoja1!$C$2:$E$279,3,FALSE) -> 11506.13 | G6: =F6*D6 -> 3462.8849 | H6: 14000 | I6: =H6*D6 -> 4213.44 | J6: =((F6/H6)*100)-100 -> -17.813357 | K6: =$K$4*E6% -> 0.30096 | L6: =$L$4*E6% -> 55 | M6: =L6*F6 -> 632837.15
B7: 1122008 | C7: RECORTE CERDO 80/20 NAL EMULSIFICADOS | D7: 0.30096 | E7: 22 | F7: =VLOOKUP(B7,[2]Hoja1!$C$2:$E$279,3,FALSE) -> 12059.2 | G7: =F7*D7 -> 3629.3368 | H7: 12498.76 | I7: =H7*D7 -> 3761.6268 | J7: =((F7/H7)*100)-100 -> -3.5168289 | K7: =$K$4*E7% -> 0.30096 | L7: =$L$4*E7% -> 55 | M7: =L7*F7 -> 663256
B8: =VLOOKUP(C8,[1]Hoja1!$B$2:$C$260,2,FALSE) -> 1131002 | C8: AGUA POTABLE | D8: 0.2057472 | E8: 15.04 | F8: =VLOOKUP(B8,[2]Hoja1!$C$2:$E$279,3,FALSE) -> 0 | G8: =F8*D8 -> 0 | H8: 0 | I8: =H8*D8 -> 0 | J8: =((F8/H8)*100)-100 -> #DIV/0! | K8: =$K$4*E8% -> 0.2057472 | L8: =$L$4*E8% -> 37.6 | M8: =L8*F8 -> 0
B9: =VLOOKUP(C9,[1]Hoja1!$B$2:$C$260,2,FALSE) -> 1270004 | C9: HUMO TRUSMOKE OIL EX | D9: 0.0005472 | E9: 0.04 | F9: =VLOOKUP(B9,[2]Hoja1!$C$2:$E$279,3,FALSE) -> 50662 | G9: =F9*D9 -> 27.722246 | H9: 53849.37 | I9: =H9*D9 -> 29.466375 | J9: =((F9/H9)*100)-100 -> -5.9190479 | K9: =$K$4*E9% -> 0.0005472 | L9: =$L$4*E9% -> 0.1 | M9: =L9*F9 -> 5066.2
B10: =VLOOKUP(C10,[1]Hoja1!$B$2:$C$260,2,FALSE) -> 1210006 | C10: SAL REDUCIDA EN SODIO 60/40 | D10: 0.02736 | E10: 2 | F10: =VLOOKUP(B10,[2]Hoja1!$C$2:$E$279,3,FALSE) -> 8904.45 | G10: =F10*D10 -> 243.62575 | H10: 8910.1 | I10: =H10*D10 -> 243.78034 | J10: =((F10/H10)*100)-100 -> -0.063411185 | K10: =$K$4*E10% -> 0.02736 | L10: =$L$4*E10% -> 5 | M10: =L10*F10 -> 44522.25
B11: =VLOOKUP(C11,[1]Hoja1!$B$2:$C$260,2,FALSE) -> 1210004 | C11: SAL CURANTE AL 12 % | D11: 0.0012312 | E11: 0.09 | F11: =VLOOKUP(B11,[2]Hoja1!$C$2:$E$279,3,FALSE) -> 3841 | G11: =F11*D11 -> 4.7290392 | H11: 3508.01 | I11: =H11*D11 -> 4.3190619 | J11: =((F11/H11)*100)-100 -> 9.4922762 | K11: =$K$4*E11% -> 0.0012312 | L11: =$L$4*E11% -> 0.225 | M11: =L11*F11 -> 864.225
B12: =VLOOKUP(C12,[1]Hoja1!$B$2:$C$260,2,FALSE) -> 1210002 | C12: MEZCLA FOSFATOS CARFOSEL996 (GRANULAR) | D12: 0.004104 | E12: 0.3 | F12: =VLOOKUP(B12,[2]Hoja1!$C$2:$E$279,3,FALSE) -> 12886 | G12: =F12*D12 -> 52.884144 | H12: 12858.08 | I12: =H12*D12 -> 52.76956 | J12: =((F12/H12)*100)-100 -> 0.21713973 | K12: =$K$4*E12% -> 0.004104 | L12: =$L$4*E12% -> 0.75 | M12: =L12*F12 -> 9664.5
B13: =VLOOKUP(C13,[1]Hoja1!$B$2:$C$260,2,FALSE) -> 1220009 | C13: CEBOLLA EN POLVO | D13: 0.0008208 | E13: 0.06 | F13: =VLOOKUP(B13,[2]Hoja1!$C$2:$E$279,3,FALSE) -> 21312.16 | G13: =F13*D13 -> 17.493021 | H13: 20299 | I13: =H13*D13 -> 16.661419 | J13: =((F13/H13)*100)-100 -> 4.9911818 | K13: =$K$4*E13% -> 0.0008208 | L13: =$L$4*E13% -> 0.15 | M13: =L13*F13 -> 3196.824
B14: =VLOOKUP(C14,[1]Hoja1!$B$2:$C$260,2,FALSE) -> 1230013 | C14: PAPRIKA POLVO | D14: 0.002736 | E14: 0.2 | F14: =VLOOKUP(B14,[2]Hoja1!$C$2:$E$279,3,FALSE) -> 20777.07 | G14: =F14*D14 -> 56.846064 | H14: 19794.98 | I14: =H14*D14 -> 54.159065 | J14: =((F14/H14)*100)-100 -> 4.9613084 | K14: =$K$4*E14% -> 0.002736 | L14: =$L$4*E14% -> 0.5 | M14: =L14*F14 -> 10388.535
B15: =VLOOKUP(C15,[1]Hoja1!$B$2:$C$260,2,FALSE) -> 1220005 | C15: AJO MOLIDO DESHIDRATADO B.1 | D15: 0.0008208 | E15: 0.06 | F15: =VLOOKUP(B15,[2]Hoja1!$C$2:$E$279,3,FALSE) -> 17429.99 | G15: =F15*D15 -> 14.306536 | H15: 17430 | I15: =H15*D15 -> 14.306544 | J15: =((F15/H15)*100)-100 -> -5.7372347e-05 | K15: =$K$4*E15% -> 0.0008208 | L15: =$L$4*E15% -> 0.15 | M15: =L15*F15 -> 2614.4985
B16: =VLOOKUP(C16,[1]Hoja1!$B$2:$C$260,2,FALSE) -> 1220007 | C16: PIMIENTA NEGRA MOLIDA | D16: 0.0008208 | E16: 0.06 | F16: =VLOOKUP(B16,[2]Hoja1!$C$2:$E$279,3,FALSE) -> 60081.72 | G16: =F16*D16 -> 49.315076 | H16: 56748.6 | I16: =H16*D16 -> 46.579251 | J16: =((F16/H16)*100)-100 -> 5.8734841 | K16: =$K$4*E16% -> 0.0008208 | L16: =$L$4*E16% -> 0.15 | M16: =L16*F16 -> 9012.258
B17: =VLOOKUP(C17,[1]Hoja1!$B$2:$C$260,2,FALSE) -> 1210003 | C17: ERITORBATO DE SODIO | D17: 0.000684 | E17: 0.05 | F17: =VLOOKUP(B17,[2]Hoja1!$C$2:$E$279,3,FALSE) -> 16235.45 | G17: =F17*D17 -> 11.105048 | H17: 12852.58 | I17: =H17*D17 -> 8.7911647 | J17: =((F17/H17)*100)-100 -> 26.320552 | K17: =$K$4*E17% -> 0.000684 | L17: =$L$4*E17% -> 0.125 | M17: =L17*F17 -> 2029.4313
B18: =VLOOKUP(C18,[1]Hoja1!$B$2:$C$260,2,FALSE) -> 1121009 | C18: TOCINO NACIONAL | D18: 0.09576 | E18: 7 | F18: =VLOOKUP(B18,[2]Hoja1!$C$2:$E$279,3,FALSE) -> 8741.62 | G18: =F18*D18 -> 837.09753 | H18: 8754.28 | I18: =H18*D18 -> 838.30985 | J18: =((F18/H18)*100)-100 -> -0.14461498 | K18: =$K$4*E18% -> 0.09576 | L18: =$L$4*E18% -> 17.5 | M18: =L18*F18 -> 152978.35
B19: =VLOOKUP(C19,[1]Hoja1!$B$2:$C$260,2,FALSE) -> 1240002 | C19: CONSERVANTE INBAC ACN NA | D19: 0.004104 | E19: 0.3 | F19: =VLOOKUP(B19,[2]Hoja1!$C$2:$E$279,3,FALSE) -> 66115.8 | G19: =F19*D19 -> 271.33924 | H19: 70840.75 | I19: =H19*D19 -> 290.73044 | J19: =((F19/H19)*100)-100 -> -6.6698193 | K19: =$K$4*E19% -> 0.004104 | L19: =$L$4*E19% -> 0.75 | M19: =L19*F19 -> 49586.85
... B23: =VLOOKUP(C23,[1]Hoja1!$B$2:$C$260,2,FALSE) -> 1220010 | C23: DEXTROSA | D23: 0.021888 | E23: 1.6 | F23: =VLOOKUP(B23,[2]Hoja1!$C$2:$E$279,3,FALSE) -> 4744.72 | G23: =F23*D23 -> 103.85243 | H23: 9381 | I23: =H23*D23 -> 205.33133 | J23: =((F23/H23)*100)-100 -> -49.422023 | K23: =$K$4*E23% -> 0.021888 | L23: =$L$4*E23% -> 4 | M23: =L23*F23 -> 18978.88
B24: TOTAL | D24: =SUM(D23,D22,D21,D20,D19,D18,D17,D16,D15,D14,D13,D12,D11,D10,D9,D8,D7,D6,D5) -> 1.3684104 | E24: =SUM(E5:E23) -> 100.03 | G24: =SUM(G5:G23) -> 10339.525 | I24: =SUM(I5:I23) -> 11524.08 | J24: =((G24/I24)*100)-100 -> -10.278955 | M24: =SUM(M5:M23) -> 1889533.1
B26: MERMAS | D26: =+C29+(C29*C35%) -> 1368
B27: Linea | C27: Salchichas
B28: Referencia | C28: Salcicha Jumbi
B29: Presentación en Gramos | C29: 1200
B30: Máquina | C30: 0
B31: Cocción | C31: 9
B32: Frío | C32: 2 | F32: =0.2098*16 -> 3.3568
B33: Recorte | C33: 1
B34: Sobrepeso | C34: 2
B35: Merma Total | C35: =C34+C33+C32+C31 -> 14
B37: MATERIAL DE EMPAQUE
C38: DESCRIPCIÓN | D38: CATIDAD | E38: =+'CIF Y PV'!$F$4 -> JUN-COP/UMB | F38: =+'CIF Y PV'!$G$4 -> JUN-COP/APP | G38: =+'CIF Y PV'!$H$4 -> MAY-COP/UMB | H38: =+'CIF Y PV'!$I$4 -> MAY-COP/APP | I38: %
B39: =VLOOKUP(C39,[1]Hoja1!$B$2:$C$260,2,FALSE) -> 1370028 | C39: FUNDA CELULOSA 26 X 84 | D39: 3.3568 | E39: =VLOOKUP(B39,[2]Hoja1!$C$2:$E$279,3,FALSE) -> 186.09 | F39: =D39*E39 -> 624.66691 | G39: 201.77 | H39: =G39*D39 -> 677.30154 | I39: =((E39/G39)*100)-100 -> -7.7712247
B40: =VLOOKUP(C40,[1]Hoja1!$B$2:$C$260,2,FALSE) -> 1310018 | C40: LAM SUP TRANS ECOWEB M/PAUV 42U 301MM | D40: 0.15 | E40: =VLOOKUP(B40,[2]Hoja1!$C$2:$E$279,3,FALSE) -> 478.26 | F40: =D40*E40 -> 71.739 | G40: 503.51 | H40: =G40*D40 -> 75.5265 | I40: =((E40/G40)*100)-100 -> -5.0147961
B41: =VLOOKUP(C41,[1]Hoja1!$B$2:$C$260,2,FALSE) -> 1320004 | C41: LAM INFE SUDPACK GVA200 BT323 MM 8MM | D41: 0.15 | E41: =VLOOKUP(B41,[2]Hoja1!$C$2:$E$279,3,FALSE) -> 1481.51 | F41: =D41*E41 -> 222.2265 | G41: 1575.9 | H41: =G41*D41 -> 236.385 | I41: =((E41/G41)*100)-100 -> -5.9895932
B42: =VLOOKUP(C42,[1]Hoja1!$B$2:$C$260,2,FALSE) -> 1330022 | C42: ETI BLANCA GENERICA 100 X 80 | D42: 1 | E42: =VLOOKUP(B42,[2]Hoja1!$C$2:$E$279,3,FALSE) -> 40.87 | F42: =D42*E42 -> 40.87 | G42: 40.2 | H42: =G42*D42 -> 40.2 | I42: =((E42/G42)*100)-100 -> 1.6666667
C43: TOTAL | F43: =SUM(F39:F42) -> 959.50241 | H43: =SUM(H39:H42) -> 1029.413 | I43: =((F43/H43)*100)-100 -> -6.7913094
G45: =+'CIF Y PV'!$G$1 -> MAYO
B46: TOTAL INSUMOS (UND 450G) | G46: =F43+G24 -> 11299.027
B47: ASIGNACIÓN MOD/CIF | G47: =+('CIF Y PV'!C3/1000)*1200 -> 2268
B48: TOTAL COSTO POR UND (450 G) | G48: =+G46+G47 -> 13567.027
B49: PRECIO DE VENTA | G49: ='CIF Y PV'!C46 -> 24657.98
B50: MB | G50: =+(G49-G48)/G49 -> 0.44979161 | J50: =1-J49 -> 1

Sheet SCHA JUMBO X 450G fazán
B2: SCHA JUMBO X 450 G
B4: CÓDIGO | C4: DESCRIPCIÓN | D4: CATIDAD | E4: % | F4: =+'CIF Y PV'!$F$2 -> JUN-COP/Kg | G4: =+'CIF Y PV'!$G$2 -> JUN-COP/APP | H4: =+'CIF Y PV'!$H$2 -> MAY-COP/Kg | I4: =+'CIF Y PV'!$I$2 -> MAY-COP/APP | J4: % | K4: 0.513 | L4: 250
B5: =VLOOKUP(C5,[1]Hoja1!$B$2:$C$260,2,FALSE) -> 1112001 | C5: PASTA DE POLLO IMPORTADA PREMIUM | D5: 0.12825 | E5: 25 | F5: =VLOOKUP(B5,[2]Hoja1!$C$2:$E$279,3,FALSE) -> 3663.96 | G5: =F5*D5 -> 469.90287 | H5: 4222.72 | I5: =H5*D5 -> 541.56384 | J5: =((F5/H5)*100)-100 -> -13.232229 | K5: =$K$4*E5% -> 0.12825 | L5: =$L$4*E5 -> 6250
B6: =VLOOKUP(C6,[1]Hoja1!$B$2:$C$260,2,FALSE) -> 1122001 | C6: BRAZUELO DE CERDO NACIONAL | D6: 0.11286 | E6: 22 | F6: =VLOOKUP(B6,[2]Hoja1!$C$2:$E$279,3,FALSE) -> 11506.13 | G6: =F6*D6 -> 1298.5818 | H6: 14000 | I6: =H6*D6 -> 1580.04 | J6: =((F6/H6)*100)-100 -> -17.813357 | K6: =$K$4*E6% -> 0.11286
B7: 1122008 | C7: RECORTE CERDO 80/20 NAL EMULSIFICADOS | D7: 0.11286 | E7: 22 | F7: =VLOOKUP(B7,[2]Hoja1!$C$2:$E$279,3,FALSE) -> 12059.2 | G7: =F7*D7 -> 1361.0013 | H7: 12498.76 | I7: =H7*D7 -> 1410.6101 | J7: =((F7/H7)*100)-100 -> -3.5168289 | K7: =$K$4*E7% -> 0.11286
B8: =VLOOKUP(C8,[1]Hoja1!$B$2:$C$260,2,FALSE) -> 1131002 | C8: AGUA POTABLE | D8: 0.0771552 | E8: 15.04 | F8: =VLOOKUP(B8,[2]Hoja1!$C$2:$E$279,3,FALSE) -> 0 | G8: =F8*D8 -> 0 | H8: 0 | I8: =H8*D8 -> 0 | J8: =((F8/H8)*100)-100 -> #DIV/0! | K8: =$K$4*E8% -> 0.0771552
B9: =VLOOKUP(C9,[1]Hoja1!$B$2:$C$260,2,FALSE) -> 1270004 | C9: HUMO TRUSMOKE OIL EX | D9: 0.0002052 | E9: 0.04 | F9: =VLOOKUP(B9,[2]Hoja1!$C$2:$E$279,3,FALSE) -> 50662 | G9: =F9*D9 -> 10.395842 | H9: 53849.37 | I9: =H9*D9 -> 11.049891 | J9: =((F9/H9)*100)-100 -> -5.9190479 | K9: =$K$4*E9% -> 0.0002052
B10: =VLOOKUP(C10,[1]Hoja1!$B$2:$C$260,2,FALSE) -> 1210006 | C10: SAL REDUCIDA EN SODIO 60/40 | D10: 0.01026 | E10: 2 | F10: =VLOOKUP(B10,[2]Hoja1!$C$2:$E$279,3,FALSE) -> 8904.45 | G10: =F10*D10 -> 91.359657 | H10: 8910.1 | I10: =H10*D10 -> 91.417626 | J10: =((F10/H10)*100)-100 -> -0.063411185 | K10: =$K$4*E10% -> 0.01026
B11: =VLOOKUP(C11,[1]Hoja1!$B$2:$C$260,2,FALSE) -> 1210004 | C11: SAL CURANTE AL 12 % | D11: 0.0004617 | E11: 0.09 | F11: =VLOOKUP(B11,[2]Hoja1!$C$2:$E$279,3,FALSE) -> 3841 | G11: =F11*D11 -> 1.7733897 | H11: 3508.01 | I11: =H11*D11 -> 1.6196482 | J11: =((F11/H11)*100)-100 -> 9.4922762 | K11: =$K$4*E11% -> 0.0004617
B12: =VLOOKUP(C12,[1]Hoja1!$B$2:$C$260,2,FALSE) -> 1210002 | C12: MEZCLA FOSFATOS CARFOSEL996 (GRANULAR) | D12: 0.001539 | E12: 0.3 | F12: =VLOOKUP(B12,[2]Hoja1!$C$2:$E$279,3,FALSE) -> 12886 | G12: =F12*D12 -> 19.831554 | H12: 12858.08 | I12: =H12*D12 -> 19.788585 | J12: =((F12/H12)*100)-100 -> 0.21713973 | K12: =$K$4*E12% -> 0.001539
B13: =VLOOKUP(C13,[1]Hoja1!$B$2:$C$260,2,FALSE) -> 1220009 | C13: CEBOLLA EN POLVO | D13: 0.0003078 | E13: 0.06 | F13: =VLOOKUP(B13,[2]Hoja1!$C$2:$E$279,3,FALSE) -> 21312.16 | G13: =F13*D13 -> 6.5598828 | H13: 20299 | I13: =H13*D13 -> 6.2480322 | J13: =((F13/H13)*100)-100 -> 4.9911818 | K13: =$K$4*E13% -> 0.0003078
B14: =VLOOKUP(C14,[1]Hoja1!$B$2:$C$260,2,FALSE) -> 1230013 | C14: PAPRIKA POLVO | D14: 0.001026 | E14: 0.2 | F14: =VLOOKUP(B14,[2]Hoja1!$C$2:$E$279,3,FALSE) -> 20777.07 | G14: =F14*D14 -> 21.317274 | H14: 19794.98 | I14: =H14*D14 -> 20.309649 | J14: =((F14/H14)*100)-100 -> 4.9613084 | K14: =$K$4*E14% -> 0.001026
B15: =VLOOKUP(C15,[1]Hoja1!$B$2:$C$260,2,FALSE) -> 1220005 | C15: AJO MOLIDO DESHIDRATADO B.1 | D15: 0.0003078 | E15: 0.06 | F15: =VLOOKUP(B15,[2]Hoja1!$C$2:$E$279,3,FALSE) -> 17429.99 | G15: =F15*D15 -> 5.3649509 | H15: 17430 | I15: =H15*D15 -> 5.364954 | J15: =((F15/H15)*100)-100 -> -5.7372347e-05 | K15: =$K$4*E15% -> 0.0003078
B16: =VLOOKUP(C16,[1]Hoja1!$B$2:$C$260,2,FALSE) -> 1220007 | C16: PIMIENTA NEGRA MOLIDA | D16: 0.0003078 | E16: 0.06 | F16: =VLOOKUP(B16,[2]Hoja1!$C$2:$E$279,3,FALSE) -> 60081.72 | G16: =F16*D16 -> 18.493153 | H16: 56748.6 | I16: =H16*D16 -> 17.467219 | J16: =((F16/H16)*100)-100 -> 5.8734841 | K16: =$K$4*E16% -> 0.0003078
B17: =VLOOKUP(C17,[1]Hoja1!$B$2:$C$260,2,FALSE) -> 1210003 | C17: ERITORBATO DE SODIO | D17: 0.0002565 | E17: 0.05 | F17: =VLOOKUP(B17,[2]Hoja1!$C$2:$E$279,3,FALSE) -> 16235.45 | G17: =F17*D17 -> 4.1643929 | H17: 12852.58 | I17: =H17*D17 -> 3.2966868 | J17: =((F17/H17)*100)-100 -> 26.320552 | K17: =$K$4*E17% -> 0.0002565
B18: =VLOOKUP(C18,[1]Hoja1!$B$2:$C$260,2,FALSE) -> 1121009 | C18: TOCINO NACIONAL | D18: 0.03591 | E18: 7 | F18: =VLOOKUP(B18,[2]Hoja1!$C$2:$E$279,3,FALSE) -> 8741.62 | G18: =F18*D18 -> 313.91157 | H18: 8754.28 | I18: =H18*D18 -> 314.36619 | J18: =((F18/H18)*100)-100 -> -0.14461498 | K18: =$K$4*E18% -> 0.03591
B19: =VLOOKUP(C19,[1]Hoja1!$B$2:$C$260,2,FALSE) -> 1240002 | C19: CONSERVANTE INBAC ACN NA | D19: 0.001539 | E19: 0.3 | F19: =VLOOKUP(B19,[2]Hoja1!$C$2:$E$279,3,FALSE) -> 66115.8 | G19: =F19*D19 -> 101.75222 | H19: 70840.75 | I19: =H19*D19 -> 109.02391 | J19: =((F19/H19)*100)-100 -> -6.6698193 | K19: =$K$4*E19% -> 0.001539
... B23: =VLOOKUP(C23,[1]Hoja1!$B$2:$C$260,2,FALSE) -> 1220010 | C23: DEXTROSA | D23: 0.008208 | E23: 1.6 | F23: =VLOOKUP(B23,[2]Hoja1!$C$2:$E$279,3,FALSE) -> 4744.72 | G23: =F23*D23 -> 38.944662 | H23: 9381 | I23: =H23*D23 -> 76.999248 | J23: =((F23/H23)*100)-100 -> -49.422023 | K23: =$K$4*E23% -> 0.008208
B24: TOTAL | D24: =SUM(D23,D22,D21,D20,D19,D18,D17,D16,D15,D14,D13,D12,D11,D10,D9,D8,D7,D6,D5) -> 0.5131539 | E24: =SUM(E5:E23) -> 100.03 | G24: =SUM(G5:G23) -> 3877.3219 | I24: =SUM(I5:I23) -> 4321.53 | J24: =((G24/I24)*100)-100 -> -10.278955
B26: MERMAS | D26: =+C29+(C29*C35%) -> 513
B27: Linea | C27: Salchichas
B28: Referencia | C28: Salcicha Jumbo
B29: Presentación en Gramos | C29: 450
B30: Máquina | C30: 0
B31: Cocción | C31: 9
B32: Frío | C32: 2
B33: Recorte | C33: 1
B34: Sobrepeso | C34: 2
B35: Merma Total | C35: =C34+C33+C32+C31 -> 14
B37: MATERIAL DE EMPAQUE
C38: DESCRIPCIÓN | D38: CATIDAD | E38: =+'CIF Y PV'!$F$4 -> JUN-COP/UMB | F38: =+'CIF Y PV'!$G$4 -> JUN-COP/APP | G38: =+'CIF Y PV'!$H$4 -> MAY-COP/UMB | H38: =+'CIF Y PV'!$I$4 -> MAY-COP/APP | I38: %
B39: 1370028 | C39: FUNDA CELULOSA 26 X 84 | D39: 1.2588 | E39: =VLOOKUP(B39,[2]Hoja1!$C$2:$E$279,3,FALSE) -> 186.09 | F39: =E39*D39 -> 234.25009 | G39: 201.77 | H39: =G39*D39 -> 253.98808 | I39: =((E39/G39)*100)-100 -> -7.7712247
B40: 1310018 | C40: LAM SUP TRANS ECOWEB M/PAUV 42U 301MM | D40: 0.15 | E40: =VLOOKUP(B40,[2]Hoja1!$C$2:$E$279,3,FALSE) -> 478.26 | F40: =E40*D40 -> 71.739 | G40: 503.51 | H40: =G40*D40 -> 75.5265 | I40: =((E40/G40)*100)-100 -> -5.0147961
B41: 1320005 | C41: LAM INFE SUDPACK GVP 130-323 MM | D41: 0.15 | E41: =VLOOKUP(B41,[2]Hoja1!$C$2:$E$279,3,FALSE) -> 740.21 | F41: =E41*D41 -> 111.0315 | G41: 828.94 | H41: =G41*D41 -> 124.341 | I41: =((E41/G41)*100)-100 -> -10.704032
B42: 1330051 | C42: ETI RESPALDO SCHA JUMBO 450 G X 6 UND | D42: 1 | E42: =VLOOKUP(B42,[2]Hoja1!$C$2:$E$279,3,FALSE) -> 119.7 | F42: =E42*D42 -> 119.7 | G42: 119.7 | H42: =G42*D42 -> 119.7 | I42: =((E42/G42)*100)-100 -> 0
B43: 1330032 | C43: ETI SALCHICHA JUMBO X 450 G X 6 UND | D43: 1 | E43: =VLOOKUP(B43,[2]Hoja1!$C$2:$E$279,3,FALSE) -> 166.97 | F43: =E43*D43 -> 166.97 | G43: 166.96 | H43: =G43*D43 -> 166.96
C44: TOTAL | F44: =SUM(F39:F43) -> 703.69059 | H44: =SUM(H39:H43) -> 740.51558 | I44: =((F44/H44)*100)-100 -> -4.9728845
G46: =+'CIF Y PV'!$G$1 -> MAYO
B47: TOTAL INSUMOS (UND 450G) | G47: =F44+G24 -> 4581.0125
B48: ASIGNACIÓN MOD/CIF | G48: =+('CIF Y PV'!C3/1000)*450 -> 850.5
B49: TOTAL COSTO POR UND (450 G) | G49: =+G47+G48 -> 5431.5125
B50: PRECIO DE VENTA | G50: ='CIF Y PV'!C47 -> 11371.752
B51: MB | G51: =+(G50-G49)/G50 -> 0.52236802 | J51: =1-J50 -> 1

Sheet MINI PERRO X 1.0
B2: SALCHICHA MINI PERRO X 1.0 - 40 UNDS
B4: CÓDIGO | C4: DESCRIPCIÓN | D4: CATIDAD | E4: % | F4: =+'CIF Y PV'!$F$2 -> JUN-COP/Kg | G4: =+'CIF Y PV'!$G$2 -> JUN-COP/APP | H4: =+'CIF Y PV'!$H$2 -> MAY-COP/Kg | I4: =+'CIF Y PV'!$I$2 -> MAY-COP/APP | J4: % | K4: 1.14
B5: =VLOOKUP(C5,[1]Hoja1!$B$2:$C$260,2,FALSE) -> 1112001 | C5: PASTA DE POLLO IMPORTADA PREMIUM | D5: 0.5419053 | E5: 47.535552 | F5: =VLOOKUP(B5,[2]Hoja1!$C$2:$E$279,3,FALSE) -> 3663.96 | G5: =F5*D5 -> 1985.5193 | H5: 4222.72 | I5: =H5*D5 -> 2288.3143 | J5: =((F5/H5)*100)-100 -> -13.232229 | K5: =$K$4*E5% -> 0.5419053
B6: =VLOOKUP(C6,[1]Hoja1!$B$2:$C$260,2,FALSE) -> 2906001 | C6: EMULSION DE PIEL DE CERDO | D6: 0.096263219 | E6: 8.444142 | F6: =VLOOKUP(B6,[2]Hoja1!$C$2:$E$279,3,FALSE) -> 1956.71 | G6: =F6*D6 -> 188.3592 | H6: 2033.73 | I6: =H6*D6 -> 195.7734 | J6: =((F6/H6)*100)-100 -> -3.7871301 | K6: =$K$4*E6% -> 0.096263219
B7: =VLOOKUP(C7,[1]Hoja1!$B$2:$C$260,2,FALSE) -> 1131002 | C7: AGUA POTABLE | D7: 0.27903876 | E7: 24.477084 | F7: =VLOOKUP(B7,[2]Hoja1!$C$2:$E$279,3,FALSE) -> 0 | G7: =F7*D7 -> 0 | H7: 0 | I7: =H7*D7 -> 0 | J7: =((F7/H7)*100)-100 -> #DIV/0! | K7: =$K$4*E7% -> 0.27903876
B8: =VLOOKUP(C8,[1]Hoja1!$B$2:$C$260,2,FALSE) -> 1250009 | C8: COLOR NATURAL ROJO AC150 | D8: 0.00067950507 | E8: 0.059605708 | F8: =VLOOKUP(B8,[2]Hoja1!$C$2:$E$279,3,FALSE) -> 83551.55 | G8: =F8*D8 -> 56.773702 | H8: 71910.02 | I8: =H8*D8 -> 48.863223 | J8: =((F8/H8)*100)-100 -> 16.189023 | K8: =$K$4*E8% -> 0.00067950507
B9: =VLOOKUP(C9,[1]Hoja1!$B$2:$C$260,2,FALSE) -> 1250004 | C9: COLOR NATURAL NARANJA PR801WD | D9: 9.0600677e-05 | E9: 0.0079474278 | F9: =VLOOKUP(B9,[2]Hoja1!$C$2:$E$279,3,FALSE) -> 164481.95 | G9: =F9*D9 -> 14.902176 | H9: 156520.02 | I9: =H9*D9 -> 14.18082 | J9: =((F9/H9)*100)-100 -> 5.0868445 | K9: =$K$4*E9% -> 9.0600677e-05
B10: 1210005 | C10: SAL YODADA REFISAL | D10: 0.01197 | E10: 1.05 | F10: =VLOOKUP(B10,[2]Hoja1!$C$2:$E$279,3,FALSE) -> 1356 | G10: =F10*D10 -> 16.23132 | K10: =$K$4*E10% -> 0.01197
B11: 1210010 | C11: CLORURO DE POTASIO - KCL | D11: 0.00798 | E11: 0.7 | F11: =VLOOKUP(B11,[2]Hoja1!$C$2:$E$279,3,FALSE) -> 11600 | G11: =F11*D11 -> 92.568 | H11: 8910.1 | I11: =H11*D11 -> 71.102598 | J11: =((F11/H11)*100)-100 -> 30.189336 | K11: =$K$4*E11% -> 0.00798
B12: =VLOOKUP(C12,[1]Hoja1!$B$2:$C$260,2,FALSE) -> 1210004 | C12: SAL CURANTE AL 12 % | D12: 0.0018969517 | E12: 0.16639927 | F12: =VLOOKUP(B12,[2]Hoja1!$C$2:$E$279,3,FALSE) -> 3841 | G12: =F12*D12 -> 7.2861913 | H12: 3508.01 | I12: =H12*D12 -> 6.6545254 | J12: =((F12/H12)*100)-100 -> 9.4922762 | K12: =$K$4*E12% -> 0.0018969517
B13: =VLOOKUP(C13,[1]Hoja1!$B$2:$C$260,2,FALSE) -> 121007 | C13: SUPRA MEAT F451 | D13: 0.0045300338 | E13: 0.39737139 | F13: =VLOOKUP(B13,[2]Hoja1!$C$2:$E$279,3,FALSE) -> 16905 | G13: =F13*D13 -> 76.580222 | H13: 16100 | I13: =H13*D13 -> 72.933545 | J13: =((F13/H13)*100)-100 -> 5 | K13: =$K$4*E13% -> 0.0045300338
B14: =VLOOKUP(C14,[1]Hoja1!$B$2:$C$260,2,FALSE) -> 1240002 | C14: CONSERVANTE INBAC ACN NA | D14: 0.0056625423 | E14: 0.49671424 | F14: =VLOOKUP(B14,[2]Hoja1!$C$2:$E$279,3,FALSE) -> 66115.8 | G14: =F14*D14 -> 374.38351 | H14: 70840.75 | I14: =H14*D14 -> 401.13874 | J14: =((F14/H14)*100)-100 -> -6.6698193 | K14: =$K$4*E14% -> 0.0056625423
B15: =VLOOKUP(C15,[1]Hoja1!$B$2:$C$260,2,FALSE) -> 1220015 | C15: MEZCLA LIQUIDA SALCHICHA | D15: 0.0076444321 | E15: 0.67056422 | F15: =VLOOKUP(B15,[2]Hoja1!$C$2:$E$279,3,FALSE) -> 30702.27 | G15: =F15*D15 -> 234.70142 | H15: 29189.39 | I15: =H15*D15 -> 223.13631 | J15: =((F15/H15)*100)-100 -> 5.1829792 | K15: =$K$4*E15% -> 0.0076444321
B16: =VLOOKUP(C16,[1]Hoja1!$B$2:$C$260,2,FALSE) -> 1220014 | C16: PVH LIQUIDA M 1222 | D16: 0.0062287965 | E16: 0.54638566 | F16: =VLOOKUP(B16,[2]Hoja1!$C$2:$E$279,3,FALSE) -> 14060 | G16: =F16*D16 -> 87.576879 | H16: 13300.01 | I16: =H16*D16 -> 82.843056 | J16: =((F16/H16)*100)-100 -> 5.7142062 | K16: =$K$4*E16% -> 0.0062287965
B17: =VLOOKUP(C17,[1]Hoja1!$B$2:$C$260,2,FALSE) -> 1210003 | C17: ERITORBATO DE SODIO | D17: 0.00056625423 | E17: 0.049671424 | F17: =VLOOKUP(B17,[2]Hoja1!$C$2:$E$279,3,FALSE) -> 16235.45 | G17: =F17*D17 -> 9.1933922 | H17: 12852.58 | I17: =H17*D17 -> 7.2778278 | J17: =((F17/H17)*100)-100 -> 26.320552 | K17: =$K$4*E17% -> 0.00056625423
B18: 1260024 | C18: EXTRACTO PROTEICO GP 83 | D18: 0.011325085 | E18: 0.99342847 | F18: =VLOOKUP(B18,[2]Hoja1!$C$2:$E$279,3,FALSE) -> 12625.84 | G18: =F18*D18 -> 142.98871 | H18: 18900 | I18: =H18*D18 -> 214.0441 | J18: =((F18/H18)*100)-100 -> -33.196614 | K18: =$K$4*E18% -> 0.011325085
B19: =VLOOKUP(C19,[1]Hoja1!$B$2:$C$260,2,FALSE) -> 1260005 | C19: PLASMA PORCINO | D19: 0.011325085 | E19: 0.99342847 | F19: =VLOOKUP(B19,[2]Hoja1!$C$2:$E$279,3,FALSE) -> 26429 | G19: =F19*D19 -> 299.31066 | H19: 25850 | I19: =H19*D19 -> 292.75344 | J19: =((F19/H19)*100)-100 -> 2.2398453 | K19: =$K$4*E19% -> 0.011325085
B20: =VLOOKUP(C20,[1]Hoja1!$B$2:$C$260,2,FALSE) -> 1260010 | C20: PROTEINA CONCENTRADA SOYA 65% | D20: 0.056625423 | E20: 4.9671424 | F20: =VLOOKUP(B20,[2]Hoja1!$C$2:$E$279,3,FALSE) -> 6959.71 | G20: =F20*D20 -> 394.09652 | H20: 9565.21 | I20: =H20*D20 -> 541.63406 | J20: =((F20/H20)*100)-100 -> -27.239339 | K20: =$K$4*E20% -> 0.056625423
B21: =VLOOKUP(C21,[1]Hoja1!$B$2:$C$260,2,FALSE) -> 1260017 | C21: ALMIDON MODIFICADO DE MAIZ | D21: 0.056625423 | E21: 4.9671424 | F21: =VLOOKUP(B21,[2]Hoja1!$C$2:$E$279,3,FALSE) -> 4500 | G21: =F21*D21 -> 254.8144 | H21: 4500 | I21: =H21*D21 -> 254.8144 | J21: =((F21/H21)*100)-100 -> 0 | K21: =$K$4*E21% -> 0.056625423
B22: =VLOOKUP(C22,[1]Hoja1!$B$2:$C$260,2,FALSE) -> 1260012 | C22: SOLU TEX GRASAS NEUTRO | D22: 0.0036919776 | E22: 0.32385768 | F22: =VLOOKUP(B22,[2]Hoja1!$C$2:$E$279,3,FALSE) -> 46081 | G22: =F22*D22 -> 170.13002 | H22: 46081 | I22: =H22*D22 -> 170.13002 | J22: =((F22/H22)*100)-100 -> 0 | K22: =$K$4*E22% -> 0.0036919776
B23: =VLOOKUP(C23,[1]Hoja1!$B$2:$C$260,2,FALSE) -> 1121009 | C23: TOCINO NACIONAL | D23: 0.036931101 | E23: 3.2395702 | F23: =VLOOKUP(B23,[2]Hoja1!$C$2:$E$279,3,FALSE) -> 8741.62 | G23: =F23*D23 -> 322.83765 | H23: 8754.28 | I23: =H23*D23 -> 323.3052 | J23: =((F23/H23)*100)-100 -> -0.14461498 | K23: =$K$4*E23% -> 0.036931101
B24: TOTAL | D24: =SUM(D5:D23) -> 1.1409805 | E24: =SUM(E5:E23) -> 100.08601 | G24: =SUM(G5:G23) -> 4728.2533 | I24: =SUM(I5:I23) -> 5208.8996 | J24: =((G24/I24)*100)-100 -> -9.2274055
B26: MERMAS | D26: =+C29+(C29*C35%) -> 1140
B27: Linea | C27: Salchichas
B28: Referencia | C28: Perro
B29: Presentación en Gramos | C29: 1000
B30: Máquina | C30: 0
B31: Cocción | C31: 9
B32: Frío | C32: 2
B33: Recorte | C33: 1
B34: Sobrepeso | C34: 2
B35: Merma Total | C35: =C34+C33+C32+C31 -> 14
B37: MATERIAL DE EMPAQUE
B38: CÓDIGO | C38: DESCRIPCIÓN | D38: CATIDAD | E38: =+'CIF Y PV'!$F$4 -> JUN-COP/UMB | F38: =+'CIF Y PV'!$G$4 -> JUN-COP/APP | G38: =+'CIF Y PV'!$H$4 -> MAY-COP/UMB | H38: =+'CIF Y PV'!$I$4 -> MAY-COP/APP | I38: % | J38: 1772
B39: =VLOOKUP(C39,[1]Hoja1!$B$2:$C$260,2,FALSE) -> 1370004 | C39: FUNDA CELULOSA 18 X 100 | D39: 5.6 | E39: =VLOOKUP(B39,[2]Hoja1!$C$2:$E$279,3,FALSE) -> 164.29 | F39: =E39*D39 -> 920.024 | G39: 181.63 | H39: =G39*D39 -> 1017.128 | I39: =((E39/G39)*100)-100 -> -9.546881 | J39: =J38*D39 -> 9923.2
B40: 1330029 | C40: ETI MINI PERRO X 1 KG X 40 U | D40: 1 | E40: =VLOOKUP(B40,[2]Hoja1!$C$2:$E$279,3,FALSE) -> 162.88 | F40: =E40*D40 -> 162.88 | J40: =J38*D41 -> 265.8
B41: =VLOOKUP(C41,[1]Hoja1!$B$2:$C$260,2,FALSE) -> 1310018 | C41: LAM SUP TRANS ECOWEB M/PAUV 42U 301MM | D41: 0.15 | E41: =VLOOKUP(B41,[2]Hoja1!$C$2:$E$279,3,FALSE) -> 478.26 | F41: =E41*D41 -> 71.739 | G41: 882 | H41: =G41*D41 -> 132.3 | I41: =((E41/G41)*100)-100 -> -45.77551
B42: =VLOOKUP(C42,[1]Hoja1!$B$2:$C$260,2,FALSE) -> 1320004 | C42: LAM INFE SUDPACK GVA200 BT323 MM 8MM | D42: 0.15 | E42: =VLOOKUP(B42,[2]Hoja1!$C$2:$E$279,3,FALSE) -> 1481.51 | F42: =E42*D42 -> 222.2265 | G42: 1575.9 | H42: =G42*D42 -> 236.385 | I42: =((E42/G42)*100)-100 -> -5.9895932 | J42: =J38*D42 -> 265.8
C43: TOTAL | F43: =SUM(F39:F42) -> 1376.8695 | H43: =SUM(H39:H42) -> 1385.813 | I43: =((F43/H43)*100)-100 -> -0.64536124
H44: =+'CIF Y PV'!$G$1 -> MAYO
B45: TOTAL INSUMOS (UND 1000 G) | H45: =+F43+G24 -> 6105.1228
B46: ASIGNACIÓN MOD/CIF | H46: =+('CIF Y PV'!C3/1000)*1000 -> 1890
B47: TOTAL COSTO POR UND (1000) | H47: =+H45+H46 -> 7995.1228
B48: PRECIO DE VENTA | H48: ='CIF Y PV'!C49 -> 16016.616
B49: MB | H49: =+(H48-H47)/H48 -> 0.50082322 | K49: =1-K48 -> 1

Sheet SCHA PERRO X 480 G - 12 UNDS
B2: SALCHICHA PERRO CALIENTE X 480 G - 12 UNDS
D3: 53.62
B4: CÓDIGO | C4: DESCRIPCIÓN | D4: CATIDAD | E4: % | F4: =+'CIF Y PV'!$F$2 -> JUN-COP/Kg | G4: =+'CIF Y PV'!$G$2 -> JUN-COP/APP | H4: =+'CIF Y PV'!$H$2 -> MAY-COP/Kg | I4: =+'CIF Y PV'!$I$2 -> MAY-COP/APP | J4: % | K4: 0.548
B5: =VLOOKUP(C5,[1]Hoja1!$B$2:$C$260,2,FALSE) -> 1112001 | C5: PASTA DE POLLO IMPORTADA PREMIUM | D5: 0.26049483 | E5: 47.535552 | F5: =VLOOKUP(B5,[2]Hoja1!$C$2:$E$279,3,FALSE) -> 3663.96 | G5: =F5*D5 -> 954.44263 | H5: 4222.72 | I5: =H5*D5 -> 1099.9967 | J5: =((F5/H5)*100)-100 -> -13.232229 | K5: =$K$4*E5% -> 0.26049483
B6: =VLOOKUP(C6,[1]Hoja1!$B$2:$C$260,2,FALSE) -> 2906001 | C6: EMULSION DE PIEL DE CERDO | D6: 0.046273898 | E6: 8.444142 | F6: =VLOOKUP(B6,[2]Hoja1!$C$2:$E$279,3,FALSE) -> 1956.71 | G6: =F6*D6 -> 90.544599 | H6: 2033.73 | I6: =H6*D6 -> 94.108615 | J6: =((F6/H6)*100)-100 -> -3.7871301 | K6: =$K$4*E6% -> 0.046273898
B7: =VLOOKUP(C7,[1]Hoja1!$B$2:$C$260,2,FALSE) -> 1131002 | C7: AGUA POTABLE | D7: 0.13413442 | E7: 24.477084 | F7: =VLOOKUP(B7,[2]Hoja1!$C$2:$E$279,3,FALSE) -> 0 | G7: =F7*D7 -> 0 | H7: 0 | I7: =H7*D7 -> 0 | J7: =((F7/H7)*100)-100 -> #DIV/0! | K7: =$K$4*E7% -> 0.13413442
B8: =VLOOKUP(C8,[1]Hoja1!$B$2:$C$260,2,FALSE) -> 1250009 | C8: COLOR NATURAL ROJO AC150 | D8: 0.00032663928 | E8: 0.059605708 | F8: =VLOOKUP(B8,[2]Hoja1!$C$2:$E$279,3,FALSE) -> 83551.55 | G8: =F8*D8 -> 27.291218 | H8: 71910.02 | I8: =H8*D8 -> 23.488637 | J8: =((F8/H8)*100)-100 -> 16.189023 | K8: =$K$4*E8% -> 0.00032663928
B9: =VLOOKUP(C9,[1]Hoja1!$B$2:$C$260,2,FALSE) -> 1250004 | C9: COLOR NATURAL NARANJA PR801WD | D9: 4.3551904e-05 | E9: 0.0079474278 | F9: =VLOOKUP(B9,[2]Hoja1!$C$2:$E$279,3,FALSE) -> 164481.95 | G9: =F9*D9 -> 7.1635021 | H9: 156520.02 | I9: =H9*D9 -> 6.8167449 | J9: =((F9/H9)*100)-100 -> 5.0868445 | K9: =$K$4*E9% -> 4.3551904e-05
B10: 1210005 | C10: SAL YODADA REFISAL | D10: 0.005754 | E10: 1.05 | F10: =VLOOKUP(B10,[2]Hoja1!$C$2:$E$279,3,FALSE) -> 1356 | K10: =$K$4*E10% -> 0.005754
B11: 1210010 | C11: CLORURO DE POTASIO - KCL | D11: 0.003836 | E11: 0.7 | F11: =VLOOKUP(B11,[2]Hoja1!$C$2:$E$279,3,FALSE) -> 11600 | G11: =F11*D11 -> 44.4976 | H11: 8910.1 | I11: =H11*D11 -> 34.179144 | J11: =((F11/H11)*100)-100 -> 30.189336 | K11: =$K$4*E11% -> 0.003836
B12: =VLOOKUP(C12,[1]Hoja1!$B$2:$C$260,2,FALSE) -> 1210004 | C12: SAL CURANTE AL 12 % | D12: 0.00091186799 | E12: 0.16639927 | F12: =VLOOKUP(B12,[2]Hoja1!$C$2:$E$279,3,FALSE) -> 3841 | G12: =F12*D12 -> 3.502485 | H12: 3508.01 | I12: =H12*D12 -> 3.198842 | J12: =((F12/H12)*100)-100 -> 9.4922762 | K12: =$K$4*E12% -> 0.00091186799
B13: =VLOOKUP(C13,[1]Hoja1!$B$2:$C$260,2,FALSE) -> 121007 | C13: SUPRA MEAT F451 | D13: 0.0021775952 | E13: 0.39737139 | F13: =VLOOKUP(B13,[2]Hoja1!$C$2:$E$279,3,FALSE) -> 16905 | G13: =F13*D13 -> 36.812247 | H13: 16100 | I13: =H13*D13 -> 35.059283 | J13: =((F13/H13)*100)-100 -> 5 | K13: =$K$4*E13% -> 0.0021775952
B14: =VLOOKUP(C14,[1]Hoja1!$B$2:$C$260,2,FALSE) -> 1240002 | C14: CONSERVANTE INBAC ACN NA | D14: 0.002721994 | E14: 0.49671424 | F14: =VLOOKUP(B14,[2]Hoja1!$C$2:$E$279,3,FALSE) -> 66115.8 | G14: =F14*D14 -> 179.96681 | H14: 70840.75 | I14: =H14*D14 -> 192.8281 | J14: =((F14/H14)*100)-100 -> -6.6698193 | K14: =$K$4*E14% -> 0.002721994
B15: =VLOOKUP(C15,[1]Hoja1!$B$2:$C$260,2,FALSE) -> 1220015 | C15: MEZCLA LIQUIDA SALCHICHA | D15: 0.0036746919 | E15: 0.67056422 | F15: =VLOOKUP(B15,[2]Hoja1!$C$2:$E$279,3,FALSE) -> 30702.27 | G15: =F15*D15 -> 112.82138 | H15: 29189.39 | I15: =H15*D15 -> 107.26202 | J15: =((F15/H15)*100)-100 -> 5.1829792 | K15: =$K$4*E15% -> 0.0036746919
B16: =VLOOKUP(C16,[1]Hoja1!$B$2:$C$260,2,FALSE) -> 1220014 | C16: PVH LIQUIDA M 1222 | D16: 0.0029941934 | E16: 0.54638566 | F16: =VLOOKUP(B16,[2]Hoja1!$C$2:$E$279,3,FALSE) -> 14060 | G16: =F16*D16 -> 42.098359 | H16: 13300.01 | I16: =H16*D16 -> 39.822802 | J16: =((F16/H16)*100)-100 -> 5.7142062 | K16: =$K$4*E16% -> 0.0029941934
B17: =VLOOKUP(C17,[1]Hoja1!$B$2:$C$260,2,FALSE) -> 1210003 | C17: ERITORBATO DE SODIO | D17: 0.0002721994 | E17: 0.049671424 | F17: =VLOOKUP(B17,[2]Hoja1!$C$2:$E$279,3,FALSE) -> 16235.45 | G17: =F17*D17 -> 4.4192798 | H17: 12852.58 | I17: =H17*D17 -> 3.4984646 | J17: =((F17/H17)*100)-100 -> 26.320552 | K17: =$K$4*E17% -> 0.0002721994
B18: 1260024 | C18: EXTRACTO PROTEICO GP 83 | D18: 0.005443988 | E18: 0.99342847 | F18: =VLOOKUP(B18,[2]Hoja1!$C$2:$E$279,3,FALSE) -> 12625.84 | G18: =F18*D18 -> 68.734922 | H18: 18900 | I18: =H18*D18 -> 102.89137 | J18: =((F18/H18)*100)-100 -> -33.196614 | K18: =$K$4*E18% -> 0.005443988
B19: =VLOOKUP(C19,[1]Hoja1!$B$2:$C$260,2,FALSE) -> 1260005 | C19: PLASMA PORCINO | D19: 0.005443988 | E19: 0.99342847 | F19: =VLOOKUP(B19,[2]Hoja1!$C$2:$E$279,3,FALSE) -> 26429 | G19: =F19*D19 -> 143.87916 | H19: 25850 | I19: =H19*D19 -> 140.72709 | J19: =((F19/H19)*100)-100 -> 2.2398453 | K19: =$K$4*E19% -> 0.005443988
B20: =VLOOKUP(C20,[1]Hoja1!$B$2:$C$260,2,FALSE) -> 1260010 | C20: PROTEINA CONCENTRADA SOYA 65% | D20: 0.02721994 | E20: 4.9671424 | F20: =VLOOKUP(B20,[2]Hoja1!$C$2:$E$279,3,FALSE) -> 6959.71 | G20: =F20*D20 -> 189.44289 | H20: 9565.21 | I20: =H20*D20 -> 260.36444 | J20: =((F20/H20)*100)-100 -> -27.239339 | K20: =$K$4*E20% -> 0.02721994
B21: =VLOOKUP(C21,[1]Hoja1!$B$2:$C$260,2,FALSE) -> 1260017 | C21: ALMIDON MODIFICADO DE MAIZ | D21: 0.02721994 | E21: 4.9671424 | F21: =VLOOKUP(B21,[2]Hoja1!$C$2:$E$279,3,FALSE) -> 4500 | G21: =F21*D21 -> 122.48973 | H21: 4500 | I21: =H21*D21 -> 122.48973 | J21: =((F21/H21)*100)-100 -> 0 | K21: =$K$4*E21% -> 0.02721994
B22: =VLOOKUP(C22,[1]Hoja1!$B$2:$C$260,2,FALSE) -> 1260012 | C22: SOLU TEX GRASAS NEUTRO | D22: 0.0017747401 | E22: 0.32385768 | F22: =VLOOKUP(B22,[2]Hoja1!$C$2:$E$279,3,FALSE) -> 46081 | G22: =F22*D22 -> 81.781798 | H22: 46081 | I22: =H22*D22 -> 81.781798 | J22: =((F22/H22)*100)-100 -> 0 | K22: =$K$4*E22% -> 0.0017747401
B23: =VLOOKUP(C23,[1]Hoja1!$B$2:$C$260,2,FALSE) -> 1121009 | C23: TOCINO NACIONAL | D23: 0.017752845 | E23: 3.2395702 | F23: =VLOOKUP(B23,[2]Hoja1!$C$2:$E$279,3,FALSE) -> 8741.62 | G23: =F23*D23 -> 155.18862 | H23: 8754.28 | I23: =H23*D23 -> 155.41338 | J23: =((F23/H23)*100)-100 -> -0.14461498 | K23: =$K$4*E23% -> 0.017752845
B24: TOTAL | D24: 37.43 | E24: =SUM(E5:E23) -> 100.08601 | G24: =SUM(G5:G23) -> 2265.0772 | I24: =SUM(I5:I23) -> 2503.9272 | J24: =((G24/I24)*100)-100 -> -9.5390129
B26: MERMAS | D26: =+C29+(C29*C35%) -> 547.68
B27: Linea | C27: Salchichas
B28: Referencia | C28: Perro
B29: Presentación en Gramos | C29: 480
B30: Máquina | C30: 0
B31: Cocción | C31: 9
B32: Frío | C32: 2
B33: Recorte | C33: 1
B34: Sobrepeso | C34: 2.1
B35: Merma Total | C35: =C34+C33+C32+C31 -> 14.1
B37: MATERIAL DE EMPAQUE
B38: CÓDIGO | C38: DESCRIPCIÓN | D38: CATIDAD | E38: =+'CIF Y PV'!$F$4 -> JUN-COP/UMB | F38: =+'CIF Y PV'!$G$4 -> JUN-COP/APP | G38: =+'CIF Y PV'!$H$4 -> MAY-COP/UMB | H38: =+'CIF Y PV'!$I$4 -> MAY-COP/APP | I38: % | J38: 3650
B39: =VLOOKUP(C39,[1]Hoja1!$B$2:$C$260,2,FALSE) -> 1370007 | C39: FUNDA CELULOSA 23 X 100 | D39: 1.8 | E39: =VLOOKUP(B39,[2]Hoja1!$C$2:$E$279,3,FALSE) -> 181.76 | F39: =VLOOKUP(B39,[3]Hoja1!$C$2:$E$295,3,FALSE) -> 178.15 | G39: 195.56 | H39: =G39*D39 -> 352.008 | I39: =((F39/H39)*100)-100 -> -49.390355 | J39: =J38*D39 -> 6570
B40: =VLOOKUP(C40,[1]Hoja1!$B$2:$C$260,2,FALSE) -> 1310018 | C40: LAM SUP TRANS ECOWEB M/PAUV 42U 301MM | D40: 0.0769 | E40: =VLOOKUP(B40,[2]Hoja1!$C$2:$E$279,3,FALSE) -> 478.26 | F40: =E40*D40 -> 36.778194 | G40: 503.51 | H40: =G40*D40 -> 38.719919 | I40: =((F40/H40)*100)-100 -> -5.0147961 | J40: =J38*D40 -> 280.685
B41: =VLOOKUP(C41,[1]Hoja1!$B$2:$C$260,2,FALSE) -> 1320004 | C41: LAM INFE SUDPACK GVA200 BT323 MM 8MM | D41: 0.0769 | E41: =VLOOKUP(B41,[2]Hoja1!$C$2:$E$279,3,FALSE) -> 1481.51 | F41: =E41*D41 -> 113.92812 | G41: 1575.9 | H41: =G41*D41 -> 121.18671 | I41: =((F41/H41)*100)-100 -> -5.9895932 | J41: =J38*D41 -> 280.685
B42: =VLOOKUP(C42,[1]Hoja1!$B$2:$C$260,2,FALSE) -> 1330009 | C42: ETI SALCHIPERRO CALIENTE 480 G X 12UND | D42: 1 | E42: =VLOOKUP(B42,[2]Hoja1!$C$2:$E$279,3,FALSE) -> 134.3 | F42: =E42*D42 -> 134.3 | G42: 143.12 | H42: =G42*D42 -> 143.12 | I42: =((F42/H42)*100)-100 -> -6.1626607 | J42: =J38*D42 -> 3650
A43: Ya está en etiqueta con lamina transparente
C44: TOTAL | F44: =SUM(F39:F42) -> 463.15631 | H44: =SUM(H39:H42) -> 655.03463 | I44: =((F44/H44)*100)-100 -> -29.292851
H45: =+'CIF Y PV'!$G$1 -> MAYO
B46: TOTAL INSUMOS (UND 480 G) | H46: =+F44+G24 -> 2728.2335
B47: ASIGNACIÓN MOD/CIF | H47: =+('CIF Y PV'!C3/1000)*480 -> 907.2
B48: TOTAL COSTO POR UND (480) | H48: =+H47+H46 -> 3635.4335
B49: PRECIO DE VENTA | H49: ='CIF Y PV'!C51 -> 9824.9112
B50: MB | H50: =+(H49-H48)/H49 -> 0.62997797

Sheet SCHA S. PERRO X 500 
B2: SALCHICHA SUPER PERRO X 500 G - 10 UNDS
D3: 53.62 | M3: Batch
B4: CÓDIGO | C4: DESCRIPCIÓN | D4: CATIDAD | E4: % | F4: =+'CIF Y PV'!$F$2 -> JUN-COP/Kg | G4: =+'CIF Y PV'!$G$2 -> JUN-COP/APP | H4: =+'CIF Y PV'!$H$2 -> MAY-COP/Kg | I4: =+'CIF Y PV'!$I$2 -> MAY-COP/APP | J4: % | K4: 0.571 | L4: 2013.23
B5: =VLOOKUP(C5,[1]Hoja1!$B$2:$C$260,2,FALSE) -> 1112001 | C5: PASTA DE POLLO IMPORTADA PREMIUM | D5: 0.271428 | E5: 47.535552 | F5: =VLOOKUP(B5,[2]Hoja1!$C$2:$E$279,3,FALSE) -> 3663.96 | G5: =F5*D5 -> 994.50135 | H5: 4222.72 | I5: =H5*D5 -> 1146.1645 | J5: =((F5/H5)*100)-100 -> -13.232229 | K5: =$K$4*E5% -> 0.271428 | L5: =$L$4*E5% -> 957 | M5: =L5*F5 -> 3506409.7
B6: =VLOOKUP(C6,[1]Hoja1!$B$2:$C$260,2,FALSE) -> 2906001 | C6: EMULSION DE PIEL DE CERDO | D6: 0.048216051 | E6: 8.444142 | F6: =VLOOKUP(B6,[2]Hoja1!$C$2:$E$279,3,FALSE) -> 1956.71 | G6: =F6*D6 -> 94.344829 | H6: 2033.73 | I6: =H6*D6 -> 98.058429 | J6: =((F6/H6)*100)-100 -> -3.7871301 | K6: =$K$4*E6% -> 0.048216051 | L6: =$L$4*E6% -> 170 | M6: =L6*F6 -> 332640.7
B7: =VLOOKUP(C7,[1]Hoja1!$B$2:$C$260,2,FALSE) -> 1131002 | C7: AGUA POTABLE | D7: 0.13976415 | E7: 24.477084 | F7: =VLOOKUP(B7,[2]Hoja1!$C$2:$E$279,3,FALSE) -> 0 | G7: =F7*D7 -> 0 | H7: 0 | I7: =H7*D7 -> 0 | J7: =((F7/H7)*100)-100 -> #DIV/0! | K7: =$K$4*E7% -> 0.13976415 | L7: =$L$4*E7% -> 492.78 | M7: =L7*F7 -> 0
B8: =VLOOKUP(C8,[1]Hoja1!$B$2:$C$260,2,FALSE) -> 1250009 | C8: COLOR NATURAL ROJO AC150 | D8: 0.00034034859 | E8: 0.059605708 | F8: =VLOOKUP(B8,[2]Hoja1!$C$2:$E$279,3,FALSE) -> 83551.55 | G8: =F8*D8 -> 28.436653 | H8: 71910.02 | I8: =H8*D8 -> 24.474474 | J8: =((F8/H8)*100)-100 -> 16.189023 | K8: =$K$4*E8% -> 0.00034034859 | L8: =$L$4*E8% -> 1.2 | M8: =L8*F8 -> 100261.86
B9: =VLOOKUP(C9,[1]Hoja1!$B$2:$C$260,2,FALSE) -> 1250004 | C9: COLOR NATURAL NARANJA PR801WD | D9: 4.5379813e-05 | E9: 0.0079474278 | F9: =VLOOKUP(B9,[2]Hoja1!$C$2:$E$279,3,FALSE) -> 164481.95 | G9: =F9*D9 -> 7.4641601 | H9: 156520.02 | I9: =H9*D9 -> 7.1028492 | J9: =((F9/H9)*100)-100 -> 5.0868445 | K9: =$K$4*E9% -> 4.5379813e-05 | L9: =$L$4*E9% -> 0.16 | M9: =L9*F9 -> 26317.112
B10: 1210005 | C10: SAL YODADA REFISAL | D10: 0.0059955 | E10: 1.05 | F10: =VLOOKUP(B10,[2]Hoja1!$C$2:$E$279,3,FALSE) -> 1356 | G10: =F10*D10 -> 8.129898 | H10: 8910.1 | I10: =H10*D10 -> 53.420505 | J10: =((F10/H10)*100)-100 -> -84.781316 | K10: =$K$4*E10% -> 0.0059955 | L10: =$L$4*E10% -> 21.138915 | M10: =L10*F10 -> 28664.369
B11: 1210010 | C11: CLORURO DE POTASIO - KCL | D11: 0.003997 | E11: 0.7 | F11: =VLOOKUP(B11,[2]Hoja1!$C$2:$E$279,3,FALSE) -> 11600 | G11: =F11*D11 -> 46.3652 | K11: =$K$4*E11% -> 0.003997
B12: =VLOOKUP(C12,[1]Hoja1!$B$2:$C$260,2,FALSE) -> 1210004 | C12: SAL CURANTE AL 12 % | D12: 0.0004568 | E12: 0.08 | F12: =VLOOKUP(B12,[2]Hoja1!$C$2:$E$279,3,FALSE) -> 3841 | G12: =F12*D12 -> 1.7545688 | H12: 3508.01 | I12: =H12*D12 -> 1.602459 | J12: =((F12/H12)*100)-100 -> 9.4922762 | K12: =$K$4*E12% -> 0.0004568 | L12: =$L$4*E12% -> 1.610584 | M12: =L12*F12 -> 6186.2531
B13: =VLOOKUP(C13,[1]Hoja1!$B$2:$C$260,2,FALSE) -> 121007 | C13: SUPRA MEAT F451 | D13: 0.0022689906 | E13: 0.39737139 | F13: =VLOOKUP(B13,[2]Hoja1!$C$2:$E$279,3,FALSE) -> 16905 | G13: =F13*D13 -> 38.357287 | H13: 16100 | I13: =H13*D13 -> 36.530749 | J13: =((F13/H13)*100)-100 -> 5 | K13: =$K$4*E13% -> 0.0022689906 | L13: =$L$4*E13% -> 8 | M13: =L13*F13 -> 135240
B14: =VLOOKUP(C14,[1]Hoja1!$B$2:$C$260,2,FALSE) -> 1240002 | C14: CONSERVANTE INBAC ACN NA | D14: 0.0028362383 | E14: 0.49671424 | F14: =VLOOKUP(B14,[2]Hoja1!$C$2:$E$279,3,FALSE) -> 66115.8 | G14: =F14*D14 -> 187.52016 | H14: 70840.75 | I14: =H14*D14 -> 200.92125 | J14: =((F14/H14)*100)-100 -> -6.6698193 | K14: =$K$4*E14% -> 0.0028362383 | L14: =$L$4*E14% -> 10 | M14: =L14*F14 -> 661158
B15: =VLOOKUP(C15,[1]Hoja1!$B$2:$C$260,2,FALSE) -> 1220015 | C15: MEZCLA LIQUIDA SALCHICHA | D15: 0.0038289217 | E15: 0.67056422 | F15: =VLOOKUP(B15,[2]Hoja1!$C$2:$E$279,3,FALSE) -> 30702.27 | G15: =F15*D15 -> 117.55659 | H15: 29189.39 | I15: =H15*D15 -> 111.76389 | J15: =((F15/H15)*100)-100 -> 5.1829792 | K15: =$K$4*E15% -> 0.0038289217 | L15: =$L$4*E15% -> 13.5 | M15: =L15*F15 -> 414480.65
B16: =VLOOKUP(C16,[1]Hoja1!$B$2:$C$260,2,FALSE) -> 1220014 | C16: PVH LIQUIDA M 1222 | D16: 0.0031198621 | E16: 0.54638566 | F16: =VLOOKUP(B16,[2]Hoja1!$C$2:$E$279,3,FALSE) -> 14060 | G16: =F16*D16 -> 43.865261 | H16: 13300.01 | I16: =H16*D16 -> 41.494197 | J16: =((F16/H16)*100)-100 -> 5.7142062 | K16: =$K$4*E16% -> 0.0031198621 | L16: =$L$4*E16% -> 11 | M16: =L16*F16 -> 154660
B17: =VLOOKUP(C17,[1]Hoja1!$B$2:$C$260,2,FALSE) -> 1210003 | C17: ERITORBATO DE SODIO | D17: 0.00028362383 | E17: 0.049671424 | F17: =VLOOKUP(B17,[2]Hoja1!$C$2:$E$279,3,FALSE) -> 16235.45 | G17: =F17*D17 -> 4.6047605 | H17: 12852.58 | I17: =H17*D17 -> 3.6452979 | J17: =((F17/H17)*100)-100 -> 26.320552 | K17: =$K$4*E17% -> 0.00028362383 | L17: =$L$4*E17% -> 1 | M17: =L17*F17 -> 16235.45
B18: 1260024 | C18: EXTRACTO PROTEICO GP 83 | D18: 0.0056724766 | E18: 0.99342847 | F18: =VLOOKUP(B18,[2]Hoja1!$C$2:$E$279,3,FALSE) -> 12625.84 | G18: =F18*D18 -> 71.619782 | H18: 18900 | I18: =H18*D18 -> 107.20981 | J18: =((F18/H18)*100)-100 -> -33.196614 | K18: =$K$4*E18% -> 0.0056724766 | L18: =$L$4*E18% -> 20 | M18: =L18*F18 -> 252516.8
B19: =VLOOKUP(C19,[1]Hoja1!$B$2:$C$260,2,FALSE) -> 1260005 | C19: PLASMA PORCINO | D19: 0.0056724766 | E19: 0.99342847 | F19: =VLOOKUP(B19,[2]Hoja1!$C$2:$E$279,3,FALSE) -> 26429 | G19: =F19*D19 -> 149.91788 | H19: 25850 | I19: =H19*D19 -> 146.63352 | J19: =((F19/H19)*100)-100 -> 2.2398453 | K19: =$K$4*E19% -> 0.0056724766 | L19: =$L$4*E19% -> 20 | M19: =L19*F19 -> 528580
B20: =VLOOKUP(C20,[1]Hoja1!$B$2:$C$260,2,FALSE) -> 1260010 | C20: PROTEINA CONCENTRADA SOYA 65% | D20: 0.028362383 | E20: 4.9671424 | F20: =VLOOKUP(B20,[2]Hoja1!$C$2:$E$279,3,FALSE) -> 6959.71 | G20: =F20*D20 -> 197.39396 | H20: 9565.21 | I20: =H20*D20 -> 271.29215 | J20: =((F20/H20)*100)-100 -> -27.239339 | K20: =$K$4*E20% -> 0.028362383 | L20: =$L$4*E20% -> 100 | M20: =L20*F20 -> 695971
B21: =VLOOKUP(C21,[1]Hoja1!$B$2:$C$260,2,FALSE) -> 1260017 | C21: ALMIDON MODIFICADO DE MAIZ | D21: 0.028362383 | E21: 4.9671424 | F21: =VLOOKUP(B21,[2]Hoja1!$C$2:$E$279,3,FALSE) -> 4500 | G21: =F21*D21 -> 127.63072 | H21: 4500 | I21: =H21*D21 -> 127.63072 | J21: =((F21/H21)*100)-100 -> 0 | K21: =$K$4*E21% -> 0.028362383 | L21: =$L$4*E21% -> 100 | M21: =L21*F21 -> 450000
B22: =VLOOKUP(C22,[1]Hoja1!$B$2:$C$260,2,FALSE) -> 1260012 | C22: SOLU TEX GRASAS NEUTRO | D22: 0.0018492274 | E22: 0.32385768 | F22: =VLOOKUP(B22,[2]Hoja1!$C$2:$E$279,3,FALSE) -> 46081 | G22: =F22*D22 -> 85.214246 | H22: 46081 | I22: =H22*D22 -> 85.214246 | J22: =((F22/H22)*100)-100 -> 0 | K22: =$K$4*E22% -> 0.0018492274 | L22: =$L$4*E22% -> 6.52 | M22: =L22*F22 -> 300448.12
B23: =VLOOKUP(C23,[1]Hoja1!$B$2:$C$260,2,FALSE) -> 1121009 | C23: TOCINO NACIONAL | D23: 0.018497946 | E23: 3.2395702 | F23: =VLOOKUP(B23,[2]Hoja1!$C$2:$E$279,3,FALSE) -> 8741.62 | G23: =F23*D23 -> 161.70202 | H23: 8754.28 | I23: =H23*D23 -> 161.9362 | J23: =((F23/H23)*100)-100 -> -0.14461498 | K23: =$K$4*E23% -> 0.018497946 | L23: =$L$4*E23% -> 65.22 | M23: =L23*F23 -> 570128.46
B24: TOTAL | D24: 37.43 | E24: =SUM(E5:E23) -> 99.999608 | G24: =SUM(G5:G23) -> 2366.3793 | I24: =SUM(I5:I23) -> 2625.0952 | J24: =((G24/I24)*100)-100 -> -9.8554854 | M24: =SUM(M5:M23) -> 8179898.5
B26: MERMAS | D26: =+C29+(C29*C35%) -> 570.5
B27: Linea | C27: Salchichas
B28: Referencia | C28: Perro
B29: Presentación en Gramos | C29: 500
B30: Máquina | C30: 0
B31: Cocción | C31: 9
B32: Frío | C32: 2
B33: Recorte | C33: 1
B34: Sobrepeso | C34: 2.1
B35: Merma Total | C35: =C34+C33+C32+C31 -> 14.1
E36: =0.21*10 -> 2.1
B37: MATERIAL DE EMPAQUE
B38: CÓDIGO | C38: DESCRIPCIÓN | D38: CATIDAD | E38: =+'CIF Y PV'!$F$4 -> JUN-COP/UMB | F38: =+'CIF Y PV'!$G$4 -> JUN-COP/APP | G38: =+'CIF Y PV'!$H$4 -> MAY-COP/UMB | H38: =+'CIF Y PV'!$I$4 -> MAY-COP/APP | I38: % | J38: 3650
B39: =VLOOKUP(C39,[1]Hoja1!$B$2:$C$260,2,FALSE) -> 1370031 | C39: FUNDA CELULOSA 20 X 110 | D39: 2.1 | E39: =VLOOKUP(B39,[2]Hoja1!$C$2:$E$279,3,FALSE) -> 136.56 | F39: =E39*D39 -> 286.776 | G39: 153.32 | H39: =G39*D39 -> 321.972 | I39: =((F39/H39)*100)-100 -> -10.931385 | J39: =J38*D39 -> 7665
B40: =VLOOKUP(C40,[1]Hoja1!$B$2:$C$260,2,FALSE) -> 1310059 | C40: LAM SUP SALCH SUPER PERRO 500G 10UN 302 | D40: 0.15 | E40: =VLOOKUP(B40,[2]Hoja1!$C$2:$E$279,3,FALSE) -> 889 | F40: =E40*D40 -> 133.35 | G40: 889 | H40: =G40*D40 -> 133.35 | I40: =((F40/H40)*100)-100 -> 0 | J40: =J38*D40 -> 547.5
B41: 1320010 | C41: LAM INFE SUDPACK BTX 100-323 MM | D41: 0.15 | E41: =VLOOKUP(B41,[2]Hoja1!$C$2:$E$279,3,FALSE) -> 741.22 | F41: =E41*D41 -> 111.183 | G41: 833.3 | H41: =G41*D41 -> 124.995 | I41: =((F41/H41)*100)-100 -> -11.050042 | J41: =J38*D41 -> 547.5
B42: =VLOOKUP(C42,[1]Hoja1!$B$2:$C$260,2,FALSE) -> 1330076 | C42: ETI RESPALDO SCHA S.PERRO 500 G X 10 UND | D42: 1 | E42: =VLOOKUP(B42,[2]Hoja1!$C$2:$E$279,3,FALSE) -> 77 | F42: =E42*D42 -> 77 | G42: 77 | H42: =G42*D42 -> 77 | I42: =((F42/H42)*100)-100 -> 0 | J42: =J38*D42 -> 3650
C43: TOTAL | F43: =SUM(F39:F42) -> 608.309 | H43: =SUM(H39:H42) -> 657.317 | I43: =((F43/H43)*100)-100 -> -7.4557634
H44: =+'CIF Y PV'!$G$1 -> MAYO
B45: TOTAL INSUMOS (UND 480 G) | H45: =+F43+G24 -> 2974.6883
B46: ASIGNACIÓN MOD/CIF | H46: =+('CIF Y PV'!C3/1000)*500 -> 945
B47: TOTAL COSTO POR UND (480) | H47: =+H46+H45 -> 3919.6883
B48: PRECIO DE VENTA | H48: ='CIF Y PV'!C69 -> 8175
B49: MB | H49: =+(H48-H47)/H48 -> 0.52052742

Sheet SUPER PERRO X 2500
B2: SALCHICHA SUPER PERRO X 2.5 - 50 UNDS
B4: CÓDIGO | C4: DESCRIPCIÓN | D4: CATIDAD | E4: % | F4: =+'CIF Y PV'!$F$2 -> JUN-COP/Kg | G4: =+'CIF Y PV'!$G$2 -> JUN-COP/APP | H4: =+'CIF Y PV'!$H$2 -> MAY-COP/Kg | I4: =+'CIF Y PV'!$I$2 -> MAY-COP/APP | J4: % | K4: 2.85
B5: =VLOOKUP(C5,[1]Hoja1!$B$2:$C$260,2,FALSE) -> 1112001 | C5: PASTA DE POLLO IMPORTADA PREMIUM | D5: 1.3547632 | E5: 47.535552 | F5: =VLOOKUP(B5,[2]Hoja1!$C$2:$E$279,3,FALSE) -> 3663.96 | G5: =F5*D5 -> 4963.7983 | H5: 4222.72 | I5: =H5*D5 -> 5720.7858 | J5: =((F5/H5)*100)-100 -> -13.232229 | K5: =$K$4*E5% -> 1.3547632
B6: =VLOOKUP(C6,[1]Hoja1!$B$2:$C$260,2,FALSE) -> 2906001 | C6: EMULSION DE PIEL DE CERDO | D6: 0.24065805 | E6: 8.444142 | F6: =VLOOKUP(B6,[2]Hoja1!$C$2:$E$279,3,FALSE) -> 1956.71 | G6: =F6*D6 -> 470.89801 | H6: 2033.73 | I6: =H6*D6 -> 489.43349 | J6: =((F6/H6)*100)-100 -> -3.7871301 | K6: =$K$4*E6% -> 0.24065805
B7: =VLOOKUP(C7,[1]Hoja1!$B$2:$C$260,2,FALSE) -> 1131002 | C7: AGUA POTABLE | D7: 0.6975969 | E7: 24.477084 | F7: =VLOOKUP(B7,[2]Hoja1!$C$2:$E$279,3,FALSE) -> 0 | G7: =F7*D7 -> 0 | H7: 0 | I7: =H7*D7 -> 0 | J7: =((F7/H7)*100)-100 -> #DIV/0! | K7: =$K$4*E7% -> 0.6975969
B8: =VLOOKUP(C8,[1]Hoja1!$B$2:$C$260,2,FALSE) -> 1250009 | C8: COLOR NATURAL ROJO AC150 | D8: 0.0016987627 | E8: 0.059605708 | F8: =VLOOKUP(B8,[2]Hoja1!$C$2:$E$279,3,FALSE) -> 83551.55 | G8: =F8*D8 -> 141.93426 | H8: 71910.02 | I8: =H8*D8 -> 122.15806 | J8: =((F8/H8)*100)-100 -> 16.189023 | K8: =$K$4*E8% -> 0.0016987627
B9: =VLOOKUP(C9,[1]Hoja1!$B$2:$C$260,2,FALSE) -> 1250004 | C9: COLOR NATURAL NARANJA PR801WD | D9: 0.00022650169 | E9: 0.0079474278 | F9: =VLOOKUP(B9,[2]Hoja1!$C$2:$E$279,3,FALSE) -> 164481.95 | G9: =F9*D9 -> 37.25544 | H9: 156520.02 | I9: =H9*D9 -> 35.452049 | J9: =((F9/H9)*100)-100 -> 5.0868445 | K9: =$K$4*E9% -> 0.00022650169
B10: 1210005 | C10: SAL YODADA REFISAL | D10: 0.029925 | E10: 1.05 | F10: =VLOOKUP(B10,[2]Hoja1!$C$2:$E$279,3,FALSE) -> 1356 | G10: =F10*D10 -> 40.5783 | K10: =$K$4*E10% -> 0.029925
B11: 1210010 | C11: CLORURO DE POTASIO - KCL | D11: 0.01995 | E11: 0.7 | F11: =VLOOKUP(B11,[2]Hoja1!$C$2:$E$279,3,FALSE) -> 11600 | G11: =F11*D11 -> 231.42 | H11: 8910.1 | I11: =H11*D11 -> 177.7565 | J11: =((F11/H11)*100)-100 -> 30.189336 | K11: =$K$4*E11% -> 0.01995
B12: =VLOOKUP(C12,[1]Hoja1!$B$2:$C$260,2,FALSE) -> 1210004 | C12: SAL CURANTE AL 12 % | D12: 0.0047423792 | E12: 0.16639927 | F12: =VLOOKUP(B12,[2]Hoja1!$C$2:$E$279,3,FALSE) -> 3841 | G12: =F12*D12 -> 18.215478 | H12: 3508.01 | I12: =H12*D12 -> 16.636314 | J12: =((F12/H12)*100)-100 -> 9.4922762 | K12: =$K$4*E12% -> 0.0047423792
B13: =VLOOKUP(C13,[1]Hoja1!$B$2:$C$260,2,FALSE) -> 121007 | C13: SUPRA MEAT F451 | D13: 0.011325085 | E13: 0.39737139 | F13: =VLOOKUP(B13,[2]Hoja1!$C$2:$E$279,3,FALSE) -> 16905 | G13: =F13*D13 -> 191.45055 | H13: 16100 | I13: =H13*D13 -> 182.33386 | J13: =((F13/H13)*100)-100 -> 5 | K13: =$K$4*E13% -> 0.011325085
B14: =VLOOKUP(C14,[1]Hoja1!$B$2:$C$260,2,FALSE) -> 1240002 | C14: CONSERVANTE INBAC ACN NA | D14: 0.014156356 | E14: 0.49671424 | F14: =VLOOKUP(B14,[2]Hoja1!$C$2:$E$279,3,FALSE) -> 66115.8 | G14: =F14*D14 -> 935.95878 | H14: 70840.75 | I14: =H14*D14 -> 1002.8469 | J14: =((F14/H14)*100)-100 -> -6.6698193 | K14: =$K$4*E14% -> 0.014156356
B15: =VLOOKUP(C15,[1]Hoja1!$B$2:$C$260,2,FALSE) -> 1220015 | C15: MEZCLA LIQUIDA SALCHICHA | D15: 0.01911108 | E15: 0.67056422 | F15: =VLOOKUP(B15,[2]Hoja1!$C$2:$E$279,3,FALSE) -> 30702.27 | G15: =F15*D15 -> 586.75354 | H15: 29189.39 | I15: =H15*D15 -> 557.84077 | J15: =((F15/H15)*100)-100 -> 5.1829792 | K15: =$K$4*E15% -> 0.01911108
B16: =VLOOKUP(C16,[1]Hoja1!$B$2:$C$260,2,FALSE) -> 1220014 | C16: PVH LIQUIDA M 1222 | D16: 0.015571991 | E16: 0.54638566 | F16: =VLOOKUP(B16,[2]Hoja1!$C$2:$E$279,3,FALSE) -> 14060 | G16: =F16*D16 -> 218.9422 | H16: 13300.01 | I16: =H16*D16 -> 207.10764 | J16: =((F16/H16)*100)-100 -> 5.7142062 | K16: =$K$4*E16% -> 0.015571991
B17: =VLOOKUP(C17,[1]Hoja1!$B$2:$C$260,2,FALSE) -> 1210003 | C17: ERITORBATO DE SODIO | D17: 0.0014156356 | E17: 0.049671424 | F17: =VLOOKUP(B17,[2]Hoja1!$C$2:$E$279,3,FALSE) -> 16235.45 | G17: =F17*D17 -> 22.983481 | H17: 12852.58 | I17: =H17*D17 -> 18.194569 | J17: =((F17/H17)*100)-100 -> 26.320552 | K17: =$K$4*E17% -> 0.0014156356
B18: 1260024 | C18: EXTRACTO PROTEICO GP 83 | D18: 0.028312711 | E18: 0.99342847 | F18: =VLOOKUP(B18,[2]Hoja1!$C$2:$E$279,3,FALSE) -> 12625.84 | G18: =F18*D18 -> 357.47176 | H18: 18900 | I18: =H18*D18 -> 535.11025 | J18: =((F18/H18)*100)-100 -> -33.196614 | K18: =$K$4*E18% -> 0.028312711
B19: =VLOOKUP(C19,[1]Hoja1!$B$2:$C$260,2,FALSE) -> 1260005 | C19: PLASMA PORCINO | D19: 0.028312711 | E19: 0.99342847 | F19: =VLOOKUP(B19,[2]Hoja1!$C$2:$E$279,3,FALSE) -> 26429 | G19: =F19*D19 -> 748.27665 | H19: 25850 | I19: =H19*D19 -> 731.88359 | J19: =((F19/H19)*100)-100 -> 2.2398453 | K19: =$K$4*E19% -> 0.028312711
B20: =VLOOKUP(C20,[1]Hoja1!$B$2:$C$260,2,FALSE) -> 1260010 | C20: PROTEINA CONCENTRADA SOYA 65% | D20: 0.14156356 | E20: 4.9671424 | F20: =VLOOKUP(B20,[2]Hoja1!$C$2:$E$279,3,FALSE) -> 6959.71 | G20: =F20*D20 -> 985.2413 | H20: 9565.21 | I20: =H20*D20 -> 1354.0852 | J20: =((F20/H20)*100)-100 -> -27.239339 | K20: =$K$4*E20% -> 0.14156356
B21: =VLOOKUP(C21,[1]Hoja1!$B$2:$C$260,2,FALSE) -> 1260017 | C21: ALMIDON MODIFICADO DE MAIZ | D21: 0.14156356 | E21: 4.9671424 | F21: =VLOOKUP(B21,[2]Hoja1!$C$2:$E$279,3,FALSE) -> 4500 | G21: =F21*D21 -> 637.03601 | H21: 4500 | I21: =H21*D21 -> 637.03601 | J21: =((F21/H21)*100)-100 -> 0 | K21: =$K$4*E21% -> 0.14156356
B22: =VLOOKUP(C22,[1]Hoja1!$B$2:$C$260,2,FALSE) -> 1260012 | C22: SOLU TEX GRASAS NEUTRO | D22: 0.0092299439 | E22: 0.32385768 | F22: =VLOOKUP(B22,[2]Hoja1!$C$2:$E$279,3,FALSE) -> 46081 | G22: =F22*D22 -> 425.32505 | H22: 46081 | I22: =H22*D22 -> 425.32505 | J22: =((F22/H22)*100)-100 -> 0 | K22: =$K$4*E22% -> 0.0092299439
B23: =VLOOKUP(C23,[1]Hoja1!$B$2:$C$260,2,FALSE) -> 1121009 | C23: TOCINO NACIONAL | D23: 0.092327752 | E23: 3.2395702 | F23: =VLOOKUP(B23,[2]Hoja1!$C$2:$E$279,3,FALSE) -> 8741.62 | G23: =F23*D23 -> 807.09412 | H23: 8754.28 | I23: =H23*D23 -> 808.26299 | J23: =((F23/H23)*100)-100 -> -0.14461498 | K23: =$K$4*E23% -> 0.092327752
B24: TOTAL | D24: =SUM(D5:D23) -> 2.8524512 | E24: =SUM(E5:E23) -> 100.08601 | G24: =SUM(G5:G23) -> 11820.633 | I24: =SUM(I5:I23) -> 13022.249 | J24: =((G24/I24)*100)-100 -> -9.2274055
B26: MERMAS | D26: =+C29+(C29*C35%) -> 2850
B27: Linea | C27: Salchichas
B28: Referencia | C28: Perro
B29: Presentación en Gramos | C29: 2500
B30: Máquina | C30: 0
B31: Cocción | C31: 9
B32: Frío | C32: 2
B33: Recorte | C33: 1
B34: Sobrepeso | C34: 2
B35: Merma Total | C35: =C34+C33+C32+C31 -> 14
E36: =0.21*50 -> 10.5
B37: MATERIAL DE EMPAQUE
B38: CÓDIGO | C38: DESCRIPCIÓN | D38: CATIDAD | E38: =+'CIF Y PV'!$F$4 -> JUN-COP/UMB | F38: =+'CIF Y PV'!$G$4 -> JUN-COP/APP | G38: =+'CIF Y PV'!$H$4 -> MAY-COP/UMB | H38: =+'CIF Y PV'!$I$4 -> MAY-COP/APP | I38: % | J38: 8363
B39: =VLOOKUP(C39,[1]Hoja1!$B$2:$C$260,2,FALSE) -> 1370031 | C39: FUNDA CELULOSA 20 X 110 | D39: 10.5 | E39: =VLOOKUP(B39,[2]Hoja1!$C$2:$E$279,3,FALSE) -> 136.56 | F39: =E39*D39 -> 1433.88 | G39: 153.32 | H39: =G39*D39 -> 1609.86 | I39: =((E39/G39)*100)-100 -> -10.931385 | J39: =J38*D39 -> 87811.5
B40: 1330027 | C40: ETI SALCHICHA SUPER PERRO X 2.5 X 50 U | D40: 1 | E40: =VLOOKUP(B40,[2]Hoja1!$C$2:$E$279,3,FALSE) -> 331.33 | F40: =E40*D40 -> 331.33 | G40: 888.9 | H40: =G40*D40 -> 888.9 | I40: =((E40/G40)*100)-100 -> -62.725841 | J40: =J38*D40 -> 8363
B41: 1310018 | C41: LAM SUP TRANS ECOWEB M/PAUV 42U 301MM | D41: 0.3 | E41: =VLOOKUP(B41,[2]Hoja1!$C$2:$E$279,3,FALSE) -> 478.26 | F41: =E41*D41 -> 143.478
B42: =VLOOKUP(C42,[1]Hoja1!$B$2:$C$260,2,FALSE) -> 1320004 | C42: LAM INFE SUDPACK GVA200 BT323 MM 8MM | D42: 0.3 | E42: =VLOOKUP(B42,[2]Hoja1!$C$2:$E$279,3,FALSE) -> 1481.51 | F42: =E42*D42 -> 444.453 | G42: 1577.09 | H42: =G42*D42 -> 473.127 | I42: =((E42/G42)*100)-100 -> -6.0605292 | J42: =J38*D42 -> 2508.9
C43: TOTAL | F43: =SUM(F39:F42) -> 2353.141 | H43: =SUM(H39:H42) -> 2971.887 | I43: =((F43/H43)*100)-100 -> -20.819971
H44: =+'CIF Y PV'!$G$1 -> MAYO
B45: TOTAL INSUMOS (UND 2500 G) | H45: =+F43+G24 -> 14173.774
B46: ASIGNACIÓN MOD/CIF | H46: =+('CIF Y PV'!C3/1000)*2500 -> 4725
B47: TOTAL COSTO POR UND (2500) | H47: =+H46+H45 -> 18898.774
B48: PRECIO DE VENTA | H48: ='CIF Y PV'!C53 -> 35476.92
B49: MB | H49: =+(H48-H47)/H48 -> 0.46729383

Sheet SUPER PERRO X 2500 RX
B2: SALCHICHA SUPER PERRO X 2.5 - 50 UNDS - RX
B4: CÓDIGO | C4: DESCRIPCIÓN | D4: CATIDAD | E4: % | F4: =+'CIF Y PV'!$F$2 -> JUN-COP/Kg | G4: =+'CIF Y PV'!$G$2 -> JUN-COP/APP | H4: =+'CIF Y PV'!$H$2 -> MAY-COP/Kg | I4: =+'CIF Y PV'!$I$2 -> MAY-COP/APP | J4: % | K4: 2.85
B5: =VLOOKUP(C5,[1]Hoja1!$B$2:$C$260,2,FALSE) -> 1112001 | C5: PASTA DE POLLO IMPORTADA PREMIUM | D5: 1.3547632 | E5: 47.535552 | F5: =VLOOKUP(B5,[2]Hoja1!$C$2:$E$279,3,FALSE) -> 3663.96 | G5: =F5*D5 -> 4963.7983 | H5: 4222.72 | I5: =H5*D5 -> 5720.7858 | J5: =((F5/H5)*100)-100 -> -13.232229 | K5: =$K$4*E5% -> 1.3547632
B6: =VLOOKUP(C6,[1]Hoja1!$B$2:$C$260,2,FALSE) -> 2906001 | C6: EMULSION DE PIEL DE CERDO | D6: 0.24065805 | E6: 8.444142 | F6: =VLOOKUP(B6,[2]Hoja1!$C$2:$E$279,3,FALSE) -> 1956.71 | G6: =F6*D6 -> 470.89801 | H6: 2033.73 | I6: =H6*D6 -> 489.43349 | J6: =((F6/H6)*100)-100 -> -3.7871301 | K6: =$K$4*E6% -> 0.24065805
B7: =VLOOKUP(C7,[1]Hoja1!$B$2:$C$260,2,FALSE) -> 1131002 | C7: AGUA POTABLE | D7: 0.6975969 | E7: 24.477084 | F7: =VLOOKUP(B7,[2]Hoja1!$C$2:$E$279,3,FALSE) -> 0 | G7: =F7*D7 -> 0 | H7: 0 | I7: =H7*D7 -> 0 | J7: =((F7/H7)*100)-100 -> #DIV/0! | K7: =$K$4*E7% -> 0.6975969
B8: =VLOOKUP(C8,[1]Hoja1!$B$2:$C$260,2,FALSE) -> 1250009 | C8: COLOR NATURAL ROJO AC150 | D8: 0.0016987627 | E8: 0.059605708 | F8: =VLOOKUP(B8,[2]Hoja1!$C$2:$E$279,3,FALSE) -> 83551.55 | G8: =F8*D8 -> 141.93426 | H8: 71910.02 | I8: =H8*D8 -> 122.15806 | J8: =((F8/H8)*100)-100 -> 16.189023 | K8: =$K$4*E8% -> 0.0016987627
B9: =VLOOKUP(C9,[1]Hoja1!$B$2:$C$260,2,FALSE) -> 1250004 | C9: COLOR NATURAL NARANJA PR801WD | D9: 0.00022650169 | E9: 0.0079474278 | F9: =VLOOKUP(B9,[2]Hoja1!$C$2:$E$279,3,FALSE) -> 164481.95 | G9: =F9*D9 -> 37.25544 | H9: 156520.02 | I9: =H9*D9 -> 35.452049 | J9: =((F9/H9)*100)-100 -> 5.0868445 | K9: =$K$4*E9% -> 0.00022650169
B10: 1210005 | C10: SAL YODADA REFISAL | D10: 0.029925 | E10: 1.05 | F10: =VLOOKUP(B10,[2]Hoja1!$C$2:$E$279,3,FALSE) -> 1356 | G10: =F10*D10 -> 40.5783 | K10: =$K$4*E10% -> 0.029925
B11: 1210010 | C11: CLORURO DE POTASIO - KCL | D11: 0.01995 | E11: 0.7 | F11: =VLOOKUP(B11,[2]Hoja1!$C$2:$E$279,3,FALSE) -> 11600 | G11: =F11*D11 -> 231.42 | H11: 8910.1 | I11: =H11*D11 -> 177.7565 | J11: =((F11/H11)*100)-100 -> 30.189336 | K11: =$K$4*E11% -> 0.01995
B12: =VLOOKUP(C12,[1]Hoja1!$B$2:$C$260,2,FALSE) -> 1210004 | C12: SAL CURANTE AL 12 % | D12: 0.0047423792 | E12: 0.16639927 | F12: =VLOOKUP(B12,[2]Hoja1!$C$2:$E$279,3,FALSE) -> 3841 | G12: =F12*D12 -> 18.215478 | H12: 3508.01 | I12: =H12*D12 -> 16.636314 | J12: =((F12/H12)*100)-100 -> 9.4922762 | K12: =$K$4*E12% -> 0.0047423792
B13: =VLOOKUP(C13,[1]Hoja1!$B$2:$C$260,2,FALSE) -> 121007 | C13: SUPRA MEAT F451 | D13: 0.011325085 | E13: 0.39737139 | F13: =VLOOKUP(B13,[2]Hoja1!$C$2:$E$279,3,FALSE) -> 16905 | G13: =F13*D13 -> 191.45055 | H13: 16100 | I13: =H13*D13 -> 182.33386 | J13: =((F13/H13)*100)-100 -> 5 | K13: =$K$4*E13% -> 0.011325085
B14: =VLOOKUP(C14,[1]Hoja1!$B$2:$C$260,2,FALSE) -> 1240002 | C14: CONSERVANTE INBAC ACN NA | D14: 0.014156356 | E14: 0.49671424 | F14: =VLOOKUP(B14,[2]Hoja1!$C$2:$E$279,3,FALSE) -> 66115.8 | G14: =F14*D14 -> 935.95878 | H14: 70840.75 | I14: =H14*D14 -> 1002.8469 | J14: =((F14/H14)*100)-100 -> -6.6698193 | K14: =$K$4*E14% -> 0.014156356
B15: =VLOOKUP(C15,[1]Hoja1!$B$2:$C$260,2,FALSE) -> 1220015 | C15: MEZCLA LIQUIDA SALCHICHA | D15: 0.01911108 | E15: 0.67056422 | F15: =VLOOKUP(B15,[2]Hoja1!$C$2:$E$279,3,FALSE) -> 30702.27 | G15: =F15*D15 -> 586.75354 | H15: 29189.39 | I15: =H15*D15 -> 557.84077 | J15: =((F15/H15)*100)-100 -> 5.1829792 | K15: =$K$4*E15% -> 0.01911108
B16: =VLOOKUP(C16,[1]Hoja1!$B$2:$C$260,2,FALSE) -> 1220014 | C16: PVH LIQUIDA M 1222 | D16: 0.015571991 | E16: 0.54638566 | F16: =VLOOKUP(B16,[2]Hoja1!$C$2:$E$279,3,FALSE) -> 14060 | G16: =F16*D16 -> 218.9422 | H16: 13300.01 | I16: =H16*D16 -> 207.10764 | J16: =((F16/H16)*100)-100 -> 5.7142062 | K16: =$K$4*E16% -> 0.015571991
B17: =VLOOKUP(C17,[1]Hoja1!$B$2:$C$260,2,FALSE) -> 1210003 | C17: ERITORBATO DE SODIO | D17: 0.0014156356 | E17: 0.049671424 | F17: =VLOOKUP(B17,[2]Hoja1!$C$2:$E$279,3,FALSE) -> 16235.45 | G17: =F17*D17 -> 22.983481 | H17: 12852.58 | I17: =H17*D17 -> 18.194569 | J17: =((F17/H17)*100)-100 -> 26.320552 | K17: =$K$4*E17% -> 0.0014156356
B18: 1260024 | C18: EXTRACTO PROTEICO GP 83 | D18: 0.028312711 | E18: 0.99342847 | F18: =VLOOKUP(B18,[2]Hoja1!$C$2:$E$279,3,FALSE) -> 12625.84 | G18: =F18*D18 -> 357.47176 | H18: 18900 | I18: =H18*D18 -> 535.11025 | J18: =((F18/H18)*100)-100 -> -33.196614 | K18: =$K$4*E18% -> 0.028312711
B19: =VLOOKUP(C19,[1]Hoja1!$B$2:$C$260,2,FALSE) -> 1260005 | C19: PLASMA PORCINO | D19: 0.028312711 | E19: 0.99342847 | F19: =VLOOKUP(B19,[2]Hoja1!$C$2:$E$279,3,FALSE) -> 26429 | G19: =F19*D19 -> 748.27665 | H19: 25850 | I19: =H19*D19 -> 731.88359 | J19: =((F19/H19)*100)-100 -> 2.2398453 | K19: =$K$4*E19% -> 0.028312711
B20: =VLOOKUP(C20,[1]Hoja1!$B$2:$C$260,2,FALSE) -> 1260010 | C20: PROTEINA CONCENTRADA SOYA 65% | D20: 0.14156356 | E20: 4.9671424 | F20: =VLOOKUP(B20,[2]Hoja1!$C$2:$E$279,3,FALSE) -> 6959.71 | G20: =F20*D20 -> 985.2413 | H20: 9565.21 | I20: =H20*D20 -> 1354.0852 | J20: =((F20/H20)*100)-100 -> -27.239339 | K20: =$K$4*E20% -> 0.14156356
B21: =VLOOKUP(C21,[1]Hoja1!$B$2:$C$260,2,FALSE) -> 1260017 | C21: ALMIDON MODIFICADO DE MAIZ | D21: 0.14156356 | E21: 4.9671424 | F21: =VLOOKUP(B21,[2]Hoja1!$C$2:$E$279,3,FALSE) -> 4500 | G21: =F21*D21 -> 637.03601 | H21: 4500 | I21: =H21*D21 -> 637.03601 | J21: =((F21/H21)*100)-100 -> 0 | K21: =$K$4*E21% -> 0.14156356
B22: =VLOOKUP(C22,[1]Hoja1!$B$2:$C$260,2,FALSE) -> 1260012 | C22: SOLU TEX GRASAS NEUTRO | D22: 0.0092299439 | E22: 0.32385768 | F22: =VLOOKUP(B22,[2]Hoja1!$C$2:$E$279,3,FALSE) -> 46081 | G22: =F22*D22 -> 425.32505 | H22: 46081 | I22: =H22*D22 -> 425.32505 | J22: =((F22/H22)*100)-100 -> 0 | K22: =$K$4*E22% -> 0.0092299439
B23: =VLOOKUP(C23,[1]Hoja1!$B$2:$C$260,2,FALSE) -> 1121009 | C23: TOCINO NACIONAL | D23: 0.092327752 | E23: 3.2395702 | F23: =VLOOKUP(B23,[2]Hoja1!$C$2:$E$279,3,FALSE) -> 8741.62 | G23: =F23*D23 -> 807.09412 | H23: 8754.28 | I23: =H23*D23 -> 808.26299 | J23: =((F23/H23)*100)-100 -> -0.14461498 | K23: =$K$4*E23% -> 0.092327752
B24: TOTAL | D24: =SUM(D5:D23) -> 2.8524512 | E24: =SUM(E5:E23) -> 100.08601 | G24: =SUM(G5:G23) -> 11820.633 | I24: =SUM(I5:I23) -> 13022.249 | J24: =((G24/I24)*100)-100 -> -9.2274055
B26: MERMAS | D26: =+C29+(C29*C35%) -> 2850
B27: Linea | C27: Salchichas
B28: Referencia | C28: Perro
B29: Presentación en Gramos | C29: 2500
B30: Máquina | C30: 0
B31: Cocción | C31: 9
B32: Frío | C32: 2
B33: Recorte | C33: 1
B34: Sobrepeso | C34: 2
B35: Merma Total | C35: =C34+C33+C32+C31 -> 14
E36: =0.21*50 -> 10.5
B37: MATERIAL DE EMPAQUE
B38: CÓDIGO | C38: DESCRIPCIÓN | D38: CATIDAD | E38: =+'CIF Y PV'!$F$4 -> JUN-COP/UMB | F38: =+'CIF Y PV'!$G$4 -> JUN-COP/APP | G38: =+'CIF Y PV'!$H$4 -> MAY-COP/UMB | H38: =+'CIF Y PV'!$I$4 -> MAY-COP/APP | I38: % | J38: 8363
B39: =VLOOKUP(C39,[1]Hoja1!$B$2:$C$260,2,FALSE) -> 1370031 | C39: FUNDA CELULOSA 20 X 110 | D39: 10.5 | E39: =VLOOKUP(B39,[2]Hoja1!$C$2:$E$279,3,FALSE) -> 136.56 | F39: =E39*D39 -> 1433.88 | G39: 153.32 | H39: =G39*D39 -> 1609.86 | I39: =((E39/G39)*100)-100 -> -10.931385 | J39: =J38*D39 -> 87811.5
B40: 1330027 | C40: ETI SALCHICHA SUPER PERRO X 2.5 X 50 U | D40: 1 | E40: =VLOOKUP(B40,[2]Hoja1!$C$2:$E$279,3,FALSE) -> 331.33 | F40: =E40*D40 -> 331.33
B41: 1310066 | C41: LAM SUP TRANS ECOWEB 42 U 445 MM | D41: 0.3 | E41: =VLOOKUP(B41,[2]Hoja1!$C$2:$E$279,3,FALSE) -> 765.19 | F41: =E41*D41 -> 229.557 | G41: 888.9 | H41: =G41*D41 -> 266.67 | I41: =((E41/G41)*100)-100 -> -13.917201 | J41: =J38*D41 -> 2508.9
B42: 1320004 | C42: LAM INFE SUDPACK GVA200 BT323 MM 8MM | D42: 0.3 | E42: =VLOOKUP(B42,[2]Hoja1!$C$2:$E$279,3,FALSE) -> 1481.51 | F42: =E42*D42 -> 444.453 | G42: 1577.09 | H42: =G42*D42 -> 473.127 | I42: =((E42/G42)*100)-100 -> -6.0605292 | J42: =J38*D42 -> 2508.9
C43: TOTAL | F43: =SUM(F39:F42) -> 2439.22 | H43: =SUM(H39:H42) -> 2349.657 | I43: =((F43/H43)*100)-100 -> 3.8117478
H44: =+'CIF Y PV'!$G$1 -> MAYO
B45: TOTAL INSUMOS (UND 2500 G) | H45: =+F43+G24 -> 14259.853
B46: ASIGNACIÓN MOD/CIF | H46: =+('CIF Y PV'!C3/1000)*2500 -> 4725
B47: TOTAL COSTO POR UND (2500) | H47: =+H46+H45 -> 18984.853
B48: PRECIO DE VENTA | H48: ='CIF Y PV'!C53 -> 35476.92
B49: MB | H49: =+(H48-H47)/H48 -> 0.46486749

Sheet CHRZ CON TERNERA 110 G 2 UND
B2: CHORIZO CON TERNERA 110 G 2 UND
L3: Batch | M3: Costo del Batch
B4: CÓDIGO | C4: DESCRIPCIÓN | D4: CATIDAD | E4: % | F4: =+'CIF Y PV'!$F$2 -> JUN-COP/Kg | G4: =+'CIF Y PV'!$G$2 -> JUN-COP/APP | H4: =+'CIF Y PV'!$H$2 -> MAY-COP/Kg | I4: =+'CIF Y PV'!$I$2 -> MAY-COP/APP | J4: % | K4: =+D21/1000 -> 0.12342 | L4: 498.5
B5: =VLOOKUP(C5,[1]Hoja1!$B$2:$C$260,2,FALSE) -> 2903003 | C5: BRAZUELO CHARQUEADO | D5: 0.051248921 | E5: 41.524 | F5: =VLOOKUP(B5,[2]Hoja1!$C$2:$E$279,3,FALSE) -> 11506.13 | G5: =F5*D5 -> 589.67675 | H5: 15000 | I5: =H5*D5 -> 768.73381 | J5: =((F5/H5)*100)-100 -> -23.292467 | K5: =$K$4*E5% -> 0.051248921 | L5: =$L$4*E5% -> 206.99714 | M5: =L5*F5 -> 2381736
B6: =VLOOKUP(C6,[1]Hoja1!$B$2:$C$260,2,FALSE) -> 1141001 | C6: CARNE DE TERNERA | D6: 0.0049516104 | E6: 4.012 | F6: =VLOOKUP(B6,[2]Hoja1!$C$2:$E$279,3,FALSE) -> 15597.29 | G6: =F6*D6 -> 77.231703 | H6: 15999.99 | I6: =H6*D6 -> 79.225717 | J6: =((F6/H6)*100)-100 -> -2.5168766 | K6: =$K$4*E6% -> 0.0049516104 | L6: =$L$4*E6% -> 19.99982 | M6: =L6*F6 -> 311942.99
B7: =VLOOKUP(C7,[1]Hoja1!$B$2:$C$260,2,FALSE) -> 1131002 | C7: AGUA POTABLE | D7: 0.024758052 | E7: 20.06 | F7: =VLOOKUP(B7,[2]Hoja1!$C$2:$E$279,3,FALSE) -> 0 | G7: =F7*D7 -> 0 | H7: 0 | I7: =H7*D7 -> 0 | J7: =((F7/H7)*100)-100 -> #DIV/0! | K7: =$K$4*E7% -> 0.024758052 | L7: =$L$4*E7% -> 99.9991 | M7: =L7*F7 -> 0
B8: =VLOOKUP(C8,[1]Hoja1!$B$2:$C$260,2,FALSE) -> 1230006 | C8: PREPARADO SABOR CHORIZO TERNERA | D8: 0.0023523852 | E8: 1.906 | F8: =VLOOKUP(B8,[2]Hoja1!$C$2:$E$279,3,FALSE) -> 44693.38 | G8: =F8*D8 -> 105.13605 | H8: 42594.15 | I8: =H8*D8 -> 100.19785 | J8: =((F8/H8)*100)-100 -> 4.9284467 | K8: =$K$4*E8% -> 0.0023523852 | L8: =$L$4*E8% -> 9.50141 | M8: =L8*F8 -> 424650.13
B9: =VLOOKUP(C9,[1]Hoja1!$B$2:$C$260,2,FALSE) -> 1210006 | C9: SAL REDUCIDA EN SODIO 60/40 | D9: 0.0017945268 | E9: 1.454 | F9: =VLOOKUP(B9,[2]Hoja1!$C$2:$E$279,3,FALSE) -> 8904.45 | G9: =F9*D9 -> 15.979274 | H9: 8910.1 | I9: =H9*D9 -> 15.989413 | J9: =((F9/H9)*100)-100 -> -0.063411185 | K9: =$K$4*E9% -> 0.0017945268 | L9: =$L$4*E9% -> 7.24819 | M9: =L9*F9 -> 64541.145
B10: =VLOOKUP(C10,[1]Hoja1!$B$2:$C$260,2,FALSE) -> 1210004 | C10: SAL CURANTE AL 12 % | D10: 0.000104907 | E10: 0.085 | F10: =VLOOKUP(B10,[2]Hoja1!$C$2:$E$279,3,FALSE) -> 3841 | G10: =F10*D10 -> 0.40294779 | H10: 3508.01 | I10: =H10*D10 -> 0.36801481 | J10: =((F10/H10)*100)-100 -> 9.4922762 | K10: =$K$4*E10% -> 0.000104907 | L10: =$L$4*E10% -> 0.423725 | M10: =L10*F10 -> 1627.5277
B11: =VLOOKUP(C11,[1]Hoja1!$B$2:$C$260,2,FALSE) -> 121007 | C11: SUPRA MEAT F451 | D11: 0.0004949142 | E11: 0.401 | F11: =VLOOKUP(B11,[2]Hoja1!$C$2:$E$279,3,FALSE) -> 16905 | G11: =F11*D11 -> 8.3665246 | H11: 16100 | I11: =H11*D11 -> 7.9681186 | J11: =((F11/H11)*100)-100 -> 5 | K11: =$K$4*E11% -> 0.0004949142 | L11: =$L$4*E11% -> 1.998985 | M11: =L11*F11 -> 33792.841
B12: =VLOOKUP(C12,[1]Hoja1!$B$2:$C$260,2,FALSE) -> 1250003 | C12: COLOR NATURAL HEMOGLOBINA I RED | D12: 8.14572e-05 | E12: 0.066 | F12: =VLOOKUP(B12,[2]Hoja1!$C$2:$E$279,3,FALSE) -> 50952.79 | G12: =F12*D12 -> 4.1504716 | H12: 47385.41 | I12: =H12*D12 -> 3.8598828 | J12: =((F12/H12)*100)-100 -> 7.5284354 | K12: =$K$4*E12% -> 8.14572e-05 | L12: =$L$4*E12% -> 0.32901 | M12: =L12*F12 -> 16763.977
B13: =VLOOKUP(C13,[1]Hoja1!$B$2:$C$260,2,FALSE) -> 1250002 | C13: COLOR LOY NARANJA LIQ A10 1 | D13: 0.0002110482 | E13: 0.171 | F13: =VLOOKUP(B13,[2]Hoja1!$C$2:$E$279,3,FALSE) -> 44120.54 | G13: =F13*D13 -> 9.3115606 | H13: 43034 | I13: =H13*D13 -> 9.0822482 | J13: =((F13/H13)*100)-100 -> 2.5248408 | K13: =$K$4*E13% -> 0.0002110482 | L13: =$L$4*E13% -> 0.852435 | M13: =L13*F13 -> 37609.893
B14: =VLOOKUP(C14,[1]Hoja1!$B$2:$C$260,2,FALSE) -> 1260009 | C14: PROTEINA CONCENTRADA DE SOYA 70% | D14: 0.004085202 | E14: 3.31 | F14: =VLOOKUP(B14,[2]Hoja1!$C$2:$E$279,3,FALSE) -> 7033.69 | G14: =F14*D14 -> 28.734044 | H14: 9565.21 | I14: =H14*D14 -> 39.075815 | J14: =((F14/H14)*100)-100 -> -26.465911 | K14: =$K$4*E14% -> 0.004085202 | L14: =$L$4*E14% -> 16.50035 | M14: =L14*F14 -> 116058.35
B15: =VLOOKUP(C15,[1]Hoja1!$B$2:$C$260,2,FALSE) -> 1121009 | C15: TOCINO NACIONAL | D15: 0.029709662 | E15: 24.072 | F15: =VLOOKUP(B15,[2]Hoja1!$C$2:$E$279,3,FALSE) -> 8741.62 | G15: =F15*D15 -> 259.71058 | H15: 8754.28 | I15: =H15*D15 -> 260.0867 | J15: =((F15/H15)*100)-100 -> -0.14461498 | K15: =$K$4*E15% -> 0.029709662 | L15: =$L$4*E15% -> 119.99892 | M15: =L15*F15 -> 1048985
B16: =VLOOKUP(C16,[1]Hoja1!$B$2:$C$260,2,FALSE) -> 1250005 | C16: COLOR NATURAL NARANJA RA 40-3 9827 | D16: 0.000160446 | E16: 0.13 | F16: =VLOOKUP(B16,[2]Hoja1!$C$2:$E$279,3,FALSE) -> 66921.05 | G16: =F16*D16 -> 10.737215 | H16: 62991.09 | I16: =H16*D16 -> 10.106668 | J16: =((F16/H16)*100)-100 -> 6.2389141 | K16: =$K$4*E16% -> 0.000160446 | L16: =$L$4*E16% -> 0.64805 | M16: =L16*F16 -> 43368.186
B17: =VLOOKUP(C17,[1]Hoja1!$B$2:$C$260,2,FALSE) -> 1260017 | C17: ALMIDON MODIFICADO DE MAIZ | D17: 0.0034656336 | E17: 2.808 | F17: =VLOOKUP(B17,[2]Hoja1!$C$2:$E$279,3,FALSE) -> 4500 | G17: =F17*D17 -> 15.595351 | H17: 4500 | I17: =H17*D17 -> 15.595351 | J17: =((F17/H17)*100)-100 -> 0 | K17: =$K$4*E17% -> 0.0034656336 | L17: =$L$4*E17% -> 13.99788 | M17: =L17*F17 -> 62990.46
F18: =VLOOKUP(B18,[2]Hoja1!$C$2:$E$279,3,FALSE) -> #N/A | I18: =H18*D18 -> 0 | L18: =$L$4+E18 -> 498.5
B19: TOTAL | D19: =SUM(D5:D17) -> 0.12341877 | E19: =SUM(E5:E17) -> 99.999 | G19: =SUM(G5:G17) -> 1125.0325 | I19: =SUM(I5:I17) -> 1310.2896 | J19: =((G19/I19)*100)-100 -> -14.13864 | L19: =SUM(L5:L17) -> 498.49502 | M19: =SUM(M5:M17) -> 4544066.5
B21: MERMAS | D21: =+C24+(C24*C30%) -> 123.42
B22: Linea | C22: Chorizos
B23: Referencia | C23: Chorizo con Ternera
B24: Presentación en Gramos | C24: 110
B25: Máquina | C25: 0
B26: Cocción | C26: 6
B27: Frío | C27: 1
B28: Recorte | C28: 1
B29: Sobrepeso | C29: 4.2
B30: Merma Total | C30: =C29+C28+C27+C26 -> 12.2
E31: =0.0608*2 -> 0.1216
B32: MATERIAL DE EMPAQUE
B33: CÓDIGO | C33: DESCRIPCIÓN | D33: CATIDAD | E33: =+'CIF Y PV'!$F$4 -> JUN-COP/UMB | F33: =+'CIF Y PV'!$G$4 -> JUN-COP/APP | G33: =+'CIF Y PV'!$H$4 -> MAY-COP/UMB | H33: =+'CIF Y PV'!$I$4 -> MAY-COP/APP | I33: % | J33: 13522
B34: =VLOOKUP(C34,[1]Hoja1!$B$2:$C$260,2,FALSE) -> 1370009 | C34: FUNDA COLAGENO ND 26/60 | D34: 0.3 | E34: =VLOOKUP(B34,[2]Hoja1!$C$2:$E$279,3,FALSE) -> 487.07 | F34: =E34*D34 -> 146.121 | G34: 504.87 | H34: =G34*D34 -> 151.461 | I34: =((E34/G34)*100)-100 -> -3.5256601 | J34: =J33*D34 -> 4056.6
B35: 1320010 | C35: LAM INFE SUDPACK BTX 100-323 MM | D35: 0.038 | E35: =VLOOKUP(B35,[2]Hoja1!$C$2:$E$279,3,FALSE) -> 741.22 | F35: =E35*D35 -> 28.16636 | G35: 828.94 | H35: =G35*D35 -> 31.49972 | I35: =((E35/G35)*100)-100 -> -10.582189 | J35: =J33*D35 -> 513.836
B36: =VLOOKUP(C36,[1]Hoja1!$B$2:$C$260,2,FALSE) -> 1310018 | C36: LAM SUP TRANS ECOWEB M/PAUV 42U 301MM | D36: 0.038 | E36: =VLOOKUP(B36,[2]Hoja1!$C$2:$E$279,3,FALSE) -> 478.26 | F36: =E36*D36 -> 18.17388 | G36: 503.51 | H36: =G36*D36 -> 19.13338
B37: =VLOOKUP(C37,[1]Hoja1!$B$2:$C$260,2,FALSE) -> 1330081 | C37: ETI CHORIZO CON TERNERA X 110 GR X 2 U | D37: 1 | E37: =VLOOKUP(B37,[2]Hoja1!$C$2:$E$279,3,FALSE) -> 137.25 | F37: =E37*D37 -> 137.25 | G37: 120 | H37: =G37*D37 -> 120 | I37: =((E37/G37)*100)-100 -> 14.375 | J37: =J33*D37 -> 13522
C38: TOTAL | F38: =SUM(F34:F37) -> 329.71124 | H38: =SUM(H34:H37) -> 322.0941 | I38: =((F38/H38)*100)-100 -> 2.3648803
H39: =+'CIF Y PV'!$G$1 -> MAYO
B40: TOTAL INSUMOS (UND 110 G) | H40: =F38+G19 -> 1454.7437
B41: ASIGNACIÓN MOD/CIF | H41: =+('CIF Y PV'!C3/1000)*110 -> 207.9
B42: TOTAL COSTO POR UND (120) | H42: =H40+H41 -> 1662.6437
A43: Ya está en etiqueta con lamina transparente | B43: PRECIO DE VENTA | H43: ='CIF Y PV'!C10 -> 2862.885
B44: MB | H44: =+(H43-H42)/H43 -> 0.41924188

Sheet CHORIZO CON TERNERA 220
B2: CHORIZO CON TERNERA X 220 G - 4 UNDS
B4: CÓDIGO | C4: DESCRIPCIÓN | D4: CATIDAD | E4: % | F4: =+'CIF Y PV'!$F$2 -> JUN-COP/Kg | G4: =+'CIF Y PV'!$G$2 -> JUN-COP/APP | H4: =+'CIF Y PV'!$H$2 -> MAY-COP/Kg | I4: =+'CIF Y PV'!$I$2 -> MAY-COP/APP | J4: % | K4: =+D21/1000 -> 0.24222
B5: =VLOOKUP(C5,[1]Hoja1!$B$2:$C$260,2,FALSE) -> 2903003 | C5: BRAZUELO CHARQUEADO | D5: 0.10057943 | E5: 41.524 | F5: =VLOOKUP(B5,[2]Hoja1!$C$2:$E$279,3,FALSE) -> 11506.13 | G5: =F5*D5 -> 1157.28 | H5: 14000 | I5: =H5*D5 -> 1408.1121 | J5: =((F5/H5)*100)-100 -> -17.813357 | K5: =$K$4*E5% -> 0.10057943
B6: =VLOOKUP(C6,[1]Hoja1!$B$2:$C$260,2,FALSE) -> 1141001 | C6: CARNE DE TERNERA | D6: 0.0097178664 | E6: 4.012 | F6: =VLOOKUP(B6,[2]Hoja1!$C$2:$E$279,3,FALSE) -> 15597.29 | G6: =F6*D6 -> 151.57238 | H6: 15999.99 | I6: =H6*D6 -> 155.48577 | J6: =((F6/H6)*100)-100 -> -2.5168766 | K6: =$K$4*E6% -> 0.0097178664
B7: =VLOOKUP(C7,[1]Hoja1!$B$2:$C$260,2,FALSE) -> 1131002 | C7: AGUA POTABLE | D7: 0.048589332 | E7: 20.06 | F7: =VLOOKUP(B7,[2]Hoja1!$C$2:$E$279,3,FALSE) -> 0 | G7: =F7*D7 -> 0 | H7: 0 | I7: =H7*D7 -> 0 | J7: =((F7/H7)*100)-100 -> #DIV/0! | K7: =$K$4*E7% -> 0.048589332
B8: =VLOOKUP(C8,[1]Hoja1!$B$2:$C$260,2,FALSE) -> 1230006 | C8: PREPARADO SABOR CHORIZO TERNERA | D8: 0.0046167132 | E8: 1.906 | F8: =VLOOKUP(B8,[2]Hoja1!$C$2:$E$279,3,FALSE) -> 44693.38 | G8: =F8*D8 -> 206.33652 | H8: 42594.15 | I8: =H8*D8 -> 196.64497 | J8: =((F8/H8)*100)-100 -> 4.9284467 | K8: =$K$4*E8% -> 0.0046167132
B9: =VLOOKUP(C9,[1]Hoja1!$B$2:$C$260,2,FALSE) -> 1210006 | C9: SAL REDUCIDA EN SODIO 60/40 | D9: 0.0035218788 | E9: 1.454 | F9: =VLOOKUP(B9,[2]Hoja1!$C$2:$E$279,3,FALSE) -> 8904.45 | G9: =F9*D9 -> 31.360394 | H9: 8910.1 | I9: =H9*D9 -> 31.380292 | J9: =((F9/H9)*100)-100 -> -0.063411185 | K9: =$K$4*E9% -> 0.0035218788
B10: =VLOOKUP(C10,[1]Hoja1!$B$2:$C$260,2,FALSE) -> 1210004 | C10: SAL CURANTE AL 12 % | D10: 0.000205887 | E10: 0.085 | F10: =VLOOKUP(B10,[2]Hoja1!$C$2:$E$279,3,FALSE) -> 3841 | G10: =F10*D10 -> 0.79081197 | H10: 3508.01 | I10: =H10*D10 -> 0.72225365 | J10: =((F10/H10)*100)-100 -> 9.4922762 | K10: =$K$4*E10% -> 0.000205887
B11: =VLOOKUP(C11,[1]Hoja1!$B$2:$C$260,2,FALSE) -> 121007 | C11: SUPRA MEAT F451 | D11: 0.0009713022 | E11: 0.401 | F11: =VLOOKUP(B11,[2]Hoja1!$C$2:$E$279,3,FALSE) -> 16905 | G11: =F11*D11 -> 16.419864 | H11: 16100 | I11: =H11*D11 -> 15.637965 | J11: =((F11/H11)*100)-100 -> 5 | K11: =$K$4*E11% -> 0.0009713022
B12: =VLOOKUP(C12,[1]Hoja1!$B$2:$C$260,2,FALSE) -> 1250003 | C12: COLOR NATURAL HEMOGLOBINA I RED | D12: 0.0001598652 | E12: 0.066 | F12: =VLOOKUP(B12,[2]Hoja1!$C$2:$E$279,3,FALSE) -> 50952.79 | G12: =F12*D12 -> 8.145578 | H12: 47385.41 | I12: =H12*D12 -> 7.575278 | J12: =((F12/H12)*100)-100 -> 7.5284354 | K12: =$K$4*E12% -> 0.0001598652
B13: =VLOOKUP(C13,[1]Hoja1!$B$2:$C$260,2,FALSE) -> 1250002 | C13: COLOR LOY NARANJA LIQ A10 1 | D13: 0.0004141962 | E13: 0.171 | F13: =VLOOKUP(B13,[2]Hoja1!$C$2:$E$279,3,FALSE) -> 44120.54 | G13: =F13*D13 -> 18.27456 | H13: 43034 | I13: =H13*D13 -> 17.824519 | J13: =((F13/H13)*100)-100 -> 2.5248408 | K13: =$K$4*E13% -> 0.0004141962
B14: =VLOOKUP(C14,[1]Hoja1!$B$2:$C$260,2,FALSE) -> 1260009 | C14: PROTEINA CONCENTRADA DE SOYA 70% | D14: 0.008017482 | E14: 3.31 | F14: =VLOOKUP(B14,[2]Hoja1!$C$2:$E$279,3,FALSE) -> 7033.69 | G14: =F14*D14 -> 56.392483 | H14: 9565.21 | I14: =H14*D14 -> 76.688899 | J14: =((F14/H14)*100)-100 -> -26.465911 | K14: =$K$4*E14% -> 0.008017482
B15: =VLOOKUP(C15,[1]Hoja1!$B$2:$C$260,2,FALSE) -> 1121009 | C15: TOCINO NACIONAL | D15: 0.058307198 | E15: 24.072 | F15: =VLOOKUP(B15,[2]Hoja1!$C$2:$E$279,3,FALSE) -> 8741.62 | G15: =F15*D15 -> 509.69937 | H15: 8754.28 | I15: =H15*D15 -> 510.43754 | J15: =((F15/H15)*100)-100 -> -0.14461498 | K15: =$K$4*E15% -> 0.058307198
B16: =VLOOKUP(C16,[1]Hoja1!$B$2:$C$260,2,FALSE) -> 1250005 | C16: COLOR NATURAL NARANJA RA 40-3 9827 | D16: 0.000314886 | E16: 0.13 | F16: =VLOOKUP(B16,[2]Hoja1!$C$2:$E$279,3,FALSE) -> 66921.05 | G16: =F16*D16 -> 21.072502 | H16: 62991.09 | I16: =H16*D16 -> 19.835012 | J16: =((F16/H16)*100)-100 -> 6.2389141 | K16: =$K$4*E16% -> 0.000314886
B17: =VLOOKUP(C17,[1]Hoja1!$B$2:$C$260,2,FALSE) -> 1260017 | C17: ALMIDON MODIFICADO DE MAIZ | D17: 0.0068015376 | E17: 2.808 | F17: =VLOOKUP(B17,[2]Hoja1!$C$2:$E$279,3,FALSE) -> 4500 | G17: =F17*D17 -> 30.606919 | H17: 4500 | I17: =H17*D17 -> 30.606919 | J17: =((F17/H17)*100)-100 -> 0 | K17: =$K$4*E17% -> 0.0068015376
F18: =VLOOKUP(B18,[2]Hoja1!$C$2:$E$279,3,FALSE) -> #N/A | G18: =F18*D18 -> #N/A | I18: =H18*D18 -> 0
B19: TOTAL | D19: =SUM(D5:D17) -> 0.24221758 | E19: =SUM(E5:E17) -> 99.999 | G19: =SUM(G5:G17) -> 2207.9514 | I19: =SUM(I5:I17) -> 2470.9515 | J19: =((G19/I19)*100)-100 -> -10.643676
B21: MERMAS | D21: =+C24+(C24*C30%) -> 242.22
B22: Linea | C22: Picados
B23: Referencia | C23: Chorizo con Ternera
B24: Presentación en Gramos | C24: 220
B25: Máquina | C25: 0
B26: Cocción | C26: 6
B27: Frío | C27: 1
B28: Recorte | C28: 1
B29: Sobrepeso | C29: 2.1
B30: Merma Total | C30: =C29+C28+C27+C26 -> 10.1
E31: =0.015*4 -> 0.06
B32: MATERIAL DE EMPAQUE
B33: CÓDIGO | C33: DESCRIPCIÓN | D33: CATIDAD | E33: =+'CIF Y PV'!$F$4 -> JUN-COP/UMB | F33: =+'CIF Y PV'!$G$4 -> JUN-COP/APP | G33: =+'CIF Y PV'!$H$4 -> MAY-COP/UMB | H33: =+'CIF Y PV'!$I$4 -> MAY-COP/APP | I33: % | J33: 3380
B34: =VLOOKUP(C34,[1]Hoja1!$B$2:$C$260,2,FALSE) -> 1370009 | C34: FUNDA COLAGENO ND 26/60 | D34: 0.06 | E34: =VLOOKUP(B34,[2]Hoja1!$C$2:$E$279,3,FALSE) -> 487.07 | F34: =E34*D34 -> 29.2242 | G34: 504.87 | H34: =G34*D34 -> 30.2922 | I34: =((E34/G34)*100)-100 -> -3.5256601 | J34: =$J$33*D34 -> 202.8
B35: =VLOOKUP(C35,[1]Hoja1!$B$2:$C$260,2,FALSE) -> 1320005 | C35: LAM INFE SUDPACK GVP 130-323 MM | D35: 0.075 | E35: =VLOOKUP(B35,[2]Hoja1!$C$2:$E$279,3,FALSE) -> 740.21 | F35: =E35*D35 -> 55.51575 | G35: 828.94 | H35: =G35*D35 -> 62.1705 | I35: =((E35/G35)*100)-100 -> -10.704032 | J35: =$J$33*D35 -> 253.5
B36: =VLOOKUP(C36,[1]Hoja1!$B$2:$C$260,2,FALSE) -> 1310055 | C36: LAM SUP CHZO TERNER 220 G X 4 U 302 MM | D36: 0.075 | E36: =VLOOKUP(B36,[2]Hoja1!$C$2:$E$279,3,FALSE) -> 889 | F36: =E36*D36 -> 66.675 | G36: 889 | H36: =G36*D36 -> 66.675 | I36: =((E36/G36)*100)-100 -> 0 | J36: =$J$33*D36 -> 253.5
B37: =VLOOKUP(C37,[1]Hoja1!$B$2:$C$260,2,FALSE) -> 1330074 | C37: ETI RESPALDO CHZO TERNERA 220 G X 4 UN | D37: 1 | E37: =VLOOKUP(B37,[2]Hoja1!$C$2:$E$279,3,FALSE) -> 87.82 | F37: =E37*D37 -> 87.82 | G37: 77 | H37: =G37*D37 -> 77 | I37: =((E37/G37)*100)-100 -> 14.051948 | J37: =$J$33*D37 -> 3380
C38: TOTAL | F38: =SUM(F34:F37) -> 239.23495 | H38: =SUM(H34:H37) -> 236.1377 | I38: =((F38/H38)*100)-100 -> 1.3116288
H39: =+'CIF Y PV'!$G$1 -> MAYO
B40: TOTAL INSUMOS (UND 440 G) | H40: =+F38+G19 -> 2447.1864
B41: ASIGNACIÓN MOD/CIF | H41: =+('CIF Y PV'!C3/1000)*440 -> 831.6
B42: TOTAL COSTO POR UND (440) | H42: =+H40+H41 -> 3278.7864
B43: PRECIO DE VENTA | H43: ='CIF Y PV'!C11 -> 5559
B44: MB | H44: =+(H43-H42)/H43 -> 0.41018414

Sheet CHORIZO CON TERNERA 440 G FZAN
B2: CHORIZO CON TERNERA X 440 G - 8 UNDS
B4: CÓDIGO | C4: DESCRIPCIÓN | D4: CATIDAD | E4: % | F4: =+'CIF Y PV'!$F$2 -> JUN-COP/Kg | G4: =+'CIF Y PV'!$G$2 -> JUN-COP/APP | H4: =+'CIF Y PV'!$H$2 -> MAY-COP/Kg | I4: =+'CIF Y PV'!$I$2 -> MAY-COP/APP | J4: % | K4: =+D21/1000 -> 0.48444
B5: =VLOOKUP(C5,[1]Hoja1!$B$2:$C$260,2,FALSE) -> 2903003 | C5: BRAZUELO CHARQUEADO | D5: 0.20115887 | E5: 41.524 | F5: =VLOOKUP(B5,[2]Hoja1!$C$2:$E$279,3,FALSE) -> 11506.13 | G5: =F5*D5 -> 2314.5601 | H5: 14000 | I5: =H5*D5 -> 2816.2241 | J5: =((F5/H5)*100)-100 -> -17.813357 | K5: =$K$4*E5% -> 0.20115887
B6: =VLOOKUP(C6,[1]Hoja1!$B$2:$C$260,2,FALSE) -> 1141001 | C6: CARNE DE TERNERA | D6: 0.019435733 | E6: 4.012 | F6: =VLOOKUP(B6,[2]Hoja1!$C$2:$E$279,3,FALSE) -> 15597.29 | G6: =F6*D6 -> 303.14476 | H6: 15999.99 | I6: =H6*D6 -> 310.97153 | J6: =((F6/H6)*100)-100 -> -2.5168766 | K6: =$K$4*E6% -> 0.019435733
B7: =VLOOKUP(C7,[1]Hoja1!$B$2:$C$260,2,FALSE) -> 1131002 | C7: AGUA POTABLE | D7: 0.097178664 | E7: 20.06 | F7: =VLOOKUP(B7,[2]Hoja1!$C$2:$E$279,3,FALSE) -> 0 | G7: =F7*D7 -> 0 | H7: 0 | I7: =H7*D7 -> 0 | J7: =((F7/H7)*100)-100 -> #DIV/0! | K7: =$K$4*E7% -> 0.097178664
B8: =VLOOKUP(C8,[1]Hoja1!$B$2:$C$260,2,FALSE) -> 1230006 | C8: PREPARADO SABOR CHORIZO TERNERA | D8: 0.0092334264 | E8: 1.906 | F8: =VLOOKUP(B8,[2]Hoja1!$C$2:$E$279,3,FALSE) -> 44693.38 | G8: =F8*D8 -> 412.67303 | H8: 42594.15 | I8: =H8*D8 -> 393.28995 | J8: =((F8/H8)*100)-100 -> 4.9284467 | K8: =$K$4*E8% -> 0.0092334264
B9: =VLOOKUP(C9,[1]Hoja1!$B$2:$C$260,2,FALSE) -> 1210006 | C9: SAL REDUCIDA EN SODIO 60/40 | D9: 0.0070437576 | E9: 1.454 | F9: =VLOOKUP(B9,[2]Hoja1!$C$2:$E$279,3,FALSE) -> 8904.45 | G9: =F9*D9 -> 62.720787 | H9: 8910.1 | I9: =H9*D9 -> 62.760585 | J9: =((F9/H9)*100)-100 -> -0.063411185 | K9: =$K$4*E9% -> 0.0070437576
B10: =VLOOKUP(C10,[1]Hoja1!$B$2:$C$260,2,FALSE) -> 1210004 | C10: SAL CURANTE AL 12 % | D10: 0.000411774 | E10: 0.085 | F10: =VLOOKUP(B10,[2]Hoja1!$C$2:$E$279,3,FALSE) -> 3841 | G10: =F10*D10 -> 1.5816239 | H10: 3508.01 | I10: =H10*D10 -> 1.4445073 | J10: =((F10/H10)*100)-100 -> 9.4922762 | K10: =$K$4*E10% -> 0.000411774
B11: =VLOOKUP(C11,[1]Hoja1!$B$2:$C$260,2,FALSE) -> 121007 | C11: SUPRA MEAT F451 | D11: 0.0019426044 | E11: 0.401 | F11: =VLOOKUP(B11,[2]Hoja1!$C$2:$E$279,3,FALSE) -> 16905 | G11: =F11*D11 -> 32.839727 | H11: 16100 | I11: =H11*D11 -> 31.275931 | J11: =((F11/H11)*100)-100 -> 5 | K11: =$K$4*E11% -> 0.0019426044
B12: =VLOOKUP(C12,[1]Hoja1!$B$2:$C$260,2,FALSE) -> 1250003 | C12: COLOR NATURAL HEMOGLOBINA I RED | D12: 0.0003197304 | E12: 0.066 | F12: =VLOOKUP(B12,[2]Hoja1!$C$2:$E$279,3,FALSE) -> 50952.79 | G12: =F12*D12 -> 16.291156 | H12: 47385.41 | I12: =H12*D12 -> 15.150556 | J12: =((F12/H12)*100)-100 -> 7.5284354 | K12: =$K$4*E12% -> 0.0003197304
B13: =VLOOKUP(C13,[1]Hoja1!$B$2:$C$260,2,FALSE) -> 1250002 | C13: COLOR LOY NARANJA LIQ A10 1 | D13: 0.0008283924 | E13: 0.171 | F13: =VLOOKUP(B13,[2]Hoja1!$C$2:$E$279,3,FALSE) -> 44120.54 | G13: =F13*D13 -> 36.54912 | H13: 43034 | I13: =H13*D13 -> 35.649039 | J13: =((F13/H13)*100)-100 -> 2.5248408 | K13: =$K$4*E13% -> 0.0008283924
B14: =VLOOKUP(C14,[1]Hoja1!$B$2:$C$260,2,FALSE) -> 1260009 | C14: PROTEINA CONCENTRADA DE SOYA 70% | D14: 0.016034964 | E14: 3.31 | F14: =VLOOKUP(B14,[2]Hoja1!$C$2:$E$279,3,FALSE) -> 7033.69 | G14: =F14*D14 -> 112.78497 | H14: 9565.21 | I14: =H14*D14 -> 153.3778 | J14: =((F14/H14)*100)-100 -> -26.465911 | K14: =$K$4*E14% -> 0.016034964
B15: =VLOOKUP(C15,[1]Hoja1!$B$2:$C$260,2,FALSE) -> 1121009 | C15: TOCINO NACIONAL | D15: 0.1166144 | E15: 24.072 | F15: =VLOOKUP(B15,[2]Hoja1!$C$2:$E$279,3,FALSE) -> 8741.62 | G15: =F15*D15 -> 1019.3987 | H15: 8754.28 | I15: =H15*D15 -> 1020.8751 | J15: =((F15/H15)*100)-100 -> -0.14461498 | K15: =$K$4*E15% -> 0.1166144
B16: =VLOOKUP(C16,[1]Hoja1!$B$2:$C$260,2,FALSE) -> 1250005 | C16: COLOR NATURAL NARANJA RA 40-3 9827 | D16: 0.000629772 | E16: 0.13 | F16: =VLOOKUP(B16,[2]Hoja1!$C$2:$E$279,3,FALSE) -> 66921.05 | G16: =F16*D16 -> 42.145004 | H16: 62991.09 | I16: =H16*D16 -> 39.670025 | J16: =((F16/H16)*100)-100 -> 6.2389141 | K16: =$K$4*E16% -> 0.000629772
B17: =VLOOKUP(C17,[1]Hoja1!$B$2:$C$260,2,FALSE) -> 1260017 | C17: ALMIDON MODIFICADO DE MAIZ | D17: 0.013603075 | E17: 2.808 | F17: =VLOOKUP(B17,[2]Hoja1!$C$2:$E$279,3,FALSE) -> 4500 | G17: =F17*D17 -> 61.213838 | H17: 4500 | I17: =H17*D17 -> 61.213838 | J17: =((F17/H17)*100)-100 -> 0 | K17: =$K$4*E17% -> 0.013603075
F18: =VLOOKUP(B18,[2]Hoja1!$C$2:$E$279,3,FALSE) -> #N/A | G18: =F18*D18 -> #N/A | I18: =H18*D18 -> 0
B19: TOTAL | D19: =SUM(D5:D17) -> 0.48443516 | E19: =SUM(E5:E17) -> 99.999 | G19: =SUM(G5:G17) -> 4415.9028 | I19: =SUM(I5:I17) -> 4941.903 | J19: =((G19/I19)*100)-100 -> -10.643676
B21: MERMAS | D21: =+C24+(C24*C30%) -> 484.44
B22: Linea | C22: Picados
B23: Referencia | C23: Chorizo con Ternera
B24: Presentación en Gramos | C24: 440
B25: Máquina | C25: 0
B26: Cocción | C26: 6
B27: Frío | C27: 1
B28: Recorte | C28: 1
B29: Sobrepeso | C29: 2.1
B30: Merma Total | C30: =C29+C28+C27+C26 -> 10.1
B32: MATERIAL DE EMPAQUE
B33: CÓDIGO | C33: DESCRIPCIÓN | D33: CATIDAD | E33: =+'CIF Y PV'!$F$4 -> JUN-COP/UMB | F33: =+'CIF Y PV'!$G$4 -> JUN-COP/APP | G33: =+'CIF Y PV'!$H$4 -> MAY-COP/UMB | H33: =+'CIF Y PV'!$I$4 -> MAY-COP/APP | I33: % | J33: 3380
B34: =VLOOKUP(C34,[1]Hoja1!$B$2:$C$260,2,FALSE) -> 1370009 | C34: FUNDA COLAGENO ND 26/60 | D34: 1.2 | E34: =VLOOKUP(B34,[2]Hoja1!$C$2:$E$279,3,FALSE) -> 487.07 | F34: =E34*D34 -> 584.484 | G34: 504.87 | H34: =G34*D34 -> 605.844 | I34: =((E34/G34)*100)-100 -> -3.5256601 | J34: =$J$33*D34 -> 4056
B35: =VLOOKUP(C35,[1]Hoja1!$B$2:$C$260,2,FALSE) -> 1320005 | C35: LAM INFE SUDPACK GVP 130-323 MM | D35: 0.075 | E35: =VLOOKUP(B35,[2]Hoja1!$C$2:$E$279,3,FALSE) -> 740.21 | F35: =E35*D35 -> 55.51575 | G35: 828.94 | H35: =G35*D35 -> 62.1705 | I35: =((E35/G35)*100)-100 -> -10.704032 | J35: =$J$33*D35 -> 253.5
B36: =VLOOKUP(C36,[1]Hoja1!$B$2:$C$260,2,FALSE) -> 1310018 | C36: LAM SUP TRANS ECOWEB M/PAUV 42U 301MM | D36: 0.075 | E36: =VLOOKUP(B36,[2]Hoja1!$C$2:$E$279,3,FALSE) -> 478.26 | F36: =E36*D36 -> 35.8695 | G36: 889 | H36: =G36*D36 -> 66.675 | I36: =((E36/G36)*100)-100 -> -46.202475 | J36: =$J$33*D36 -> 253.5
B37: 1330011 | C37: ETI CHZO TERNERA 440 G X 8U - G.EXITO | D37: 1 | E37: =VLOOKUP(B37,[2]Hoja1!$C$2:$E$279,3,FALSE) -> 141.4 | F37: =E37*D37 -> 141.4
B38: =VLOOKUP(C38,[1]Hoja1!$B$2:$C$260,2,FALSE) -> 1330068 | C38: ETI RESPAL CHZO TERNERA 440 G 8 U EXITO | D38: 1 | E38: =VLOOKUP(B38,[2]Hoja1!$C$2:$E$279,3,FALSE) -> 77 | F38: =E38*D38 -> 77 | G38: 82.78 | H38: =G38*D38 -> 82.78 | I38: =((E38/G38)*100)-100 -> -6.9823629 | J38: =$J$33*D38 -> 3380
C39: TOTAL | F39: =SUM(F34:F38) -> 894.26925 | H39: =SUM(H34:H38) -> 817.4695 | I39: =((F39/H39)*100)-100 -> 9.3948153
H40: =+'CIF Y PV'!$G$1 -> MAYO
B41: TOTAL INSUMOS (UND 440 G) | H41: =+F39+G19 -> 5310.1721
B42: ASIGNACIÓN MOD/CIF | H42: =+('CIF Y PV'!C3/1000)*440 -> 831.6
B43: TOTAL COSTO POR UND (440) | H43: =+H41+H42 -> 6141.7721
B44: PRECIO DE VENTA | H44: ='CIF Y PV'!C12 -> 11131.21
B45: MB | H45: =+(H44-H43)/H44 -> 0.44823859

Sheet CHORIZO CON TERNERA 1100
B2: CHORIZO CON TERNERA X 1.100 G - 20 UNDS
L3: Batch
B4: CÓDIGO | C4: DESCRIPCIÓN | D4: CATIDAD | E4: % | F4: =+'CIF Y PV'!$F$2 -> JUN-COP/Kg | G4: =+'CIF Y PV'!$G$2 -> JUN-COP/APP | H4: =+'CIF Y PV'!$H$2 -> MAY-COP/Kg | I4: =+'CIF Y PV'!$I$2 -> MAY-COP/APP | J4: % | K4: =+D20/1000 -> 1.199 | L4: 498 | M4: Batch $$
B5: =VLOOKUP(C5,[1]Hoja1!$B$2:$C$260,2,FALSE) -> 2903003 | C5: BRAZUELO CHARQUEADO | D5: 0.49787276 | E5: 41.524 | F5: =VLOOKUP(B5,[2]Hoja1!$C$2:$E$279,3,FALSE) -> 11506.13 | G5: =F5*D5 -> 5728.5887 | H5: 14000 | I5: =H5*D5 -> 6970.2186 | J5: =((F5/H5)*100)-100 -> -17.813357 | K5: =$K$4*E5% -> 0.49787276 | L5: =$L$4*E5% -> 206.78952 | M5: =L5*F5 -> 2379347.1
B6: =VLOOKUP(C6,[1]Hoja1!$B$2:$C$260,2,FALSE) -> 1141001 | C6: CARNE DE TERNERA | D6: 0.04810388 | E6: 4.012 | F6: =VLOOKUP(B6,[2]Hoja1!$C$2:$E$279,3,FALSE) -> 15597.29 | G6: =F6*D6 -> 750.29017 | H6: 15999.99 | I6: =H6*D6 -> 769.6616 | J6: =((F6/H6)*100)-100 -> -2.5168766 | K6: =$K$4*E6% -> 0.04810388 | L6: =$L$4*E6% -> 19.97976 | M6: =L6*F6 -> 311630.11
B7: =VLOOKUP(C7,[1]Hoja1!$B$2:$C$260,2,FALSE) -> 1131002 | C7: AGUA POTABLE | D7: 0.2405194 | E7: 20.06 | F7: =VLOOKUP(B7,[2]Hoja1!$C$2:$E$279,3,FALSE) -> 0 | G7: =F7*D7 -> 0 | H7: 0 | I7: =H7*D7 -> 0 | J7: =((F7/H7)*100)-100 -> #DIV/0! | K7: =$K$4*E7% -> 0.2405194 | L7: =$L$4*E7% -> 99.8988 | M7: =L7*F7 -> 0
B8: =VLOOKUP(C8,[1]Hoja1!$B$2:$C$260,2,FALSE) -> 1230006 | C8: PREPARADO SABOR CHORIZO TERNERA | D8: 0.02285294 | E8: 1.906 | F8: =VLOOKUP(B8,[2]Hoja1!$C$2:$E$279,3,FALSE) -> 44693.38 | G8: =F8*D8 -> 1021.3751 | H8: 42594.15 | I8: =H8*D8 -> 973.40155 | J8: =((F8/H8)*100)-100 -> 4.9284467 | K8: =$K$4*E8% -> 0.02285294 | L8: =$L$4*E8% -> 9.49188 | M8: =L8*F8 -> 424224.2
B9: =VLOOKUP(C9,[1]Hoja1!$B$2:$C$260,2,FALSE) -> 1210006 | C9: SAL REDUCIDA EN SODIO 60/40 | D9: 0.01743346 | E9: 1.454 | F9: =VLOOKUP(B9,[2]Hoja1!$C$2:$E$279,3,FALSE) -> 8904.45 | G9: =F9*D9 -> 155.23537 | H9: 8910.1 | I9: =H9*D9 -> 155.33387 | J9: =((F9/H9)*100)-100 -> -0.063411185 | K9: =$K$4*E9% -> 0.01743346 | L9: =$L$4*E9% -> 7.24092 | M9: =L9*F9 -> 64476.41
B10: =VLOOKUP(C10,[1]Hoja1!$B$2:$C$260,2,FALSE) -> 1210004 | C10: SAL CURANTE AL 12 % | D10: 0.00101915 | E10: 0.085 | F10: =VLOOKUP(B10,[2]Hoja1!$C$2:$E$279,3,FALSE) -> 3841 | G10: =F10*D10 -> 3.9145552 | H10: 3508.01 | I10: =H10*D10 -> 3.5751884 | J10: =((F10/H10)*100)-100 -> 9.4922762 | K10: =$K$4*E10% -> 0.00101915 | L10: =$L$4*E10% -> 0.4233 | M10: =L10*F10 -> 1625.8953
B11: =VLOOKUP(C11,[1]Hoja1!$B$2:$C$260,2,FALSE) -> 121007 | C11: SUPRA MEAT F451 | D11: 0.00480799 | E11: 0.401 | F11: =VLOOKUP(B11,[2]Hoja1!$C$2:$E$279,3,FALSE) -> 16905 | G11: =F11*D11 -> 81.279071 | H11: 16100 | I11: =H11*D11 -> 77.408639 | J11: =((F11/H11)*100)-100 -> 5 | K11: =$K$4*E11% -> 0.00480799 | L11: =$L$4*E11% -> 1.99698 | M11: =L11*F11 -> 33758.947
B12: =VLOOKUP(C12,[1]Hoja1!$B$2:$C$260,2,FALSE) -> 1250003 | C12: COLOR NATURAL HEMOGLOBINA I RED | D12: 0.00079134 | E12: 0.066 | F12: =VLOOKUP(B12,[2]Hoja1!$C$2:$E$279,3,FALSE) -> 50952.79 | G12: =F12*D12 -> 40.320981 | H12: 47385.41 | I12: =H12*D12 -> 37.49797 | J12: =((F12/H12)*100)-100 -> 7.5284354 | K12: =$K$4*E12% -> 0.00079134 | L12: =$L$4*E12% -> 0.32868 | M12: =L12*F12 -> 16747.163
B13: =VLOOKUP(C13,[1]Hoja1!$B$2:$C$260,2,FALSE) -> 1250002 | C13: COLOR LOY NARANJA LIQ A10 1 | D13: 0.00205029 | E13: 0.171 | F13: =VLOOKUP(B13,[2]Hoja1!$C$2:$E$279,3,FALSE) -> 44120.54 | G13: =F13*D13 -> 90.459902 | H13: 43034 | I13: =H13*D13 -> 88.23218 | J13: =((F13/H13)*100)-100 -> 2.5248408 | K13: =$K$4*E13% -> 0.00205029 | L13: =$L$4*E13% -> 0.85158 | M13: =L13*F13 -> 37572.169
B14: =VLOOKUP(C14,[1]Hoja1!$B$2:$C$260,2,FALSE) -> 1260009 | C14: PROTEINA CONCENTRADA DE SOYA 70% | D14: 0.0396869 | E14: 3.31 | F14: =VLOOKUP(B14,[2]Hoja1!$C$2:$E$279,3,FALSE) -> 7033.69 | G14: =F14*D14 -> 279.14535 | H14: 9565.21 | I14: =H14*D14 -> 379.61353 | J14: =((F14/H14)*100)-100 -> -26.465911 | K14: =$K$4*E14% -> 0.0396869 | L14: =$L$4*E14% -> 16.4838 | M14: =L14*F14 -> 115941.94
B15: =VLOOKUP(C15,[1]Hoja1!$B$2:$C$260,2,FALSE) -> 1121009 | C15: TOCINO NACIONAL | D15: 0.28862328 | E15: 24.072 | F15: =VLOOKUP(B15,[2]Hoja1!$C$2:$E$279,3,FALSE) -> 8741.62 | G15: =F15*D15 -> 2523.035 | H15: 8754.28 | I15: =H15*D15 -> 2526.689 | J15: =((F15/H15)*100)-100 -> -0.14461498 | K15: =$K$4*E15% -> 0.28862328 | L15: =$L$4*E15% -> 119.87856 | M15: =L15*F15 -> 1047932.8
B16: =VLOOKUP(C16,[1]Hoja1!$B$2:$C$260,2,FALSE) -> 1250005 | C16: COLOR NATURAL NARANJA RA 40-3 9827 | D16: 0.0015587 | E16: 0.13 | F16: =VLOOKUP(B16,[2]Hoja1!$C$2:$E$279,3,FALSE) -> 66921.05 | G16: =F16*D16 -> 104.30984 | H16: 62991.09 | I16: =H16*D16 -> 98.184212 | J16: =((F16/H16)*100)-100 -> 6.2389141 | K16: =$K$4*E16% -> 0.0015587 | L16: =$L$4*E16% -> 0.6474 | M16: =L16*F16 -> 43324.688
B17: =VLOOKUP(C17,[1]Hoja1!$B$2:$C$260,2,FALSE) -> 1260017 | C17: ALMIDON MODIFICADO DE MAIZ | D17: 0.03366792 | E17: 2.808 | F17: =VLOOKUP(B17,[2]Hoja1!$C$2:$E$279,3,FALSE) -> 4500 | G17: =F17*D17 -> 151.50564 | H17: 4500 | I17: =H17*D17 -> 151.50564 | J17: =((F17/H17)*100)-100 -> 0 | K17: =$K$4*E17% -> 0.03366792 | L17: =$L$4*E17% -> 13.98384 | M17: =L17*F17 -> 62927.28
B18: TOTAL | D18: =SUM(D5:D17) -> 1.198988 | E18: =SUM(E5:E17) -> 99.999 | G18: =SUM(G5:G17) -> 10929.46 | I18: =SUM(I5:I17) -> 12231.322 | J18: =((G18/I18)*100)-100 -> -10.643676 | M18: =SUM(M5:M17) -> 4539508.7
B20: MERMAS | D20: =+C23+(C23*C29%) -> 1199
B21: Linea | C21: Picados
B22: Referencia | C22: Chorizo con Ternera
B23: Presentación en Gramos | C23: 1100
B24: Máquina | C24: 0
B25: Cocción | C25: 6
B26: Frío | C26: 1
B27: Recorte | C27: 1
B28: Sobrepeso | C28: 1
B29: Merma Total | C29: =C28+C27+C26+C25 -> 9
E30: =0.15*20 -> 3
B31: MATERIAL DE EMPAQUE
B32: CÓDIGO | C32: DESCRIPCIÓN | D32: CATIDAD | E32: =+'CIF Y PV'!$F$4 -> JUN-COP/UMB | F32: =+'CIF Y PV'!$G$4 -> JUN-COP/APP | G32: =+'CIF Y PV'!$H$4 -> MAY-COP/UMB | H32: =+'CIF Y PV'!$I$4 -> MAY-COP/APP | I32: % | J32: 1591
B33: 1370009 | C33: FUNDA COLAGENO ND 26/60 | D33: 3 | E33: =VLOOKUP(B33,[2]Hoja1!$C$2:$E$279,3,FALSE) -> 487.07 | F33: =E33*D33 -> 1461.21 | G33: 504.87 | H33: =G33*D33 -> 1514.61 | I33: =((E33/G33)*100)-100 -> -3.5256601 | J33: =J32*D33 -> 4773
B34: 1320005 | C34: LAM INFE SUDPACK GVP 130-323 MM | D34: 0.15 | E34: =VLOOKUP(B34,[2]Hoja1!$C$2:$E$279,3,FALSE) -> 740.21 | F34: =E34*D34 -> 111.0315 | G34: 828.94 | H34: =G34*D34 -> 124.341 | I34: =((E34/G34)*100)-100 -> -10.704032 | J34: =J32*D34 -> 238.65
B35: 1310018 | C35: LAM SUP TRANS ECOWEB M/PAUV 42U 301MM | D35: 0.15 | E35: =VLOOKUP(B35,[2]Hoja1!$C$2:$E$279,3,FALSE) -> 478.26 | F35: =E35*D35 -> 71.739 | G35: 889 | H35: =G35*D35 -> 133.35 | I35: =((E35/G35)*100)-100 -> -46.202475 | J35: =J32*D35 -> 238.65
B36: 1330002 | C36: ETI CHORIZO TERNERA X 120G X 2 UDS | D36: 1 | E36: =VLOOKUP(B36,[2]Hoja1!$C$2:$E$279,3,FALSE) -> 75 | F36: =E36*D36 -> 75
C37: TOTAL | F37: =SUM(F33:F36) -> 1718.9805 | H37: =SUM(H33:H35) -> 1772.301 | I37: =((F37/H37)*100)-100 -> -3.0085465
H38: =+'CIF Y PV'!$G$1 -> MAYO
B39: TOTAL INSUMOS (UND 1100 G) | H39: =+F37+G18 -> 12648.44
B40: ASIGNACIÓN MOD/CIF | H40: =+('CIF Y PV'!C3/1000)*1100 -> 2079
B41: TOTAL COSTO POR UND (1020) | H41: =+H39+H40 -> 14727.44
B42: PRECIO DE VENTA | H42: ='CIF Y PV'!C9 -> 26346.075
B43: MB | H43: =+(H42-H41)/H42 -> 0.4410006 | K43: =1-K42 -> 1
C45: Pasevilla-1724

Sheet CHORIZO DE CERDO 100 
B2: CHORIZO DE CERDO X 100 G - 2 UNDS
B4: CÓDIGO | C4: DESCRIPCIÓN | D4: CATIDAD | E4: % | F4: =+'CIF Y PV'!$F$2 -> JUN-COP/Kg | G4: =+'CIF Y PV'!$G$2 -> JUN-COP/APP | H4: =+'CIF Y PV'!$H$2 -> MAY-COP/Kg | I4: =+'CIF Y PV'!$I$2 -> MAY-COP/APP | J4: % | K4: =+D22/1000 -> 0.114 | L4: 300.278 | M4: Costo Batch
B5: =VLOOKUP(C5,[1]Hoja1!$B$2:$C$260,2,FALSE) -> 1122001 | C5: BRAZUELO DE CERDO NACIONAL | D5: 0.048594969 | E5: =(D5*100)/$D$20 -> 42.626434 | F5: =VLOOKUP(B5,[2]Hoja1!$C$2:$E$279,3,FALSE) -> 11506.13 | G5: =F5*D5 -> 559.14003 | H5: 14000 | I5: =H5*D5 -> 680.32956 | J5: =((F5/H5)*100)-100 -> -17.813357 | K5: =$K$4*E5% -> 0.048594135 | L5: =$L$4*E5% -> 127.9978 | M5: =L5*F5 -> 1472759.4
B6: =VLOOKUP(C6,[1]Hoja1!$B$2:$C$260,2,FALSE) -> 1121009 | C6: TOCINO NACIONAL | D6: 0.034168337 | E6: =(D6*100)/$D$20 -> 29.971711 | F6: =VLOOKUP(B6,[2]Hoja1!$C$2:$E$279,3,FALSE) -> 8741.62 | G6: =F6*D6 -> 298.68662 | H6: 8754.28 | I6: =H6*D6 -> 299.11919 | J6: =((F6/H6)*100)-100 -> -0.14461498 | K6: =$K$4*E6% -> 0.034167751 | L6: =$L$4*E6% -> 89.998456 | M6: =L6*F6 -> 786732.3
B7: =VLOOKUP(C7,[1]Hoja1!$B$2:$C$260,2,FALSE) -> 1131002 | C7: AGUA POTABLE | D7: 0.021260299 | E7: =(D7*100)/$D$20 -> 18.649065 | F7: =VLOOKUP(B7,[2]Hoja1!$C$2:$E$279,3,FALSE) -> 0 | G7: =F7*D7 -> 0 | H7: 0 | I7: =H7*D7 -> 0 | J7: =((F7/H7)*100)-100 -> #DIV/0! | K7: =$K$4*E7% -> 0.021259934 | L7: =$L$4*E7% -> 55.999039 | M7: =L7*F7 -> 0
B8: =VLOOKUP(C8,[1]Hoja1!$B$2:$C$260,2,FALSE) -> 1260009 | C8: PROTEINA CONCENTRADA DE SOYA 70% | D8: 0.0034168337 | E8: =(D8*100)/$D$20 -> 2.9971711 | F8: =VLOOKUP(B8,[2]Hoja1!$C$2:$E$279,3,FALSE) -> 7033.69 | G8: =F8*D8 -> 24.032949 | H8: 9565.21 | I8: =H8*D8 -> 32.682732 | J8: =((F8/H8)*100)-100 -> -26.465911 | K8: =$K$4*E8% -> 0.0034167751 | L8: =$L$4*E8% -> 8.9998456 | M8: =L8*F8 -> 63302.124
B9: =VLOOKUP(C9,[1]Hoja1!$B$2:$C$260,2,FALSE) -> 1230005 | C9: PREPARADO SABOR CHORIZO CERDO | D9: 0.0022778892 | E9: =(D9*100)/$D$20 -> 1.9981141 | F9: =VLOOKUP(B9,[2]Hoja1!$C$2:$E$279,3,FALSE) -> 45711.59 | G9: =F9*D9 -> 104.12594 | H9: 42915.05 | I9: =H9*D9 -> 97.755727 | J9: =((F9/H9)*100)-100 -> 6.5164552 | K9: =$K$4*E9% -> 0.0022778501 | L9: =$L$4*E9% -> 5.999897 | M9: =L9*F9 -> 274264.83
B10: =VLOOKUP(C10,[1]Hoja1!$B$2:$C$260,2,FALSE) -> 1260017 | C10: ALMIDON MODIFICADO DE MAIZ | D10: 0.0014426631 | E10: =(D10*100)/$D$20 -> 1.2654723 | F10: =VLOOKUP(B10,[2]Hoja1!$C$2:$E$279,3,FALSE) -> 4500 | G10: =F10*D10 -> 6.4919841 | H10: 4500 | I10: =H10*D10 -> 6.4919841 | J10: =((F10/H10)*100)-100 -> 0 | K10: =$K$4*E10% -> 0.0014426384 | L10: =$L$4*E10% -> 3.7999348 | M10: =L10*F10 -> 17099.707
B11: =VLOOKUP(C11,[1]Hoja1!$B$2:$C$260,2,FALSE) -> 1210005 | C11: SAL YODADA REFISAL | D11: 0.001197 | E11: 1.05 | F11: =VLOOKUP(B11,[2]Hoja1!$C$2:$E$279,3,FALSE) -> 1356 | G11: =F11*D11 -> 1.623132 | H11: 1360 | I11: =H11*D11 -> 1.62792 | J11: =((F11/H11)*100)-100 -> -0.29411765 | K11: =$K$4*E11% -> 0.001197 | L11: =$L$4*E11% -> 3.152919 | M11: =L11*F11 -> 4275.3582
B12: =VLOOKUP(C12,[1]Hoja1!$B$2:$C$260,2,FALSE) -> 121007 | C12: SUPRA MEAT F451 | D12: 0.00053150747 | E12: =(D12*100)/$D$20 -> 0.46622662 | F12: =VLOOKUP(B12,[2]Hoja1!$C$2:$E$279,3,FALSE) -> 16905 | G12: =F12*D12 -> 8.9851338 | H12: 16100 | I12: =H12*D12 -> 8.5572703 | J12: =((F12/H12)*100)-100 -> 5 | K12: =$K$4*E12% -> 0.00053149835 | L12: =$L$4*E12% -> 1.399976 | M12: =L12*F12 -> 23666.594
B13: =VLOOKUP(C13,[1]Hoja1!$B$2:$C$260,2,FALSE) -> 1220014 | C13: PVH LIQUIDA M 1222 | D13: 0.00051252506 | E13: =(D13*100)/$D$20 -> 0.44957567 | F13: =VLOOKUP(B13,[2]Hoja1!$C$2:$E$279,3,FALSE) -> 14060 | G13: =F13*D13 -> 7.2061023 | H13: 13300.01 | I13: =H13*D13 -> 6.8165884 | J13: =((F13/H13)*100)-100 -> 5.7142062 | K13: =$K$4*E13% -> 0.00051251627 | L13: =$L$4*E13% -> 1.3499768 | M13: =L13*F13 -> 18980.674
B14: =VLOOKUP(C14,[1]Hoja1!$B$2:$C$260,2,FALSE) -> 1210004 | C14: SAL CURANTE AL 12 % | D14: 9.576e-05 | E14: 0.084 | F14: =VLOOKUP(B14,[2]Hoja1!$C$2:$E$279,3,FALSE) -> 3841 | G14: =F14*D14 -> 0.36781416 | H14: 3508.01 | I14: =H14*D14 -> 0.33592704 | J14: =((F14/H14)*100)-100 -> 9.4922762 | K14: =$K$4*E14% -> 9.576e-05 | L14: =$L$4*E14% -> 0.25223352 | M14: =L14*F14 -> 968.82895
B15: =VLOOKUP(C15,[1]Hoja1!$B$2:$C$260,2,FALSE) -> 1250005 | C15: COLOR NATURAL NARANJA RA 40-3 9827 | D15: 0.00017122133 | E15: =(D15*100)/$D$20 -> 0.15019158 | F15: =VLOOKUP(B15,[2]Hoja1!$C$2:$E$279,3,FALSE) -> 66921.05 | G15: =F15*D15 -> 11.458312 | H15: 62991.09 | I15: =H15*D15 -> 10.785419 | J15: =((F15/H15)*100)-100 -> 6.2389141 | K15: =$K$4*E15% -> 0.0001712184 | L15: =$L$4*E15% -> 0.45099226 | M15: =L15*F15 -> 30180.876
B16: =VLOOKUP(C16,[1]Hoja1!$B$2:$C$260,2,FALSE) -> 1270004 | C16: HUMO TRUSMOKE OIL EX | D16: 0.00011920953 | E16: =(D16*100)/$D$20 -> 0.10456797 | F16: =VLOOKUP(B16,[2]Hoja1!$C$2:$E$279,3,FALSE) -> 50662 | G16: =F16*D16 -> 6.0393933 | H16: 53849.37 | I16: =H16*D16 -> 6.4193582 | J16: =((F16/H16)*100)-100 -> -5.9190479 | K16: =$K$4*E16% -> 0.00011920749 | L16: =$L$4*E16% -> 0.31399461 | M16: =L16*F16 -> 15907.595
B17: =VLOOKUP(C17,[1]Hoja1!$B$2:$C$260,2,FALSE) -> 1220001 | C17: SABOR CERDO COCIDO | D17: 0.00011389446 | E17: =(D17*100)/$D$20 -> 0.099905705 | F17: =VLOOKUP(B17,[2]Hoja1!$C$2:$E$279,3,FALSE) -> 85579.98 | G17: =F17*D17 -> 9.7470854 | H17: 81899.73 | I17: =H17*D17 -> 9.3279253 | J17: =((F17/H17)*100)-100 -> 4.4936046 | K17: =$K$4*E17% -> 0.0001138925 | L17: =$L$4*E17% -> 0.29999485 | M17: =L17*F17 -> 25673.553
B18: =VLOOKUP(C18,[1]Hoja1!$B$2:$C$260,2,FALSE) -> 1220005 | C18: AJO MOLIDO DESHIDRATADO B.1 | D18: 5.4289692e-05 | E18: =(D18*100)/$D$20 -> 0.047621719 | F18: =VLOOKUP(B18,[2]Hoja1!$C$2:$E$279,3,FALSE) -> 17429.99 | G18: =F18*D18 -> 0.94626878 | H18: 17430 | I18: =H18*D18 -> 0.94626932 | J18: =((F18/H18)*100)-100 -> -5.7372347e-05 | K18: =$K$4*E18% -> 5.428876e-05 | L18: =$L$4*E18% -> 0.14299755 | M18: =L18*F18 -> 2492.4458
B19: =VLOOKUP(C19,[1]Hoja1!$B$2:$C$260,2,FALSE) -> 1220008 | C19: COMINO MOLIDO B | D19: 4.5557783e-05 | E19: =(D19*100)/$D$20 -> 0.039962282 | F19: =VLOOKUP(B19,[2]Hoja1!$C$2:$E$279,3,FALSE) -> 50476.2 | G19: =F19*D19 -> 2.2995838 | H19: 48608.39 | I19: =H19*D19 -> 2.2144905 | J19: =((F19/H19)*100)-100 -> 3.8425671 | K19: =$K$4*E19% -> 4.5557001e-05 | L19: =$L$4*E19% -> 0.11999794 | M19: =L19*F19 -> 6057.0401
B20: TOTAL | D20: =SUM(D5:D19) -> 0.11400196 | E20: =SUM(E5:E19) -> 100.00002 | G20: =SUM(G5:G19) -> 1041.1503 | I20: =SUM(I5:I19) -> 1163.4104 | J20: =((G20/I20)*100)-100 -> -10.508762 | L20: =SUM(L5:L19) -> 300.27806 | M20: =SUM(M5:M19) -> 2742361.3
B22: MERMAS | D22: =+C25+(C25*C31%) -> 114
B23: Linea | C23: Picados
B24: Referencia | C24: Chorizo de Cerdo
B25: Presentación en Gramos | C25: 100
B26: Máquina | C26: 0
B27: Cocción | C27: 6
B28: Frío | C28: 2
B29: Recorte | C29: 2
B30: Sobrepeso | C30: 4
B31: Merma Total | C31: =C30+C29+C28+C27 -> 14
E32: 0.1513 | F32: =E32*2 -> 0.3026
B33: MATERIAL DE EMPAQUE
B34: CÓDIGO | C34: DESCRIPCIÓN | D34: CATIDAD | E34: =+'CIF Y PV'!$F$4 -> JUN-COP/UMB | F34: =+'CIF Y PV'!$G$4 -> JUN-COP/APP | G34: =+'CIF Y PV'!$H$4 -> MAY-COP/UMB | H34: =+'CIF Y PV'!$I$4 -> MAY-COP/APP | I34: % | J34: 1080
B35: =VLOOKUP(C35,[1]Hoja1!$B$2:$C$260,2,FALSE) -> 1370008 | C35: FUNDA COLAGENO NDXF 25/50 | D35: 0.302 | E35: =VLOOKUP(B35,[2]Hoja1!$C$2:$E$279,3,FALSE) -> 362.7 | F35: =E35*D35 -> 109.5354 | G35: 421.65 | H35: =G35*D35 -> 127.3383 | I35: =((E35/G35)*100)-100 -> -13.98079 | J35: =J34*D35 -> 326.16
B36: =VLOOKUP(C36,[1]Hoja1!$B$2:$C$260,2,FALSE) -> 1310056 | C36: LAM SUP CHZO CERDO 100 G X 2 U 302 MM | D36: 0.038 | E36: =VLOOKUP(B36,[2]Hoja1!$C$2:$E$279,3,FALSE) -> 889 | F36: =E36*D36 -> 33.782 | G36: 889 | H36: =G36*D36 -> 33.782 | I36: =((E36/G36)*100)-100 -> 0 | J36: =J34*D36 -> 41.04
B37: =VLOOKUP(C37,[1]Hoja1!$B$2:$C$260,2,FALSE) -> 1320005 | C37: LAM INFE SUDPACK GVP 130-323 MM | D37: 0.038 | E37: =VLOOKUP(B37,[2]Hoja1!$C$2:$E$279,3,FALSE) -> 740.21 | F37: =E37*D37 -> 28.12798 | G37: 828.94 | H37: =G37*D37 -> 31.49972 | I37: =((E37/G37)*100)-100 -> -10.704032 | J37: =J34*D37 -> 41.04
C38: TOTAL | F38: =SUM(F35:F37) -> 171.44538 | H38: =SUM(H35:H37) -> 192.62002 | I38: =((F38/H38)*100)-100 -> -10.992959
H39: =+'CIF Y PV'!$G$1 -> MAYO
B40: TOTAL INSUMOS (UND 100 G) | H40: =+G20+F38 -> 1212.5957
B41: ASIGNACIÓN MOD/CIF | H41: =+('CIF Y PV'!C3/1000)*100 -> 189
B42: TOTAL COSTO POR UND (100) | H42: =+H40+H41 -> 1401.5957
B43: PRECIO DE VENTA | H43: ='CIF Y PV'!C72 -> 2888.5
B44: MB | H44: =+(H43-H42)/H43 -> 0.51476693 | K44: =1-K43 -> 1

Sheet CHORIZO DE CERDO 250 FAZÁN
B2: CHORIZO DE CERDO X 250 G - 10 UNDS
B4: CÓDIGO | C4: DESCRIPCIÓN | D4: CATIDAD | E4: % | F4: =+'CIF Y PV'!$F$2 -> JUN-COP/Kg | G4: =+'CIF Y PV'!$G$2 -> JUN-COP/APP | H4: =+'CIF Y PV'!$H$2 -> MAY-COP/Kg | I4: =+'CIF Y PV'!$I$2 -> MAY-COP/APP | J4: % | K4: =+D22/1000 -> 0.285 | L4: 300.278 | M4: Costo Batch
B5: =VLOOKUP(C5,[1]Hoja1!$B$2:$C$260,2,FALSE) -> 2903003 | C5: BRAZUELO CHARQUEADO | D5: 0.12148742 | E5: =(D5*100)/$D$20 -> 42.627165 | F5: =VLOOKUP(B5,[2]Hoja1!$C$2:$E$279,3,FALSE) -> 11506.13 | G5: =F5*D5 -> 1397.8501 | H5: 14000 | I5: =H5*D5 -> 1700.8239 | J5: =((F5/H5)*100)-100 -> -17.813357 | K5: =$K$4*E5% -> 0.12148742 | L5: =$L$4*E5% -> 128 | M5: =L5*F5 -> 1472784.6
B6: =VLOOKUP(C6,[1]Hoja1!$B$2:$C$260,2,FALSE) -> 1121009 | C6: TOCINO NACIONAL | D6: 0.085420843 | E6: =(D6*100)/$D$20 -> 29.972226 | F6: =VLOOKUP(B6,[2]Hoja1!$C$2:$E$279,3,FALSE) -> 8741.62 | G6: =F6*D6 -> 746.71655 | H6: 8754.28 | I6: =H6*D6 -> 747.79798 | J6: =((F6/H6)*100)-100 -> -0.14461498 | K6: =$K$4*E6% -> 0.085420843 | L6: =$L$4*E6% -> 90 | M6: =L6*F6 -> 786745.8
B7: =VLOOKUP(C7,[1]Hoja1!$B$2:$C$260,2,FALSE) -> 1131002 | C7: AGUA POTABLE | D7: 0.053150747 | E7: =(D7*100)/$D$20 -> 18.649385 | F7: =VLOOKUP(B7,[2]Hoja1!$C$2:$E$279,3,FALSE) -> 0 | G7: =F7*D7 -> 0 | H7: 0 | I7: =H7*D7 -> 0 | J7: =((F7/H7)*100)-100 -> #DIV/0! | K7: =$K$4*E7% -> 0.053150747 | L7: =$L$4*E7% -> 56 | M7: =L7*F7 -> 0
B8: =VLOOKUP(C8,[1]Hoja1!$B$2:$C$260,2,FALSE) -> 1260009 | C8: PROTEINA CONCENTRADA DE SOYA 70% | D8: 0.0085420843 | E8: =(D8*100)/$D$20 -> 2.9972226 | F8: =VLOOKUP(B8,[2]Hoja1!$C$2:$E$279,3,FALSE) -> 7033.69 | G8: =F8*D8 -> 60.082373 | H8: 9565.21 | I8: =H8*D8 -> 81.706831 | J8: =((F8/H8)*100)-100 -> -26.465911 | K8: =$K$4*E8% -> 0.0085420843 | L8: =$L$4*E8% -> 9 | M8: =L8*F8 -> 63303.21
